Workbook

Sheet Legend
A1: FuelSphere - Fuel Data Model Test Scenarios
A2: Test data covering flight operations, flight dispatch fuel plan, fuel order and fuel ticket
A5: SHEET | B5: PURPOSE
A6: Test Scenarios | B6: Master list of test cases with trigger, expected system behaviour and validation focus
A7: FLIGHT_OPERATIONS | B7: Flight leg master. One row per operating leg. Parent of all fuel records
A8: FD_FUEL_PLAN | B8: Flight dispatch fuel plan. One row per plan VERSION. Never updated in place
A9: FUEL_ORDER | B9: Order placed to the into-plane supplier. Derived from a plan version
A10: FUEL_TICKET | B10: Physical fuel event record. Uplift, defuel or jettison
A11: FUEL_INVOICE | B11: Supplier invoice header including the posting lifecycle
A12: FUEL_INVOICE_LINE | B12: One billed uplift. Completes the three way match
A13: FUEL_PARAMETER | B13: Configuration. Tolerances, conversion density, density limits
A14: FUEL_PARAMETER_APPLIED | B14: Immutable record of which config row applied to a transaction
A15: APPLICATION_LOG | B15: Posting attempts, errors and warnings. Source for the error screens
A16: AI_SETTING | B16: AI provider, limits and governance so features bind to the organisation ecosystem
... A53: PAID | B53: Payment settled in the finance system

Sheet Test Scenarios
A1: Test Scenario Catalogue
A2: TC_ID | B2: Scenario | C2: Category | D2: Trigger | E2: Expected System Behaviour | F2: Primary Validation Focus
A3: TC01 | B3: Baseline single uplift | C3: Happy path | D3: Flight planned, fuelled and departed with no change | E3: One plan version, one order, one ticket. Ticket matched to order and plan | F3: 1:1:1 linkage; variance within meter tolerance
A4: TC02 | B4: Plan update before fuelling | C4: Re-plan | D4: Payload increase raises ZFW before the bowser connects | E4: New plan version created. Existing order amended to v2. Single ticket against amended order | F4: Order versioning; plan v1 marked SUPERSEDED; no orphan ticket
A5: TC03 | B5: Plan update after fuelling | C5: Re-plan | D5: ATC reroute after uplift completed | E5: New plan version. Required uplift computed as delta against actual FOB, not arrival FOB. Separate TOP_UP order and second ticket | F5: required_uplift = block_fuel - actual FOB including prior tickets
A6: TC04 | B6: Tail swap after fuelling | C6: Disruption | D6: Original tail goes tech after uplift; flight moved to another registration | E6: New plan version with new registration. First ticket stays valid but unlinked from the leg. Second order and ticket against the new tail | F6: Ticket keyed to registration not flight; orphan ticket retained not deleted
A7: TC05 | B7: Multiple tickets per order | C7: Multi-ticket | D7: Widebody uplift exceeds single bowser capacity | E7: One order, two tickets with uplift_sequence 1 and 2. Order delivered quantity is the SUM of tickets | F7: Order rollup summed from tickets, never stored as a scalar
A8: TC06 | B8: Interrupted fuelling | C8: Multi-ticket | D8: Fuelling stopped mid-uplift when alternate changed, resumed under a new order | E8: First order shows PART_FULFILLED with under-delivery. New order covers the balance | F8: Under-delivery flagged with a reason code, not treated as supplier shortfall
A9: TC07 | B9: Cancelled flight after fuelling | C9: Disruption | D9: Flight cancelled after fuel already delivered | E9: Leg status CANCELLED. Ticket remains valid and billable. Cost allocated to aircraft not flight leg | F9: cost_allocation_basis populated; ticket not orphaned or voided
A10: TC08 | B10: Return to ramp with defuel | C10: Return | D10: Aircraft returns to stand before takeoff; replacement routing is shorter | E10: New plan version. DEFUEL event recorded as a negative quantity ticket | F10: Negative quantity accepted; FOB delta negative and consistent
A11: TC09 | B11: Air return with jettison | C11: Return | D11: Aircraft returns to departure station airborne and jettisons fuel to reach MLW | E11: JETTISON event recorded with quantity from FQIS and no meter reading or density | F11: Non-metered event supported; burn variance not inflated by unrecorded jettison
A12: TC10 | B12: Ticket with no order | C12: Exception | D12: Post-freeze top-up requested verbally at the aircraft | E12: Ticket created with null fuel_order_id and match_status UNMATCHED, pending reconciliation | F12: Nullable FK; ticket not rejected at ingestion
A13: TC11 | B13: Captain discretionary fuel | C13: Re-plan | D13: Commander requests extra fuel for expected holding at destination | E13: New plan version with extra_fuel populated and a discretionary reason code | F13: extra_fuel separated from additional_fuel; reason code captured
... A159: TC67 | B159: Delta sequence gap detected | C159: Interface | D159: Intraday delta stream skips a sequence number | E159: Gap raised on the run. Snapshot run resets the expected sequence position | F159: Gap detection scoped to the delta stream only

Sheet FLIGHT_OPERATIONS
A1: FLIGHT_OPERATIONS - PK flight_leg_id | UK airline_code + flight_number + sched_dep_date_utc + leg_sequence | OOOI, stand, weight and payload fields feed burn derivation and variance analysis
A2: TC_ID | B2: flight_leg_id | C2: airline_code | D2: flight_number | E2: sched_dep_date_utc | F2: leg_sequence | G2: operating_carrier | H2: marketing_carrier | I2: codeshare_numbers | J2: service_type | K2: flight_nature | L2: departure_station | M2: arrival_station | N2: sched_dep_station | O2: sched_arr_station | P2: route_sequence | Q2: is_multi_leg | R2: std_utc | S2: sta_utc | T2: etd_utc | U2: eta_utc | V2: out_utc | W2: off_utc | X2: on_utc | Y2: in_utc | Z2: block_minutes | AA2: flight_minutes | AB2: taxi_out_minutes | AC2: taxi_in_minutes | AD2: aircraft_type_id | AE2: aircraft_config_id | AF2: planned_registration | AG2: actual_registration | AH2: tail_change_flag | AI2: dep_stand | AJ2: dep_stand_type | AK2: arr_stand | AL2: arr_stand_type | AM2: dep_runway | AN2: arr_runway | AO2: flight_status | AP2: ops_phase | AQ2: return_type | AR2: status_reason | AS2: status_updated_utc | AT2: sync_status | AU2: pending_field_summary | AV2: delay_code | AW2: delay_minutes | AX2: diversion_station | AY2: cancellation_reason | AZ2: pax_booked | BA2: pax_actual | BB2: cargo_kg | BC2: mail_kg | BD2: bag_kg | BE2: actual_zfw_kg | BF2: actual_tow_kg | BG2: actual_lw_kg | BH2: loadsheet_ref | BI2: cruise_level_planned | BJ2: cruise_level_flown | BK2: alternate_planned | BL2: alternate_used | BM2: single_engine_taxi_flag | BN2: deicing_flag | BO2: apu_reported_flag | BP2: fuel_processing_mode | BQ2: resolved_arrangement_id | BR2: provisional_tail_flag | BS2: fuel_reconciled_flag | BT2: burn_capture_status
A3: TC01 | B3: LEG-26081401 | C3: PR | D3: 0126 | E3: 2026-08-14 | F3: 1 | G3: PR | H3: PR | J3: J | K3: REVENUE | L3: MNL | M3: SIN | N3: MNL | O3: SIN | P3: 1 | Q3: N | R3: 46248.25 | S3: 46248.41 | V3: 46248.253 | W3: 46248.263 | X3: 46248.401 | Y3: 46248.411 | Z3: =IF(OR(V3="",Y3=""),"",ROUND((Y3-V3)*1440,0)) -> 228 | AA3: =IF(OR(W3="",X3=""),"",ROUND((X3-W3)*1440,0)) -> 199 | AB3: =IF(OR(V3="",W3=""),"",ROUND((W3-V3)*1440,0)) -> 15 | AC3: =IF(OR(X3="",Y3=""),"",ROUND((Y3-X3)*1440,0)) -> 14 | AD3: A321 | AF3: RP-C4108 | AG3: RP-C4108 | AH3: N | AI3: S12 | AJ3: CONTACT | AK3: B04 | AL3: CONTACT | AO3: ARRIVED | AP3: ON_BLOCKS | AT3: CURRENT | AW3: =IF(OR(V3="",R3=""),"",ROUND((V3-R3)*1440,0)) -> 4 | AZ3: 168 | BA3: 161 | BB3: 4200 | BC3: 0 | BD3: 0 | BE3: 68400 | BF3: 79651 | BG3: 71231 | BH3: LS-081401 | BI3: 350 | BJ3: 350 | BK3: WSSS | BL3: WSSS | BM3: Y | BN3: N | BO3: Y | BP3: FULL | BQ3: CAR-01 | BR3: N | BS3: Y | BT3: COMPLETE
A4: TC02 | B4: LEG-26081402 | C4: PR | D4: 0128 | E4: 2026-08-14 | F4: 1 | G4: PR | H4: PR | J4: J | K4: REVENUE | L4: MNL | M4: SIN | N4: MNL | O4: SIN | P4: 1 | Q4: N | R4: 46248.458 | S4: 46248.618 | V4: 46248.467 | W4: 46248.478 | X4: 46248.612 | Y4: 46248.622 | Z4: =IF(OR(V4="",Y4=""),"",ROUND((Y4-V4)*1440,0)) -> 223 | AA4: =IF(OR(W4="",X4=""),"",ROUND((X4-W4)*1440,0)) -> 192 | AB4: =IF(OR(V4="",W4=""),"",ROUND((W4-V4)*1440,0)) -> 17 | AC4: =IF(OR(X4="",Y4=""),"",ROUND((Y4-X4)*1440,0)) -> 14 | AD4: A321 | AF4: RP-C4110 | AG4: RP-C4110 | AH4: N | AI4: S14 | AJ4: CONTACT | AK4: B07 | AL4: CONTACT | AO4: ARRIVED | AP4: ON_BLOCKS | AT4: CURRENT | AW4: =IF(OR(V4="",R4=""),"",ROUND((V4-R4)*1440,0)) -> 12 | AZ4: 180 | BA4: 177 | BB4: 5100 | BC4: 0 | BD4: 0 | BE4: 71200 | BF4: 82735 | BG4: 74045 | BH4: LS-081402 | BI4: 350 | BJ4: 370 | BK4: WSSS | BL4: WSSS | BM4: Y | BN4: N | BO4: Y | BP4: FULL | BQ4: CAR-01 | BR4: N | BS4: Y | BT4: PARTIAL
A5: TC03 | B5: LEG-26081403 | C5: PR | D5: 0130 | E5: 2026-08-14 | F5: 1 | G5: PR | H5: PR | J5: J | K5: REVENUE | L5: MNL | M5: SIN | N5: MNL | O5: SIN | P5: 1 | Q5: N | R5: 46248.625 | S5: 46248.785 | V5: 46248.653 | W5: 46248.665 | X5: 46248.8 | Y5: 46248.81 | Z5: =IF(OR(V5="",Y5=""),"",ROUND((Y5-V5)*1440,0)) -> 225 | AA5: =IF(OR(W5="",X5=""),"",ROUND((X5-W5)*1440,0)) -> 194 | AB5: =IF(OR(V5="",W5=""),"",ROUND((W5-V5)*1440,0)) -> 17 | AC5: =IF(OR(X5="",Y5=""),"",ROUND((Y5-X5)*1440,0)) -> 14 | AD5: A321 | AF5: RP-C4112 | AG5: RP-C4112 | AH5: N | AI5: S09 | AJ5: CONTACT | AK5: B02 | AL5: CONTACT | AO5: ARRIVED | AP5: ON_BLOCKS | AT5: CURRENT | AV5: 81 | AW5: =IF(OR(V5="",R5=""),"",ROUND((V5-R5)*1440,0)) -> 41 | AZ5: 172 | BA5: 170 | BB5: 4600 | BC5: 0 | BD5: 0 | BE5: 69100 | BF5: 81387 | BG5: 71987 | BH5: LS-081403 | BI5: 350 | BJ5: 330 | BK5: WSSS | BL5: WSSS | BM5: N | BN5: N | BO5: Y | BP5: FULL | BQ5: CAR-01 | BR5: N | BS5: Y | BT5: PARTIAL
A6: TC04 | B6: LEG-26081404 | C6: PR | D6: 0132 | E6: 2026-08-14 | F6: 1 | G6: PR | H6: PR | J6: J | K6: REVENUE | L6: MNL | M6: SIN | N6: MNL | O6: SIN | P6: 1 | Q6: N | R6: 46248.75 | S6: 46248.91 | V6: 46248.788 | W6: 46248.799 | X6: 46248.937 | Y6: 46248.947 | Z6: =IF(OR(V6="",Y6=""),"",ROUND((Y6-V6)*1440,0)) -> 229 | AA6: =IF(OR(W6="",X6=""),"",ROUND((X6-W6)*1440,0)) -> 198 | AB6: =IF(OR(V6="",W6=""),"",ROUND((W6-V6)*1440,0)) -> 16 | AC6: =IF(OR(X6="",Y6=""),"",ROUND((Y6-X6)*1440,0)) -> 15 | AD6: A321 | AF6: RP-C4108 | AG6: RP-C4109 | AH6: Y | AI6: S11 | AJ6: CONTACT | AK6: B09 | AL6: CONTACT | AO6: ARRIVED | AP6: ON_BLOCKS | AR6: TAIL_SWAP | AT6: CURRENT | AV6: 41 | AW6: =IF(OR(V6="",R6=""),"",ROUND((V6-R6)*1440,0)) -> 55 | AZ6: 166 | BA6: 158 | BB6: 3900 | BC6: 0 | BD6: 0 | BE6: 67800 | BF6: 79446 | BG6: 70936 | BH6: LS-081404 | BI6: 350 | BJ6: 350 | BK6: WSSS | BL6: WSSS | BM6: Y | BN6: N | BO6: Y | BP6: FULL | BQ6: CAR-01 | BR6: N | BS6: Y | BT6: COMPLETE
A7: TC05 | B7: LEG-26081405 | C7: PR | D7: 0102 | E7: 2026-08-14 | F7: 1 | G7: PR | H7: PR | I7: KE7702 | J7: J | K7: REVENUE | L7: MNL | M7: LAX | N7: MNL | O7: LAX | P7: 1 | Q7: N | R7: 46248.556 | S7: 46249.045 | V7: 46248.56 | W7: 46248.572 | X7: 46249.035 | Y7: 46249.045 | Z7: =IF(OR(V7="",Y7=""),"",ROUND((Y7-V7)*1440,0)) -> 699 | AA7: =IF(OR(W7="",X7=""),"",ROUND((X7-W7)*1440,0)) -> 667 | AB7: =IF(OR(V7="",W7=""),"",ROUND((W7-V7)*1440,0)) -> 18 | AC7: =IF(OR(X7="",Y7=""),"",ROUND((Y7-X7)*1440,0)) -> 14 | AD7: A350-900 | AF7: RP-C3505 | AG7: RP-C3505 | AH7: N | AI7: S22 | AJ7: CONTACT | AK7: T148 | AL7: CONTACT | AO7: ARRIVED | AP7: ON_BLOCKS | AT7: CURRENT | AW7: =IF(OR(V7="",R7=""),"",ROUND((V7-R7)*1440,0)) -> 6 | AZ7: 289 | BA7: 281 | BB7: 18400 | BC7: 0 | BD7: 0 | BE7: 178300 | BF7: 283692 | BG7: 187292 | BH7: LS-081405 | BI7: 340 | BJ7: 360 | BK7: KSFO | BL7: KSFO | BM7: Y | BN7: N | BO7: Y | BP7: FULL | BQ7: CAR-01 | BR7: N | BS7: Y | BT7: COMPLETE
A8: TC06 | B8: LEG-26081406 | C8: PR | D8: 0104 | E8: 2026-08-15 | F8: 1 | G8: PR | H8: PR | J8: J | K8: REVENUE | L8: MNL | M8: LAX | N8: MNL | O8: LAX | P8: 1 | Q8: N | R8: 46249.556 | S8: 46250.045 | V8: 46249.582 | W8: 46249.594 | X8: 46250.057 | Y8: 46250.067 | Z8: =IF(OR(V8="",Y8=""),"",ROUND((Y8-V8)*1440,0)) -> 698 | AA8: =IF(OR(W8="",X8=""),"",ROUND((X8-W8)*1440,0)) -> 666 | AB8: =IF(OR(V8="",W8=""),"",ROUND((W8-V8)*1440,0)) -> 18 | AC8: =IF(OR(X8="",Y8=""),"",ROUND((Y8-X8)*1440,0)) -> 14 | AD8: A350-900 | AF8: RP-C3507 | AG8: RP-C3507 | AH8: N | AI8: S22 | AJ8: CONTACT | AK8: T148 | AL8: CONTACT | AO8: ARRIVED | AP8: ON_BLOCKS | AT8: CURRENT | AV8: 89 | AW8: =IF(OR(V8="",R8=""),"",ROUND((V8-R8)*1440,0)) -> 38 | AZ8: 291 | BA8: 288 | BB8: 19100 | BC8: 0 | BD8: 0 | BE8: 179000 | BF8: 287142 | BG8: 187942 | BH8: LS-081406 | BI8: 340 | BJ8: 340 | BK8: KSFO | BL8: KSFO | BM8: Y | BN8: N | BO8: Y | BP8: FULL | BQ8: CAR-01 | BR8: N | BS8: Y | BT8: COMPLETE
A9: TC07 | B9: LEG-26081407 | C9: PR | D9: 0134 | E9: 2026-08-15 | F9: 1 | G9: PR | H9: PR | J9: J | K9: REVENUE | L9: MNL | M9: SIN | N9: MNL | O9: SIN | P9: 1 | Q9: N | R9: 46249.25 | S9: 46249.41 | Z9: =IF(OR(V9="",Y9=""),"",ROUND((Y9-V9)*1440,0)) | AA9: =IF(OR(W9="",X9=""),"",ROUND((X9-W9)*1440,0)) | AB9: =IF(OR(V9="",W9=""),"",ROUND((W9-V9)*1440,0)) | AC9: =IF(OR(X9="",Y9=""),"",ROUND((Y9-X9)*1440,0)) | AD9: A321 | AF9: RP-C4114 | AG9: RP-C4114 | AH9: N | AI9: S07 | AJ9: CONTACT | AO9: CANCELLED | AP9: NOT_STARTED | AR9: TECHNICAL | AT9: CURRENT | AV9: 41 | AW9: =IF(OR(V9="",R9=""),"",ROUND((V9-R9)*1440,0)) | AY9: TECHNICAL | AZ9: 165 | BA9: 0 | BB9: 0 | BC9: 0 | BD9: 0 | BH9: LS-081407 | BI9: 350 | BK9: WSSS | BM9: N | BN9: N | BO9: Y | BP9: FULL | BQ9: CAR-01 | BR9: N | BS9: N | BT9: NOT_CAPTURED
A10: TC08 | B10: LEG-26081408 | C10: PR | D10: 0136 | E10: 2026-08-15 | F10: 1 | G10: PR | H10: PR | J10: J | K10: REVENUE | L10: MNL | M10: SIN | N10: MNL | O10: SIN | P10: 1 | Q10: N | R10: 46249.458 | S10: 46249.618 | V10: 46249.464 | Y10: 46249.494 | Z10: =IF(OR(V10="",Y10=""),"",ROUND((Y10-V10)*1440,0)) -> 44 | AA10: =IF(OR(W10="",X10=""),"",ROUND((X10-W10)*1440,0)) | AB10: =IF(OR(V10="",W10=""),"",ROUND((W10-V10)*1440,0)) | AC10: =IF(OR(X10="",Y10=""),"",ROUND((Y10-X10)*1440,0)) | AD10: A321 | AF10: RP-C4116 | AG10: RP-C4116 | AH10: N | AI10: S16 | AJ10: CONTACT | AK10: S16 | AL10: CONTACT | AO10: RETURN_TO_RAMP | AP10: ON_BLOCKS | AQ10: RAMP | AR10: TECHNICAL | AT10: CURRENT | AV10: 41 | AW10: =IF(OR(V10="",R10=""),"",ROUND((V10-R10)*1440,0)) -> 8 | AZ10: 174 | BA10: 171 | BB10: 4400 | BC10: 0 | BD10: 0 | BE10: 70200 | BF10: 81451 | BH10: LS-081408 | BI10: 350 | BK10: WSSS | BM10: N | BN10: N | BO10: Y | BP10: FULL | BQ10: CAR-01 | BR10: N | BS10: Y | BT10: PARTIAL
A11: TC09 | B11: LEG-26081409 | C11: PR | D11: 0106 | E11: 2026-08-15 | F11: 1 | G11: PR | H11: PR | J11: J | K11: REVENUE | L11: MNL | M11: LAX | N11: MNL | O11: LAX | P11: 1 | Q11: N | R11: 46249.556 | S11: 46250.045 | V11: 46249.558 | W11: 46249.57 | X11: 46249.606 | Y11: 46249.616 | Z11: =IF(OR(V11="",Y11=""),"",ROUND((Y11-V11)*1440,0)) -> 83 | AA11: =IF(OR(W11="",X11=""),"",ROUND((X11-W11)*1440,0)) -> 51 | AB11: =IF(OR(V11="",W11=""),"",ROUND((W11-V11)*1440,0)) -> 17 | AC11: =IF(OR(X11="",Y11=""),"",ROUND((Y11-X11)*1440,0)) -> 15 | AD11: A350-900 | AF11: RP-C3509 | AG11: RP-C3509 | AH11: N | AI11: S24 | AJ11: CONTACT | AK11: S24 | AL11: CONTACT | AO11: AIR_RETURN | AP11: ON_BLOCKS | AQ11: AIR | AR11: MEDICAL | AT11: CURRENT | AV11: 63 | AW11: =IF(OR(V11="",R11=""),"",ROUND((V11-R11)*1440,0)) -> 4 | AZ11: 286 | BA11: 279 | BB11: 17800 | BC11: 0 | BD11: 0 | BE11: 177600 | BF11: 283592 | BG11: 207000 | BH11: LS-081409 | BI11: 340 | BJ11: 260 | BK11: KSFO | BL11: RPLL | BM11: Y | BN11: N | BO11: Y | BP11: FULL | BQ11: CAR-01 | BR11: N | BS11: Y | BT11: COMPLETE
A12: TC10 | B12: LEG-26081410 | C12: PR | D12: 0138 | E12: 2026-08-16 | F12: 1 | G12: PR | H12: PR | J12: J | K12: REVENUE | L12: MNL | M12: SIN | N12: MNL | O12: SIN | P12: 1 | Q12: N | R12: 46250.25 | S12: 46250.41 | V12: 46250.262 | W12: 46250.274 | X12: 46250.411 | Y12: 46250.422 | Z12: =IF(OR(V12="",Y12=""),"",ROUND((Y12-V12)*1440,0)) -> 229 | AA12: =IF(OR(W12="",X12=""),"",ROUND((X12-W12)*1440,0)) -> 197 | AB12: =IF(OR(V12="",W12=""),"",ROUND((W12-V12)*1440,0)) -> 17 | AC12: =IF(OR(X12="",Y12=""),"",ROUND((Y12-X12)*1440,0)) -> 15 | AD12: A321 | AF12: RP-C4118 | AG12: RP-C4118 | AH12: N | AI12: S12 | AJ12: CONTACT | AK12: B04 | AL12: CONTACT | AO12: ARRIVED | AP12: ON_BLOCKS | AT12: CURRENT | AW12: =IF(OR(V12="",R12=""),"",ROUND((V12-R12)*1440,0)) -> 18 | AZ12: 169 | BA12: 164 | BB12: 4300 | BC12: 0 | BD12: 0 | BE12: 68600 | BF12: 80486 | BG12: 71286 | BH12: LS-081410 | BI12: 350 | BJ12: 350 | BK12: WSSS | BL12: WSSS | BM12: Y | BN12: N | BO12: Y | BP12: FULL | BQ12: CAR-01 | BR12: N | BS12: N | BT12: PARTIAL
A13: TC11 | B13: LEG-26081411 | C13: PR | D13: 0140 | E13: 2026-08-16 | F13: 1 | G13: PR | H13: PR | J13: J | K13: REVENUE | L13: MNL | M13: SIN | N13: MNL | O13: SIN | P13: 1 | Q13: N | R13: 46250.458 | S13: 46250.618 | V13: 46250.46 | W13: 46250.472 | X13: 46250.61 | Y13: 46250.619 | Z13: =IF(OR(V13="",Y13=""),"",ROUND((Y13-V13)*1440,0)) -> 229 | AA13: =IF(OR(W13="",X13=""),"",ROUND((X13-W13)*1440,0)) -> 198 | AB13: =IF(OR(V13="",W13=""),"",ROUND((W13-V13)*1440,0)) -> 17 | AC13: =IF(OR(X13="",Y13=""),"",ROUND((Y13-X13)*1440,0)) -> 14 | AD13: A321 | AF13: RP-C4120 | AG13: RP-C4120 | AH13: N | AI13: S14 | AJ13: CONTACT | AK13: B07 | AL13: CONTACT | AO13: ARRIVED | AP13: ON_BLOCKS | AT13: CURRENT | AW13: =IF(OR(V13="",R13=""),"",ROUND((V13-R13)*1440,0)) -> 3 | AZ13: 171 | BA13: 168 | BB13: 4500 | BC13: 0 | BD13: 0 | BE13: 68900 | BF13: 81051 | BG13: 71551 | BH13: LS-081411 | BI13: 350 | BJ13: 350 | BK13: WSSS | BL13: WSSS | BM13: Y | BN13: N | BO13: Y | BP13: FULL | BQ13: CAR-01 | BR13: N | BS13: Y | BT13: ESTIMATED
A14: TC12 | B14: LEG-26081412 | C14: PR | D14: 0142 | E14: 2026-08-16 | F14: 1 | G14: PR | H14: PR | J14: J | K14: REVENUE | L14: MNL | M14: SIN | N14: MNL | O14: SIN | P14: 1 | Q14: N | R14: 46250.625 | S14: 46250.785 | V14: 46250.628 | W14: 46250.64 | X14: 46250.778 | Y14: 46250.788 | Z14: =IF(OR(V14="",Y14=""),"",ROUND((Y14-V14)*1440,0)) -> 230 | AA14: =IF(OR(W14="",X14=""),"",ROUND((X14-W14)*1440,0)) -> 199 | AB14: =IF(OR(V14="",W14=""),"",ROUND((W14-V14)*1440,0)) -> 17 | AC14: =IF(OR(X14="",Y14=""),"",ROUND((Y14-X14)*1440,0)) -> 14 | AD14: A321 | AF14: RP-C4122 | AG14: RP-C4122 | AH14: N | AI14: S09 | AJ14: CONTACT | AK14: B02 | AL14: CONTACT | AO14: ARRIVED | AP14: ON_BLOCKS | AT14: CURRENT | AW14: =IF(OR(V14="",R14=""),"",ROUND((V14-R14)*1440,0)) -> 5 | AZ14: 176 | BA14: 173 | BB14: 4800 | BC14: 0 | BD14: 0 | BE14: 69800 | BF14: 81190 | BG14: 71690 | BH14: LS-081412 | BI14: 350 | BJ14: 350 | BK14: WSSS | BL14: WSSS | BM14: Y | BN14: N | BO14: Y | BP14: FULL | BQ14: CAR-01 | BR14: N | BS14: Y | BT14: COMPLETE
A15: TC13 | B15: LEG-26081413 | C15: PR | D15: 0108 | E15: 2026-08-16 | F15: 1 | G15: PR | H15: PR | J15: J | K15: REVENUE | L15: MNL | M15: LAX | N15: MNL | O15: LAX | P15: 1 | Q15: N | R15: 46250.556 | S15: 46251.045 | V15: 46250.562 | W15: 46250.575 | X15: 46250.822 | Y15: 46250.832 | Z15: =IF(OR(V15="",Y15=""),"",ROUND((Y15-V15)*1440,0)) -> 388 | AA15: =IF(OR(W15="",X15=""),"",ROUND((X15-W15)*1440,0)) -> 356 | AB15: =IF(OR(V15="",W15=""),"",ROUND((W15-V15)*1440,0)) -> 18 | AC15: =IF(OR(X15="",Y15=""),"",ROUND((Y15-X15)*1440,0)) -> 14 | AD15: A350-900 | AF15: RP-C3511 | AG15: RP-C3511 | AH15: N | AI15: S22 | AJ15: CONTACT | AK15: R12 | AL15: REMOTE | AO15: DIVERTED | AP15: ON_BLOCKS | AR15: WEATHER | AT15: CURRENT | AV15: 71 | AW15: =IF(OR(V15="",R15=""),"",ROUND((V15-R15)*1440,0)) -> 10 | AX15: CEB | AZ15: 284 | BA15: 277 | BB15: 17200 | BC15: 0 | BD15: 0 | BE15: 176800 | BF15: 282192 | BH15: LS-081413 | BI15: 340 | BJ15: 320 | BK15: KSFO | BL15: RPVM | BM15: Y | BN15: N | BO15: Y | BP15: FULL | BQ15: CAR-01 | BR15: N | BS15: N | BT15: NOT_CAPTURED
A16: TC14 | B16: LEG-26081414 | C16: PR | D16: 0144 | E16: 2026-08-17 | F16: 1 | G16: PR | H16: PR | J16: J | K16: REVENUE | L16: MNL | M16: SIN | N16: MNL | O16: SIN | P16: 1 | Q16: N | R16: 46251.25 | S16: 46251.41 | V16: 46251.251 | W16: 46251.263 | X16: 46251.4 | Y16: 46251.41 | Z16: =IF(OR(V16="",Y16=""),"",ROUND((Y16-V16)*1440,0)) -> 228 | AA16: =IF(OR(W16="",X16=""),"",ROUND((X16-W16)*1440,0)) -> 197 | AB16: =IF(OR(V16="",W16=""),"",ROUND((W16-V16)*1440,0)) -> 17 | AC16: =IF(OR(X16="",Y16=""),"",ROUND((Y16-X16)*1440,0)) -> 14 | AD16: A321 | AF16: RP-C4124 | AG16: RP-C4124 | AH16: N | AI16: S12 | AJ16: CONTACT | AK16: B04 | AL16: CONTACT | AO16: ARRIVED | AP16: ON_BLOCKS | AT16: CURRENT | AW16: =IF(OR(V16="",R16=""),"",ROUND((V16-R16)*1440,0)) -> 2 | AZ16: 170 | BA16: 167 | BB16: 4400 | BC16: 0 | BD16: 0 | BE16: 68700 | BF16: 83151 | BG16: 71451 | BH16: LS-081414 | BI16: 350 | BJ16: 350 | BK16: WSSS | BL16: WSSS | BM16: Y | BN16: N | BO16: Y | BP16: FULL | BQ16: CAR-01 | BR16: N | BS16: Y | BT16: COMPLETE
A17: TC15 | B17: LEG-26081415 | C17: PR | D17: 0150 | E17: 2026-08-17 | F17: 1 | G17: PR | H17: PR | J17: J | K17: REVENUE | L17: MNL | M17: CEB | N17: MNL | O17: CEB | P17: 1 | Q17: N | R17: 46251.292 | S17: 46251.354 | V17: 46251.294 | W17: 46251.305 | X17: 46251.346 | Y17: 46251.354 | Z17: =IF(OR(V17="",Y17=""),"",ROUND((Y17-V17)*1440,0)) -> 86 | AA17: =IF(OR(W17="",X17=""),"",ROUND((X17-W17)*1440,0)) -> 59 | AB17: =IF(OR(V17="",W17=""),"",ROUND((W17-V17)*1440,0)) -> 15 | AC17: =IF(OR(X17="",Y17=""),"",ROUND((Y17-X17)*1440,0)) -> 12 | AD17: A320 | AF17: RP-C4126 | AG17: RP-C4126 | AH17: N | AI17: S03 | AJ17: CONTACT | AK17: C05 | AL17: REMOTE | AO17: ARRIVED | AP17: ON_BLOCKS | AT17: CURRENT | AW17: =IF(OR(V17="",R17=""),"",ROUND((V17-R17)*1440,0)) -> 4 | AZ17: 156 | BA17: 151 | BB17: 2100 | BC17: 0 | BD17: 0 | BE17: 55400 | BF17: 60745 | BG17: 57345 | BH17: LS-081415 | BI17: 330 | BJ17: 330 | BK17: RPMD | BL17: RPMD | BM17: Y | BN17: N | BO17: Y | BP17: FULL | BQ17: CAR-01 | BR17: N | BS17: Y | BT17: COMPLETE
A18: TC15 | B18: LEG-26081416 | C18: PR | D18: 0150 | E18: 2026-08-17 | F18: 2 | G18: PR | H18: PR | J18: J | K18: REVENUE | L18: MNL | M18: CEB | N18: MNL | O18: CEB | P18: 1 | Q18: N | R18: 46251.667 | S18: 46251.729 | V18: 46251.674 | W18: 46251.685 | X18: 46251.725 | Y18: 46251.733 | Z18: =IF(OR(V18="",Y18=""),"",ROUND((Y18-V18)*1440,0)) -> 85 | AA18: =IF(OR(W18="",X18=""),"",ROUND((X18-W18)*1440,0)) -> 58 | AB18: =IF(OR(V18="",W18=""),"",ROUND((W18-V18)*1440,0)) -> 15 | AC18: =IF(OR(X18="",Y18=""),"",ROUND((Y18-X18)*1440,0)) -> 12 | AD18: A320 | AF18: RP-C4126 | AG18: RP-C4126 | AH18: N | AI18: S03 | AJ18: CONTACT | AK18: C05 | AL18: REMOTE | AO18: ARRIVED | AP18: ON_BLOCKS | AT18: CURRENT | AW18: =IF(OR(V18="",R18=""),"",ROUND((V18-R18)*1440,0)) -> 11 | AZ18: 158 | BA18: 154 | BB18: 2300 | BC18: 0 | BD18: 0 | BE18: 55800 | BF18: 60995 | BG18: 57595 | BH18: LS-081416 | BI18: 330 | BJ18: 330 | BK18: RPMD | BL18: RPMD | BM18: Y | BN18: N | BO18: Y | BP18: FULL | BQ18: CAR-01 | BR18: N | BS18: Y | BT18: COMPLETE
A19: TC16 | B19: LEG-26081417 | C19: PR | D19: 0152 | E19: 2026-08-18 | F19: 1 | G19: PR | H19: PR | J19: J | K19: REVENUE | L19: MNL | M19: SIN | N19: MNL | O19: SIN | P19: 1 | Q19: N | R19: 46252.25 | S19: 46252.41 | V19: 46252.252 | W19: 46252.264 | X19: 46252.401 | Y19: 46252.411 | Z19: =IF(OR(V19="",Y19=""),"",ROUND((Y19-V19)*1440,0)) -> 229 | AA19: =IF(OR(W19="",X19=""),"",ROUND((X19-W19)*1440,0)) -> 198 | AB19: =IF(OR(V19="",W19=""),"",ROUND((W19-V19)*1440,0)) -> 17 | AC19: =IF(OR(X19="",Y19=""),"",ROUND((Y19-X19)*1440,0)) -> 14 | AD19: A321 | AF19: RP-C4128 | AG19: RP-C4128 | AH19: N | AI19: S12 | AJ19: CONTACT | AK19: B04 | AL19: CONTACT | AO19: ARRIVED | AP19: ON_BLOCKS | AT19: CURRENT | AW19: =IF(OR(V19="",R19=""),"",ROUND((V19-R19)*1440,0)) -> 3 | AZ19: 167 | BA19: 163 | BB19: 4200 | BC19: 0 | BD19: 0 | BE19: 68300 | BF19: 79551 | BG19: 71131 | BH19: LS-081417 | BI19: 350 | BJ19: 350 | BK19: WSSS | BL19: WSSS | BM19: Y | BN19: N | BO19: Y | BP19: FULL | BQ19: CAR-01 | BR19: N | BS19: Y | BT19: COMPLETE
A20: TC17 | B20: LEG-26081418 | C20: PR | D20: 0154 | E20: 2026-08-18 | F20: 1 | G20: PR | H20: PR | J20: J | K20: REVENUE | L20: MNL | M20: SIN | N20: MNL | O20: SIN | P20: 1 | Q20: N | R20: 46252.458 | S20: 46252.618 | V20: 46252.476 | W20: 46252.488 | X20: 46252.626 | Y20: 46252.635 | Z20: =IF(OR(V20="",Y20=""),"",ROUND((Y20-V20)*1440,0)) -> 229 | AA20: =IF(OR(W20="",X20=""),"",ROUND((X20-W20)*1440,0)) -> 198 | AB20: =IF(OR(V20="",W20=""),"",ROUND((W20-V20)*1440,0)) -> 17 | AC20: =IF(OR(X20="",Y20=""),"",ROUND((Y20-X20)*1440,0)) -> 14 | AD20: A321 | AF20: RP-C4130 | AG20: RP-C4130 | AH20: N | AI20: S14 | AJ20: CONTACT | AK20: B07 | AL20: CONTACT | AO20: ARRIVED | AP20: ON_BLOCKS | AT20: CURRENT | AW20: =IF(OR(V20="",R20=""),"",ROUND((V20-R20)*1440,0)) -> 26 | AZ20: 173 | BA20: 169 | BB20: 4600 | BC20: 0 | BD20: 0 | BE20: 69000 | BF20: 80251 | BG20: 71131 | BH20: LS-081418 | BI20: 350 | BJ20: 350 | BK20: WSSS | BL20: WSSS | BM20: Y | BN20: N | BO20: Y | BP20: FULL | BQ20: CAR-01 | BR20: N | BS20: N | BT20: COMPLETE
A21: TC18 | B21: LEG-26081419 | C21: PR | D21: 0156 | E21: 2026-08-18 | F21: 1 | G21: PR | H21: PR | J21: J | K21: REVENUE | L21: MNL | M21: SIN | N21: MNL | O21: SIN | P21: 1 | Q21: N | R21: 46252.625 | S21: 46252.785 | V21: 46252.628 | W21: 46252.64 | X21: 46252.781 | Y21: 46252.79 | Z21: =IF(OR(V21="",Y21=""),"",ROUND((Y21-V21)*1440,0)) -> 234 | AA21: =IF(OR(W21="",X21=""),"",ROUND((X21-W21)*1440,0)) -> 203 | AB21: =IF(OR(V21="",W21=""),"",ROUND((W21-V21)*1440,0)) -> 17 | AC21: =IF(OR(X21="",Y21=""),"",ROUND((Y21-X21)*1440,0)) -> 14 | AD21: A321 | AF21: RP-C4132 | AG21: RP-C4132 | AH21: N | AI21: S09 | AJ21: CONTACT | AK21: B02 | AL21: CONTACT | AO21: ARRIVED | AP21: ON_BLOCKS | AT21: CURRENT | AW21: =IF(OR(V21="",R21=""),"",ROUND((V21-R21)*1440,0)) -> 4 | AZ21: 178 | BA21: 175 | BB21: 4900 | BC21: 0 | BD21: 0 | BE21: 70100 | BF21: 81719 | BG21: 71819 | BH21: LS-081419 | BI21: 350 | BJ21: 350 | BK21: WSSS | BL21: WSSS | BM21: Y | BN21: N | BO21: Y | BP21: FULL | BQ21: CAR-01 | BR21: N | BS21: N | BT21: COMPLETE
A22: TC19 | B22: LEG-26081420 | C22: PR | D22: 0158 | E22: 2026-08-19 | F22: 1 | G22: PR | H22: PR | J22: J | K22: REVENUE | L22: MNL | M22: SIN | N22: MNL | O22: SIN | P22: 1 | Q22: N | R22: 46253.25 | S22: 46253.41 | V22: 46253.256 | W22: 46253.268 | X22: 46253.406 | Y22: 46253.415 | Z22: =IF(OR(V22="",Y22=""),"",ROUND((Y22-V22)*1440,0)) -> 229 | AA22: =IF(OR(W22="",X22=""),"",ROUND((X22-W22)*1440,0)) -> 198 | AB22: =IF(OR(V22="",W22=""),"",ROUND((W22-V22)*1440,0)) -> 17 | AC22: =IF(OR(X22="",Y22=""),"",ROUND((Y22-X22)*1440,0)) -> 14 | AD22: A321 | AF22: RP-C4134 | AG22: RP-C4134 | AH22: N | AI22: S12 | AJ22: CONTACT | AK22: B04 | AL22: CONTACT | AO22: ARRIVED | AP22: ON_BLOCKS | AT22: CURRENT | AW22: =IF(OR(V22="",R22=""),"",ROUND((V22-R22)*1440,0)) -> 9 | AZ22: 166 | BA22: 162 | BB22: 4100 | BC22: 0 | BD22: 0 | BE22: 68200 | BF22: 79630 | BG22: 71030 | BH22: LS-081420 | BI22: 350 | BJ22: 350 | BK22: WSSS | BL22: WSSS | BM22: Y | BN22: N | BO22: Y | BP22: FULL | BQ22: CAR-01 | BR22: N | BS22: Y | BT22: COMPLETE
A23: TC20 | B23: LEG-26081421 | C23: PR | D23: 0160 | E23: 2026-08-19 | F23: 1 | G23: PR | H23: PR | J23: J | K23: REVENUE | L23: MNL | M23: SIN | N23: MNL | O23: SIN | P23: 1 | Q23: N | R23: 46253.458 | S23: 46253.618 | V23: 46253.46 | W23: 46253.472 | X23: 46253.609 | Y23: 46253.619 | Z23: =IF(OR(V23="",Y23=""),"",ROUND((Y23-V23)*1440,0)) -> 229 | AA23: =IF(OR(W23="",X23=""),"",ROUND((X23-W23)*1440,0)) -> 198 | AB23: =IF(OR(V23="",W23=""),"",ROUND((W23-V23)*1440,0)) -> 17 | AC23: =IF(OR(X23="",Y23=""),"",ROUND((Y23-X23)*1440,0)) -> 14 | AD23: A321 | AF23: RP-C4136 | AG23: RP-C4136 | AH23: N | AI23: S14 | AJ23: CONTACT | AK23: B07 | AL23: CONTACT | AO23: ARRIVED | AP23: ON_BLOCKS | AT23: CURRENT | AW23: =IF(OR(V23="",R23=""),"",ROUND((V23-R23)*1440,0)) -> 2 | AZ23: 175 | BA23: 172 | BB23: 4700 | BC23: 0 | BD23: 0 | BE23: 69400 | BF23: 81551 | BG23: 71951 | BH23: LS-081421 | BI23: 350 | BJ23: 350 | BK23: WSSS | BL23: WSSS | BM23: Y | BN23: N | BO23: Y | BP23: FULL | BQ23: CAR-01 | BR23: N | BS23: N | BT23: NOT_CAPTURED
A24: TC21 | B24: LEG-26081422 | C24: PR | D24: 0110 | E24: 2026-08-19 | F24: 1 | G24: PR | H24: PR | J24: J | K24: REVENUE | L24: MNL | M24: LAX | N24: MNL | O24: LAX | P24: 1 | Q24: N | R24: 46253.556 | S24: 46254.045 | V24: 46253.557 | W24: 46253.569 | X24: 46254.031 | Y24: 46254.04 | Z24: =IF(OR(V24="",Y24=""),"",ROUND((Y24-V24)*1440,0)) -> 696 | AA24: =IF(OR(W24="",X24=""),"",ROUND((X24-W24)*1440,0)) -> 664 | AB24: =IF(OR(V24="",W24=""),"",ROUND((W24-V24)*1440,0)) -> 18 | AC24: =IF(OR(X24="",Y24=""),"",ROUND((Y24-X24)*1440,0)) -> 14 | AD24: A350-900 | AF24: RP-C3513 | AG24: RP-C3513 | AH24: N | AI24: S22 | AJ24: CONTACT | AK24: T148 | AL24: CONTACT | AO24: ARRIVED | AP24: ON_BLOCKS | AT24: CURRENT | AW24: =IF(OR(V24="",R24=""),"",ROUND((V24-R24)*1440,0)) -> 2 | AZ24: 288 | BA24: 283 | BB24: 18900 | BC24: 0 | BD24: 0 | BE24: 178900 | BF24: 263486 | BG24: 190486 | BH24: LS-081422 | BI24: 340 | BJ24: 360 | BK24: KSFO | BL24: KSFO | BM24: Y | BN24: N | BO24: Y | BP24: FULL | BQ24: CAR-01 | BR24: N | BS24: Y | BT24: COMPLETE
A25: TC22 | B25: LEG-26081423 | C25: PR | D25: 0162 | E25: 2026-08-20 | F25: 1 | G25: PR | H25: PR | J25: J | K25: REVENUE | L25: MNL | M25: SIN | N25: MNL | O25: SIN | P25: 1 | Q25: N | R25: 46254.25 | S25: 46254.41 | V25: 46254.272 | W25: 46254.283 | X25: 46254.421 | Y25: 46254.431 | Z25: =IF(OR(V25="",Y25=""),"",ROUND((Y25-V25)*1440,0)) -> 229 | AA25: =IF(OR(W25="",X25=""),"",ROUND((X25-W25)*1440,0)) -> 198 | AB25: =IF(OR(V25="",W25=""),"",ROUND((W25-V25)*1440,0)) -> 17 | AC25: =IF(OR(X25="",Y25=""),"",ROUND((Y25-X25)*1440,0)) -> 14 | AD25: A321 | AF25: RP-C4138 | AG25: RP-C4138 | AH25: N | AI25: S12 | AJ25: CONTACT | AK25: B04 | AL25: CONTACT | AO25: ARRIVED | AP25: ON_BLOCKS | AT25: CURRENT | AV25: 89 | AW25: =IF(OR(V25="",R25=""),"",ROUND((V25-R25)*1440,0)) -> 31 | AZ25: 164 | BA25: 159 | BB25: 4000 | BC25: 0 | BD25: 0 | BE25: 67900 | BF25: 79151 | BG25: 70701 | BH25: LS-081423 | BI25: 350 | BJ25: 350 | BK25: WSSS | BL25: WSSS | BM25: Y | BN25: N | BO25: Y | BP25: FULL | BQ25: CAR-01 | BR25: N | BS25: N | BT25: PARTIAL
A26: TC33 | B26: LEG-26081424 | C26: PR | D26: 0164 | E26: 2026-08-21 | F26: 1 | G26: PR | H26: PR | J26: J | K26: REVENUE | L26: MNL | M26: SIN | N26: MNL | O26: SIN | P26: 1 | Q26: N | R26: 46255.25 | S26: 46255.41 | V26: 46255.253 | W26: 46255.265 | X26: 46255.403 | Y26: 46255.412 | Z26: =IF(OR(V26="",Y26=""),"",ROUND((Y26-V26)*1440,0)) -> 229 | AA26: =IF(OR(W26="",X26=""),"",ROUND((X26-W26)*1440,0)) -> 198 | AB26: =IF(OR(V26="",W26=""),"",ROUND((W26-V26)*1440,0)) -> 17 | AC26: =IF(OR(X26="",Y26=""),"",ROUND((Y26-X26)*1440,0)) -> 14 | AD26: A321 | AF26: RP-C4140 | AG26: RP-C4140 | AH26: N | AI26: S12 | AJ26: CONTACT | AK26: B04 | AL26: CONTACT | AO26: ARRIVED | AP26: ON_BLOCKS | AT26: CURRENT | AW26: =IF(OR(V26="",R26=""),"",ROUND((V26-R26)*1440,0)) -> 5 | AZ26: 171 | BA26: 168 | BB26: 4500 | BC26: 0 | BD26: 0 | BE26: 68800 | BF26: 83394 | BG26: 71581 | BH26: LS-081424 | BI26: 350 | BJ26: 350 | BK26: WSSS | BL26: WSSS | BM26: Y | BN26: N | BO26: Y | BP26: FULL | BQ26: CAR-01 | BR26: Y | BS26: N | BT26: COMPLETE
A29: FIELD GROUPS - why each group is held
A30: Group | B30: Fields | C30: Purpose in FuelSphere
A31: Identity | B31: carrier codes, flight number, date, leg sequence, service type | C31: Resolves the leg and the carrier arrangement. operating_carrier is distinct from the flight number
A32: OOOI | B32: out, off, on, in | C32: The four points burn is derived between. Without off and on there is no trip or taxi split
A33: Derived times | B33: block, flight, taxi out, taxi in minutes | C33: Ground time drives APU estimation. Taxi time explains taxi burn variance
A34: Stand | B34: dep and arr stand, stand type | C34: Contact versus remote determines whether APU running was avoidable
A35: Weight and payload | B35: ZFW, TOW, LW, pax, cargo | C35: Actual versus planned weight explains most burn variance
A36: Operational | B36: cruise level planned and flown, alternate planned and used | C36: Level and route deviation is the other main variance cause
A37: Efficiency flags | B37: single engine taxi, de-icing, APU reported | C37: Efficiency KPIs and taxi burn context
A38: Fuel linkage | B38: processing mode, arrangement, provisional tail, burn capture status | C38: Stamped at resolution; drives whether fuel is processed at all

Sheet FD_FUEL_PLAN
A1: FD_FUEL_PLAN - PK fd_fuel_plan_id | UK flight_leg_id + plan_version | one row per plan VERSION
A2: TC_ID | B2: fd_fuel_plan_id | C2: flight_leg_id | D2: plan_group_id | E2: plan_version | F2: source_system | G2: ofp_reference | H2: registration | I2: fuel_unit | J2: trip_fuel | K2: contingency_fuel | L2: alternate_fuel | M2: final_reserve_fuel | N2: additional_fuel | O2: taxi_fuel | P2: extra_fuel | Q2: block_fuel | R2: fuel_on_board | S2: required_uplift | T2: tankering_flag | U2: extra_reason_code | V2: plan_status | W2: change_reason | X2: fuelling_state_at_change | Y2: received_utc
A3: TC01 | B3: FDP-0101 | C3: LEG-26081401 | D3: PLG-101 | E3: 1 | F3: LIDO | G3: PR126/14AUG/01 | H3: RP-C4108 | I3: KG | J3: 8420 | K3: 421 | L3: 1180 | M3: 1050 | N3: 0 | O3: 180 | P3: 0 | Q3: =SUM(J3:P3) -> 11251 | R3: 2100 | S3: =Q3-R3 -> 9151 | T3: N | V3: ACTIVE | X3: NOT_STARTED | Y3: 2026-08-14T02:14Z
A4: TC02 | B4: FDP-0201 | C4: LEG-26081402 | D4: PLG-201 | E4: 1 | F4: LIDO | G4: PR128/14AUG/01 | H4: RP-C4110 | I4: KG | J4: 8420 | K4: 421 | L4: 1180 | M4: 1050 | N4: 0 | O4: 180 | P4: 0 | Q4: =SUM(J4:P4) -> 11251 | R4: 2050 | S4: =Q4-R4 -> 9201 | T4: N | V4: SUPERSEDED | X4: NOT_STARTED | Y4: 2026-08-14T07:10Z
A5: TC02 | B5: FDP-0202 | C5: LEG-26081402 | D5: PLG-201 | E5: 2 | F5: LIDO | G5: PR128/14AUG/02 | H5: RP-C4110 | I5: KG | J5: 8690 | K5: 435 | L5: 1180 | M5: 1050 | N5: 0 | O5: 180 | P5: 0 | Q5: =SUM(J5:P5) -> 11535 | R5: 2050 | S5: =Q5-R5 -> 9485 | T5: N | V5: ACTIVE | W5: PAYLOAD_INCREASE | X5: NOT_STARTED | Y5: 2026-08-14T08:05Z
A6: TC03 | B6: FDP-0301 | C6: LEG-26081403 | D6: PLG-301 | E6: 1 | F6: LIDO | G6: PR130/14AUG/01 | H6: RP-C4112 | I6: KG | J6: 8420 | K6: 421 | L6: 1180 | M6: 1050 | N6: 0 | O6: 180 | P6: 0 | Q6: =SUM(J6:P6) -> 11251 | R6: 2100 | S6: =Q6-R6 -> 9151 | T6: N | V6: SUPERSEDED | X6: NOT_STARTED | Y6: 2026-08-14T11:00Z
A7: TC03 | B7: FDP-0302 | C7: LEG-26081403 | D7: PLG-301 | E7: 2 | F7: LIDO | G7: PR130/14AUG/02 | H7: RP-C4112 | I7: KG | J7: 9140 | K7: 457 | L7: 1180 | M7: 1050 | N7: 0 | O7: 260 | P7: 200 | Q7: =SUM(J7:P7) -> 12287 | R7: 11540 | S7: =Q7-R7 -> 747 | T7: N | U7: OPS | V7: ACTIVE | W7: ATC_REROUTE | X7: COMPLETED | Y7: 2026-08-14T13:22Z
A8: TC04 | B8: FDP-0401 | C8: LEG-26081404 | D8: PLG-401 | E8: 1 | F8: LIDO | G8: PR132/14AUG/01 | H8: RP-C4108 | I8: KG | J8: 8420 | K8: 421 | L8: 1180 | M8: 1050 | N8: 0 | O8: 180 | P8: 0 | Q8: =SUM(J8:P8) -> 11251 | R8: 2100 | S8: =Q8-R8 -> 9151 | T8: N | V8: SUPERSEDED | X8: COMPLETED | Y8: 2026-08-14T14:00Z
A9: TC04 | B9: FDP-0402 | C9: LEG-26081404 | D9: PLG-401 | E9: 2 | F9: LIDO | G9: PR132/14AUG/02 | H9: RP-C4109 | I9: KG | J9: 8510 | K9: 426 | L9: 1180 | M9: 1050 | N9: 0 | O9: 180 | P9: 0 | Q9: =SUM(J9:P9) -> 11346 | R9: 4900 | S9: =Q9-R9 -> 6446 | T9: N | V9: ACTIVE | W9: TAIL_SWAP | X9: COMPLETED | Y9: 2026-08-14T16:38Z
A10: TC05 | B10: FDP-0501 | C10: LEG-26081405 | D10: PLG-501 | E10: 1 | F10: LIDO | G10: PR102/14AUG/01 | H10: RP-C3505 | I10: KG | J10: 96400 | K10: 2892 | L10: 3100 | M10: 2400 | N10: 0 | O10: 600 | P10: 0 | Q10: =SUM(J10:P10) -> 105392 | R10: 5200 | S10: =Q10-R10 -> 100192 | T10: N | V10: ACTIVE | X10: NOT_STARTED | Y10: 2026-08-14T09:10Z
A11: TC06 | B11: FDP-0601 | C11: LEG-26081406 | D11: PLG-601 | E11: 1 | F11: LIDO | G11: PR104/15AUG/01 | H11: RP-C3507 | I11: KG | J11: 96400 | K11: 2892 | L11: 3100 | M11: 2400 | N11: 0 | O11: 600 | P11: 0 | Q11: =SUM(J11:P11) -> 105392 | R11: 5200 | S11: =Q11-R11 -> 100192 | T11: N | V11: SUPERSEDED | X11: NOT_STARTED | Y11: 2026-08-15T09:10Z
A12: TC06 | B12: FDP-0602 | C12: LEG-26081406 | D12: PLG-601 | E12: 2 | F12: LIDO | G12: PR104/15AUG/02 | H12: RP-C3507 | I12: KG | J12: 96400 | K12: 2892 | L12: 5850 | M12: 2400 | N12: 0 | O12: 600 | P12: 0 | Q12: =SUM(J12:P12) -> 108142 | R12: 69594 | S12: =Q12-R12 -> 38548 | T12: N | V12: ACTIVE | W12: ALTERNATE_CHANGE | X12: IN_PROGRESS | Y12: 2026-08-15T11:48Z
A13: TC07 | B13: FDP-0701 | C13: LEG-26081407 | D13: PLG-701 | E13: 1 | F13: LIDO | G13: PR134/15AUG/01 | H13: RP-C4114 | I13: KG | J13: 8420 | K13: 421 | L13: 1180 | M13: 1050 | N13: 0 | O13: 180 | P13: 0 | Q13: =SUM(J13:P13) -> 11251 | R13: 2100 | S13: =Q13-R13 -> 9151 | T13: N | V13: CANCELLED | W13: FLIGHT_CANCELLED | X13: COMPLETED | Y13: 2026-08-15T02:20Z
A14: TC08 | B14: FDP-0801 | C14: LEG-26081408 | D14: PLG-801 | E14: 1 | F14: LIDO | G14: PR136/15AUG/01 | H14: RP-C4116 | I14: KG | J14: 8420 | K14: 421 | L14: 1180 | M14: 1050 | N14: 0 | O14: 180 | P14: 0 | Q14: =SUM(J14:P14) -> 11251 | R14: 2100 | S14: =Q14-R14 -> 9151 | T14: N | V14: SUPERSEDED | X14: COMPLETED | Y14: 2026-08-15T07:10Z
A15: TC08 | B15: FDP-0802 | C15: LEG-26081408 | D15: PLG-801 | E15: 2 | F15: LIDO | G15: PR136/15AUG/02 | H15: RP-C4116 | I15: KG | J15: 6900 | K15: 345 | L15: 1180 | M15: 1050 | N15: 0 | O15: 180 | P15: 0 | Q15: =SUM(J15:P15) -> 9655 | R15: 11251 | S15: =Q15-R15 -> -1596 | T15: N | V15: ACTIVE | W15: RETURN_TO_RAMP | X15: COMPLETED | Y15: 2026-08-15T11:40Z
A16: TC09 | B16: FDP-0901 | C16: LEG-26081409 | D16: PLG-901 | E16: 1 | F16: LIDO | G16: PR106/15AUG/01 | H16: RP-C3509 | I16: KG | J16: 96400 | K16: 2892 | L16: 3100 | M16: 2400 | N16: 0 | O16: 600 | P16: 0 | Q16: =SUM(J16:P16) -> 105392 | R16: 5200 | S16: =Q16-R16 -> 100192 | T16: N | V16: ACTIVE | X16: COMPLETED | Y16: 2026-08-15T09:10Z
A17: TC10 | B17: FDP-1001 | C17: LEG-26081410 | D17: PLG-1001 | E17: 1 | F17: LIDO | G17: PR138/16AUG/01 | H17: RP-C4118 | I17: KG | J17: 8420 | K17: 421 | L17: 1180 | M17: 1050 | N17: 0 | O17: 180 | P17: 0 | Q17: =SUM(J17:P17) -> 11251 | R17: 2100 | S17: =Q17-R17 -> 9151 | T17: N | V17: ACTIVE | X17: NOT_STARTED | Y17: 2026-08-16T02:14Z
A18: TC11 | B18: FDP-1101 | C18: LEG-26081411 | D18: PLG-1101 | E18: 1 | F18: LIDO | G18: PR140/16AUG/01 | H18: RP-C4120 | I18: KG | J18: 8420 | K18: 421 | L18: 1180 | M18: 1050 | N18: 0 | O18: 180 | P18: 0 | Q18: =SUM(J18:P18) -> 11251 | R18: 2100 | S18: =Q18-R18 -> 9151 | T18: N | V18: SUPERSEDED | X18: NOT_STARTED | Y18: 2026-08-16T07:00Z
A19: TC11 | B19: FDP-1102 | C19: LEG-26081411 | D19: PLG-1101 | E19: 2 | F19: LIDO | G19: PR140/16AUG/02 | H19: RP-C4120 | I19: KG | J19: 8420 | K19: 421 | L19: 1180 | M19: 1050 | N19: 0 | O19: 180 | P19: 900 | Q19: =SUM(J19:P19) -> 12151 | R19: 2100 | S19: =Q19-R19 -> 10051 | T19: N | U19: CMD_WX_HOLDING | V19: ACTIVE | W19: CAPTAIN_REQUEST | X19: NOT_STARTED | Y19: 2026-08-16T08:15Z
A20: TC12 | B20: FDP-1201 | C20: LEG-26081412 | D20: PLG-1201 | E20: 1 | F20: LIDO | G20: PR142/16AUG/01 | H20: RP-C4122 | I20: KG | J20: 8420 | K20: 421 | L20: 1180 | M20: 1050 | N20: 0 | O20: 180 | P20: 0 | Q20: =SUM(J20:P20) -> 11251 | R20: 2100 | S20: =Q20-R20 -> 9151 | T20: N | V20: ACTIVE | X20: NOT_STARTED | Y20: 2026-08-16T11:00Z
A21: TC13 | B21: FDP-1301 | C21: LEG-26081413 | D21: PLG-1301 | E21: 1 | F21: LIDO | G21: PR108/16AUG/01 | H21: RP-C3511 | I21: KG | J21: 96400 | K21: 2892 | L21: 3100 | M21: 2400 | N21: 0 | O21: 600 | P21: 0 | Q21: =SUM(J21:P21) -> 105392 | R21: 5200 | S21: =Q21-R21 -> 100192 | T21: N | V21: ACTIVE | X21: NOT_STARTED | Y21: 2026-08-16T09:10Z
A22: TC14 | B22: FDP-1401 | C22: LEG-26081414 | D22: PLG-1401 | E22: 1 | F22: LIDO | G22: PR144/17AUG/01 | H22: RP-C4124 | I22: KG | J22: 8420 | K22: 421 | L22: 1180 | M22: 1050 | N22: 0 | O22: 180 | P22: 3200 | Q22: =SUM(J22:P22) -> 14451 | R22: 2100 | S22: =Q22-R22 -> 12351 | T22: Y | U22: TANKERING | V22: ACTIVE | X22: NOT_STARTED | Y22: 2026-08-17T02:14Z
A23: TC15 | B23: FDP-1501 | C23: LEG-26081415 | D23: PLG-1501 | E23: 1 | F23: LIDO | G23: PR150/17AUG/01 | H23: RP-C4126 | I23: KG | J23: 3100 | K23: 155 | L23: 900 | M23: 1050 | N23: 0 | O23: 140 | P23: 0 | Q23: =SUM(J23:P23) -> 5345 | R23: 1800 | S23: =Q23-R23 -> 3545 | T23: N | V23: ACTIVE | X23: NOT_STARTED | Y23: 2026-08-17T02:00Z
A24: TC15 | B24: FDP-1601 | C24: LEG-26081416 | D24: PLG-1601 | E24: 1 | F24: LIDO | G24: PR150/17AUG/03 | H24: RP-C4126 | I24: KG | J24: 3100 | K24: 155 | L24: 900 | M24: 1050 | N24: 0 | O24: 140 | P24: 0 | Q24: =SUM(J24:P24) -> 5345 | R24: 1650 | S24: =Q24-R24 -> 3695 | T24: N | V24: ACTIVE | X24: NOT_STARTED | Y24: 2026-08-17T11:00Z
A25: TC16 | B25: FDP-1701 | C25: LEG-26081417 | D25: PLG-1701 | E25: 1 | F25: LIDO | G25: PR152/18AUG/01 | H25: RP-C4128 | I25: KG | J25: 8420 | K25: 421 | L25: 1180 | M25: 1050 | N25: 0 | O25: 180 | P25: 0 | Q25: =SUM(J25:P25) -> 11251 | R25: 2100 | S25: =Q25-R25 -> 9151 | T25: N | V25: ACTIVE | X25: NOT_STARTED | Y25: 2026-08-18T02:14Z
A26: TC17 | B26: FDP-1801 | C26: LEG-26081418 | D26: PLG-1801 | E26: 1 | F26: LIDO | G26: PR154/18AUG/01 | H26: RP-C4130 | I26: KG | J26: 8420 | K26: 421 | L26: 1180 | M26: 1050 | N26: 0 | O26: 180 | P26: 0 | Q26: =SUM(J26:P26) -> 11251 | R26: 2100 | S26: =Q26-R26 -> 9151 | T26: N | V26: ACTIVE | X26: NOT_STARTED | Y26: 2026-08-18T07:10Z
A27: TC18 | B27: FDP-1901 | C27: LEG-26081419 | D27: PLG-1901 | E27: 1 | F27: LIDO | G27: PR156/18AUG/01 | H27: RP-C4132 | I27: KG | J27: 8770 | K27: 439 | L27: 1180 | M27: 1050 | N27: 0 | O27: 180 | P27: 0 | Q27: =SUM(J27:P27) -> 11619 | R27: 2100 | S27: =Q27-R27 -> 9519 | T27: N | V27: ACTIVE | X27: NOT_STARTED | Y27: 2026-08-18T11:00Z
A28: TC19 | B28: FDP-2001 | C28: LEG-26081420 | D28: PLG-2001 | E28: 1 | F28: LIDO | G28: PR158/19AUG/01 | H28: RP-C4134 | I28: KG | J28: 8420 | K28: 421 | L28: 1180 | M28: 1050 | N28: 0 | O28: 180 | P28: 0 | Q28: =SUM(J28:P28) -> 11251 | R28: 11000 | S28: =Q28-R28 -> 251 | T28: N | V28: ACTIVE | W28: SLOT_DELAY | X28: COMPLETED | Y28: 2026-08-19T04:40Z
A29: TC20 | B29: FDP-2101 | C29: LEG-26081421 | D29: PLG-2101 | E29: 1 | F29: LIDO | G29: PR160/19AUG/01 | H29: RP-C4136 | I29: KG | J29: 8420 | K29: 421 | L29: 1180 | M29: 1050 | N29: 0 | O29: 180 | P29: 0 | Q29: =SUM(J29:P29) -> 11251 | R29: 2100 | S29: =Q29-R29 -> 9151 | T29: N | V29: ACTIVE | X29: NOT_STARTED | Y29: 2026-08-19T07:10Z
A30: TC21 | B30: FDP-2201 | C30: LEG-26081422 | D30: PLG-2201 | E30: 1 | F30: LIDO | G30: PR110/19AUG/01 | H30: RP-C3513 | I30: KG | J30: 76200 | K30: 2286 | L30: 3100 | M30: 2400 | N30: 0 | O30: 600 | P30: 0 | Q30: =SUM(J30:P30) -> 84586 | R30: 5200 | S30: =Q30-R30 -> 79386 | T30: N | V30: ACTIVE | X30: NOT_STARTED | Y30: 2026-08-19T09:10Z
A31: TC22 | B31: FDP-2301 | C31: LEG-26081423 | D31: PLG-2301 | E31: 1 | F31: LIDO | G31: PR162/20AUG/01 | H31: RP-C4138 | I31: KG | J31: 8420 | K31: 421 | L31: 1180 | M31: 1050 | N31: 0 | O31: 180 | P31: 0 | Q31: =SUM(J31:P31) -> 11251 | R31: 2100 | S31: =Q31-R31 -> 9151 | T31: N | V31: ACTIVE | X31: NOT_STARTED | Y31: 2026-08-20T02:14Z
A32: TC33 | B32: FDP-2401 | C32: LEG-26081424 | D32: PLG-2401 | E32: 1 | F32: LIDO | G32: PR164/21AUG/01 | H32: RP-C4140 | I32: KG | J32: 8420 | K32: 421 | L32: 1180 | M32: 1050 | N32: 0 | O32: 180 | P32: 0 | Q32: =SUM(J32:P32) -> 11251 | R32: 2100 | S32: =Q32-R32 -> 9151 | T32: N | V32: ACTIVE | X32: NOT_STARTED | Y32: 2026-08-21T02:14Z

Sheet FUEL_ORDER
A1: FUEL_ORDER - PK fuel_order_id | UK order_number + order_version | delivered_qty summed from tickets; fulfilment checked at order level
A2: TC_ID | B2: fuel_order_id | C2: order_number | D2: order_version | E2: flight_leg_id | F2: fd_fuel_plan_id | G2: registration | H2: station | I2: supplier_code | J2: ordered_qty | K2: order_unit | L2: order_type | M2: delivered_qty | N2: ticket_count | O2: variance_qty | P2: variance_pct | Q2: tolerance_qty | R2: fulfilment_check | S2: order_status | T2: under_delivery_reason | U2: freeze_flag | V2: sent_utc
A3: TC01 | B3: ORD-1001 | C3: PR/MNL/140826/0126 | D3: 1 | E3: LEG-26081401 | F3: FDP-0101 | G3: RP-C4108 | H3: MNL | I3: PPC | J3: 9151 | K3: KG | L3: INITIAL | M3: =SUMIFS(FUEL_TICKET!$Z:$Z,FUEL_TICKET!$I:$I,$B3) -> 9151.1 | N3: =COUNTIFS(FUEL_TICKET!$I:$I,$B3) -> 1 | O3: =ROUND(M3-J3,1) -> 0.1 | P3: =IF(J3=0,"",O3/ABS(J3)) -> 1.0927767e-05 | Q3: =MAX(50,0.01*ABS(J3)) -> 91.51 | R3: =IF(S3="SUPERSEDED","NOT_APPLICABLE",IF(N3=0,"NOT_DELIVERED",IF(ABS(O3)<=Q3,"WITHIN_TOLERANCE",IF(O3<0,"UNDER_DELIVERED","OVER_DELIVERED")))) -> WITHIN_TOLERANCE | S3: FULFILLED | U3: Y | V3: 2026-08-14T02:30Z
A4: TC02 | B4: ORD-1002 | C4: PR/MNL/140826/0128 | D4: 1 | E4: LEG-26081402 | F4: FDP-0201 | G4: RP-C4110 | H4: MNL | I4: PPC | J4: 9201 | K4: KG | L4: INITIAL | M4: =SUMIFS(FUEL_TICKET!$Z:$Z,FUEL_TICKET!$I:$I,$B4) -> 0 | N4: =COUNTIFS(FUEL_TICKET!$I:$I,$B4) -> 0 | O4: =ROUND(M4-J4,1) -> -9201 | P4: =IF(J4=0,"",O4/ABS(J4)) -> -1 | Q4: =MAX(50,0.01*ABS(J4)) -> 92.01 | R4: =IF(S4="SUPERSEDED","NOT_APPLICABLE",IF(N4=0,"NOT_DELIVERED",IF(ABS(O4)<=Q4,"WITHIN_TOLERANCE",IF(O4<0,"UNDER_DELIVERED","OVER_DELIVERED")))) -> NOT_APPLICABLE | S4: SUPERSEDED | U4: N | V4: 2026-08-14T07:25Z
A5: TC02 | B5: ORD-1003 | C5: PR/MNL/140826/0128 | D5: 2 | E5: LEG-26081402 | F5: FDP-0202 | G5: RP-C4110 | H5: MNL | I5: PPC | J5: 9485 | K5: KG | L5: AMENDMENT | M5: =SUMIFS(FUEL_TICKET!$Z:$Z,FUEL_TICKET!$I:$I,$B5) -> 9485.3 | N5: =COUNTIFS(FUEL_TICKET!$I:$I,$B5) -> 1 | O5: =ROUND(M5-J5,1) -> 0.3 | P5: =IF(J5=0,"",O5/ABS(J5)) -> 3.1628888e-05 | Q5: =MAX(50,0.01*ABS(J5)) -> 94.85 | R5: =IF(S5="SUPERSEDED","NOT_APPLICABLE",IF(N5=0,"NOT_DELIVERED",IF(ABS(O5)<=Q5,"WITHIN_TOLERANCE",IF(O5<0,"UNDER_DELIVERED","OVER_DELIVERED")))) -> WITHIN_TOLERANCE | S5: FULFILLED | U5: Y | V5: 2026-08-14T08:20Z
A6: TC03 | B6: ORD-1004 | C6: PR/MNL/140826/0130 | D6: 1 | E6: LEG-26081403 | F6: FDP-0301 | G6: RP-C4112 | H6: MNL | I6: PPC | J6: 9151 | K6: KG | L6: INITIAL | M6: =SUMIFS(FUEL_TICKET!$Z:$Z,FUEL_TICKET!$I:$I,$B6) -> 9151.9 | N6: =COUNTIFS(FUEL_TICKET!$I:$I,$B6) -> 1 | O6: =ROUND(M6-J6,1) -> 0.9 | P6: =IF(J6=0,"",O6/ABS(J6)) -> 9.8349907e-05 | Q6: =MAX(50,0.01*ABS(J6)) -> 91.51 | R6: =IF(S6="SUPERSEDED","NOT_APPLICABLE",IF(N6=0,"NOT_DELIVERED",IF(ABS(O6)<=Q6,"WITHIN_TOLERANCE",IF(O6<0,"UNDER_DELIVERED","OVER_DELIVERED")))) -> WITHIN_TOLERANCE | S6: FULFILLED | U6: Y | V6: 2026-08-14T11:15Z
A7: TC03 | B7: ORD-1005 | C7: PR/MNL/140826/0130-T | D7: 1 | E7: LEG-26081403 | F7: FDP-0302 | G7: RP-C4112 | H7: MNL | I7: PPC | J7: 747 | K7: KG | L7: TOP_UP | M7: =SUMIFS(FUEL_TICKET!$Z:$Z,FUEL_TICKET!$I:$I,$B7) -> 746.7 | N7: =COUNTIFS(FUEL_TICKET!$I:$I,$B7) -> 1 | O7: =ROUND(M7-J7,1) -> -0.3 | P7: =IF(J7=0,"",O7/ABS(J7)) -> -0.00040160643 | Q7: =MAX(50,0.01*ABS(J7)) -> 50 | R7: =IF(S7="SUPERSEDED","NOT_APPLICABLE",IF(N7=0,"NOT_DELIVERED",IF(ABS(O7)<=Q7,"WITHIN_TOLERANCE",IF(O7<0,"UNDER_DELIVERED","OVER_DELIVERED")))) -> WITHIN_TOLERANCE | S7: FULFILLED | U7: Y | V7: 2026-08-14T13:30Z
A8: TC04 | B8: ORD-1006 | C8: PR/MNL/140826/0132 | D8: 1 | E8: LEG-26081404 | F8: FDP-0401 | G8: RP-C4108 | H8: MNL | I8: PPC | J8: 9151 | K8: KG | L8: INITIAL | M8: =SUMIFS(FUEL_TICKET!$Z:$Z,FUEL_TICKET!$I:$I,$B8) -> 9151.9 | N8: =COUNTIFS(FUEL_TICKET!$I:$I,$B8) -> 1 | O8: =ROUND(M8-J8,1) -> 0.9 | P8: =IF(J8=0,"",O8/ABS(J8)) -> 9.8349907e-05 | Q8: =MAX(50,0.01*ABS(J8)) -> 91.51 | R8: =IF(S8="SUPERSEDED","NOT_APPLICABLE",IF(N8=0,"NOT_DELIVERED",IF(ABS(O8)<=Q8,"WITHIN_TOLERANCE",IF(O8<0,"UNDER_DELIVERED","OVER_DELIVERED")))) -> WITHIN_TOLERANCE | S8: FULFILLED | U8: Y | V8: 2026-08-14T14:15Z
A9: TC04 | B9: ORD-1007 | C9: PR/MNL/140826/0132-S | D9: 1 | E9: LEG-26081404 | F9: FDP-0402 | G9: RP-C4109 | H9: MNL | I9: PPC | J9: 6446 | K9: KG | L9: INITIAL | M9: =SUMIFS(FUEL_TICKET!$Z:$Z,FUEL_TICKET!$I:$I,$B9) -> 6445.6 | N9: =COUNTIFS(FUEL_TICKET!$I:$I,$B9) -> 1 | O9: =ROUND(M9-J9,1) -> -0.4 | P9: =IF(J9=0,"",O9/ABS(J9)) -> -6.2053987e-05 | Q9: =MAX(50,0.01*ABS(J9)) -> 64.46 | R9: =IF(S9="SUPERSEDED","NOT_APPLICABLE",IF(N9=0,"NOT_DELIVERED",IF(ABS(O9)<=Q9,"WITHIN_TOLERANCE",IF(O9<0,"UNDER_DELIVERED","OVER_DELIVERED")))) -> WITHIN_TOLERANCE | S9: FULFILLED | U9: Y | V9: 2026-08-14T16:50Z
A10: TC05 | B10: ORD-1008 | C10: PR/MNL/140826/0102 | D10: 1 | E10: LEG-26081405 | F10: FDP-0501 | G10: RP-C3505 | H10: MNL | I10: PPC | J10: 100192 | K10: KG | L10: INITIAL | M10: =SUMIFS(FUEL_TICKET!$Z:$Z,FUEL_TICKET!$I:$I,$B10) -> 100191.7 | N10: =COUNTIFS(FUEL_TICKET!$I:$I,$B10) -> 2 | O10: =ROUND(M10-J10,1) -> -0.3 | P10: =IF(J10=0,"",O10/ABS(J10)) -> -2.994251e-06 | Q10: =MAX(50,0.01*ABS(J10)) -> 1001.92 | R10: =IF(S10="SUPERSEDED","NOT_APPLICABLE",IF(N10=0,"NOT_DELIVERED",IF(ABS(O10)<=Q10,"WITHIN_TOLERANCE",IF(O10<0,"UNDER_DELIVERED","OVER_DELIVERED")))) -> WITHIN_TOLERANCE | S10: FULFILLED | U10: Y | V10: 2026-08-14T09:25Z
A11: TC06 | B11: ORD-1009 | C11: PR/MNL/150826/0104 | D11: 1 | E11: LEG-26081406 | F11: FDP-0601 | G11: RP-C3507 | H11: MNL | I11: PPC | J11: 100192 | K11: KG | L11: INITIAL | M11: =SUMIFS(FUEL_TICKET!$Z:$Z,FUEL_TICKET!$I:$I,$B11) -> 64394 | N11: =COUNTIFS(FUEL_TICKET!$I:$I,$B11) -> 2 | O11: =ROUND(M11-J11,1) -> -35798 | P11: =IF(J11=0,"",O11/ABS(J11)) -> -0.357294 | Q11: =MAX(50,0.01*ABS(J11)) -> 1001.92 | R11: =IF(S11="SUPERSEDED","NOT_APPLICABLE",IF(N11=0,"NOT_DELIVERED",IF(ABS(O11)<=Q11,"WITHIN_TOLERANCE",IF(O11<0,"UNDER_DELIVERED","OVER_DELIVERED")))) -> UNDER_DELIVERED | S11: PART_FULFILLED | T11: FUELLING_INTERRUPTED_BY_REPLAN | U11: Y | V11: 2026-08-15T09:25Z
A12: TC06 | B12: ORD-1010 | C12: PR/MNL/150826/0104-T | D12: 1 | E12: LEG-26081406 | F12: FDP-0602 | G12: RP-C3507 | H12: MNL | I12: PPC | J12: 38548 | K12: KG | L12: TOP_UP | M12: =SUMIFS(FUEL_TICKET!$Z:$Z,FUEL_TICKET!$I:$I,$B12) -> 38548.3 | N12: =COUNTIFS(FUEL_TICKET!$I:$I,$B12) -> 1 | O12: =ROUND(M12-J12,1) -> 0.3 | P12: =IF(J12=0,"",O12/ABS(J12)) -> 7.7825049e-06 | Q12: =MAX(50,0.01*ABS(J12)) -> 385.48 | R12: =IF(S12="SUPERSEDED","NOT_APPLICABLE",IF(N12=0,"NOT_DELIVERED",IF(ABS(O12)<=Q12,"WITHIN_TOLERANCE",IF(O12<0,"UNDER_DELIVERED","OVER_DELIVERED")))) -> WITHIN_TOLERANCE | S12: FULFILLED | U12: Y | V12: 2026-08-15T11:55Z
A13: TC07 | B13: ORD-1011 | C13: PR/MNL/150826/0134 | D13: 1 | E13: LEG-26081407 | F13: FDP-0701 | G13: RP-C4114 | H13: MNL | I13: PPC | J13: 9151 | K13: KG | L13: INITIAL | M13: =SUMIFS(FUEL_TICKET!$Z:$Z,FUEL_TICKET!$I:$I,$B13) -> 9151.9 | N13: =COUNTIFS(FUEL_TICKET!$I:$I,$B13) -> 1 | O13: =ROUND(M13-J13,1) -> 0.9 | P13: =IF(J13=0,"",O13/ABS(J13)) -> 9.8349907e-05 | Q13: =MAX(50,0.01*ABS(J13)) -> 91.51 | R13: =IF(S13="SUPERSEDED","NOT_APPLICABLE",IF(N13=0,"NOT_DELIVERED",IF(ABS(O13)<=Q13,"WITHIN_TOLERANCE",IF(O13<0,"UNDER_DELIVERED","OVER_DELIVERED")))) -> WITHIN_TOLERANCE | S13: FULFILLED | U13: Y | V13: 2026-08-15T02:35Z
A14: TC08 | B14: ORD-1012 | C14: PR/MNL/150826/0136 | D14: 1 | E14: LEG-26081408 | F14: FDP-0801 | G14: RP-C4116 | H14: MNL | I14: PPC | J14: 9151 | K14: KG | L14: INITIAL | M14: =SUMIFS(FUEL_TICKET!$Z:$Z,FUEL_TICKET!$I:$I,$B14) -> 9151.9 | N14: =COUNTIFS(FUEL_TICKET!$I:$I,$B14) -> 1 | O14: =ROUND(M14-J14,1) -> 0.9 | P14: =IF(J14=0,"",O14/ABS(J14)) -> 9.8349907e-05 | Q14: =MAX(50,0.01*ABS(J14)) -> 91.51 | R14: =IF(S14="SUPERSEDED","NOT_APPLICABLE",IF(N14=0,"NOT_DELIVERED",IF(ABS(O14)<=Q14,"WITHIN_TOLERANCE",IF(O14<0,"UNDER_DELIVERED","OVER_DELIVERED")))) -> WITHIN_TOLERANCE | S14: FULFILLED | U14: Y | V14: 2026-08-15T07:25Z
A15: TC08 | B15: ORD-1013 | C15: PR/MNL/150826/0136-D | D15: 1 | E15: LEG-26081408 | F15: FDP-0802 | G15: RP-C4116 | H15: MNL | I15: PPC | J15: -1596 | K15: KG | L15: DEFUEL | M15: =SUMIFS(FUEL_TICKET!$Z:$Z,FUEL_TICKET!$I:$I,$B15) -> -1595.8 | N15: =COUNTIFS(FUEL_TICKET!$I:$I,$B15) -> 1 | O15: =ROUND(M15-J15,1) -> 0.2 | P15: =IF(J15=0,"",O15/ABS(J15)) -> 0.00012531328 | Q15: =MAX(50,0.01*ABS(J15)) -> 50 | R15: =IF(S15="SUPERSEDED","NOT_APPLICABLE",IF(N15=0,"NOT_DELIVERED",IF(ABS(O15)<=Q15,"WITHIN_TOLERANCE",IF(O15<0,"UNDER_DELIVERED","OVER_DELIVERED")))) -> WITHIN_TOLERANCE | S15: FULFILLED | U15: Y | V15: 2026-08-15T11:50Z
A16: TC09 | B16: ORD-1014 | C16: PR/MNL/150826/0106 | D16: 1 | E16: LEG-26081409 | F16: FDP-0901 | G16: RP-C3509 | H16: MNL | I16: PPC | J16: 100192 | K16: KG | L16: INITIAL | M16: =SUMIFS(FUEL_TICKET!$Z:$Z,FUEL_TICKET!$I:$I,$B16) -> 100168.5 | N16: =COUNTIFS(FUEL_TICKET!$I:$I,$B16) -> 1 | O16: =ROUND(M16-J16,1) -> -23.5 | P16: =IF(J16=0,"",O16/ABS(J16)) -> -0.00023454966 | Q16: =MAX(50,0.01*ABS(J16)) -> 1001.92 | R16: =IF(S16="SUPERSEDED","NOT_APPLICABLE",IF(N16=0,"NOT_DELIVERED",IF(ABS(O16)<=Q16,"WITHIN_TOLERANCE",IF(O16<0,"UNDER_DELIVERED","OVER_DELIVERED")))) -> WITHIN_TOLERANCE | S16: FULFILLED | U16: Y | V16: 2026-08-15T09:25Z
A17: TC11 | B17: ORD-1015 | C17: PR/MNL/160826/0140 | D17: 1 | E17: LEG-26081411 | F17: FDP-1102 | G17: RP-C4120 | H17: MNL | I17: PPC | J17: 10051 | K17: KG | L17: INITIAL | M17: =SUMIFS(FUEL_TICKET!$Z:$Z,FUEL_TICKET!$I:$I,$B17) -> 10050.5 | N17: =COUNTIFS(FUEL_TICKET!$I:$I,$B17) -> 1 | O17: =ROUND(M17-J17,1) -> -0.5 | P17: =IF(J17=0,"",O17/ABS(J17)) -> -4.9746294e-05 | Q17: =MAX(50,0.01*ABS(J17)) -> 100.51 | R17: =IF(S17="SUPERSEDED","NOT_APPLICABLE",IF(N17=0,"NOT_DELIVERED",IF(ABS(O17)<=Q17,"WITHIN_TOLERANCE",IF(O17<0,"UNDER_DELIVERED","OVER_DELIVERED")))) -> WITHIN_TOLERANCE | S17: FULFILLED | U17: Y | V17: 2026-08-16T08:30Z
A18: TC12 | B18: ORD-1016 | C18: PR/MNL/160826/0142 | D18: 1 | E18: LEG-26081412 | F18: FDP-1201 | G18: RP-C4122 | H18: MNL | I18: PPC | J18: 9151 | K18: KG | L18: INITIAL | M18: =SUMIFS(FUEL_TICKET!$Z:$Z,FUEL_TICKET!$I:$I,$B18) -> 9152.8 | N18: =COUNTIFS(FUEL_TICKET!$I:$I,$B18) -> 1 | O18: =ROUND(M18-J18,1) -> 1.8 | P18: =IF(J18=0,"",O18/ABS(J18)) -> 0.00019669981 | Q18: =MAX(50,0.01*ABS(J18)) -> 91.51 | R18: =IF(S18="SUPERSEDED","NOT_APPLICABLE",IF(N18=0,"NOT_DELIVERED",IF(ABS(O18)<=Q18,"WITHIN_TOLERANCE",IF(O18<0,"UNDER_DELIVERED","OVER_DELIVERED")))) -> WITHIN_TOLERANCE | S18: FULFILLED | U18: Y | V18: 2026-08-16T11:15Z
A19: TC13 | B19: ORD-1017 | C19: PR/MNL/160826/0108 | D19: 1 | E19: LEG-26081413 | F19: FDP-1301 | G19: RP-C3511 | H19: MNL | I19: PPC | J19: 100192 | K19: KG | L19: INITIAL | M19: =SUMIFS(FUEL_TICKET!$Z:$Z,FUEL_TICKET!$I:$I,$B19) -> 100171.7 | N19: =COUNTIFS(FUEL_TICKET!$I:$I,$B19) -> 1 | O19: =ROUND(M19-J19,1) -> -20.3 | P19: =IF(J19=0,"",O19/ABS(J19)) -> -0.00020261099 | Q19: =MAX(50,0.01*ABS(J19)) -> 1001.92 | R19: =IF(S19="SUPERSEDED","NOT_APPLICABLE",IF(N19=0,"NOT_DELIVERED",IF(ABS(O19)<=Q19,"WITHIN_TOLERANCE",IF(O19<0,"UNDER_DELIVERED","OVER_DELIVERED")))) -> WITHIN_TOLERANCE | S19: FULFILLED | U19: Y | V19: 2026-08-16T09:25Z
A20: TC14 | B20: ORD-1018 | C20: PR/MNL/170826/0144 | D20: 1 | E20: LEG-26081414 | F20: FDP-1401 | G20: RP-C4124 | H20: MNL | I20: PPC | J20: 12351 | K20: KG | L20: INITIAL | M20: =SUMIFS(FUEL_TICKET!$Z:$Z,FUEL_TICKET!$I:$I,$B20) -> 12350.7 | N20: =COUNTIFS(FUEL_TICKET!$I:$I,$B20) -> 1 | O20: =ROUND(M20-J20,1) -> -0.3 | P20: =IF(J20=0,"",O20/ABS(J20)) -> -2.4289531e-05 | Q20: =MAX(50,0.01*ABS(J20)) -> 123.51 | R20: =IF(S20="SUPERSEDED","NOT_APPLICABLE",IF(N20=0,"NOT_DELIVERED",IF(ABS(O20)<=Q20,"WITHIN_TOLERANCE",IF(O20<0,"UNDER_DELIVERED","OVER_DELIVERED")))) -> WITHIN_TOLERANCE | S20: FULFILLED | U20: Y | V20: 2026-08-17T02:30Z
A21: TC15 | B21: ORD-1019 | C21: PR/MNL/170826/0150-L1 | D21: 1 | E21: LEG-26081415 | F21: FDP-1501 | G21: RP-C4126 | H21: MNL | I21: PPC | J21: 3545 | K21: KG | L21: INITIAL | M21: =SUMIFS(FUEL_TICKET!$Z:$Z,FUEL_TICKET!$I:$I,$B21) -> 3545 | N21: =COUNTIFS(FUEL_TICKET!$I:$I,$B21) -> 1 | O21: =ROUND(M21-J21,1) -> 0 | P21: =IF(J21=0,"",O21/ABS(J21)) -> 0 | Q21: =MAX(50,0.01*ABS(J21)) -> 50 | R21: =IF(S21="SUPERSEDED","NOT_APPLICABLE",IF(N21=0,"NOT_DELIVERED",IF(ABS(O21)<=Q21,"WITHIN_TOLERANCE",IF(O21<0,"UNDER_DELIVERED","OVER_DELIVERED")))) -> WITHIN_TOLERANCE | S21: FULFILLED | U21: Y | V21: 2026-08-17T02:20Z
A22: TC15 | B22: ORD-1020 | C22: PR/MNL/170826/0150-L2 | D22: 1 | E22: LEG-26081416 | F22: FDP-1601 | G22: RP-C4126 | H22: MNL | I22: PPC | J22: 3695 | K22: KG | L22: INITIAL | M22: =SUMIFS(FUEL_TICKET!$Z:$Z,FUEL_TICKET!$I:$I,$B22) -> 3695.3 | N22: =COUNTIFS(FUEL_TICKET!$I:$I,$B22) -> 1 | O22: =ROUND(M22-J22,1) -> 0.3 | P22: =IF(J22=0,"",O22/ABS(J22)) -> 8.1190798e-05 | Q22: =MAX(50,0.01*ABS(J22)) -> 50 | R22: =IF(S22="SUPERSEDED","NOT_APPLICABLE",IF(N22=0,"NOT_DELIVERED",IF(ABS(O22)<=Q22,"WITHIN_TOLERANCE",IF(O22<0,"UNDER_DELIVERED","OVER_DELIVERED")))) -> WITHIN_TOLERANCE | S22: FULFILLED | U22: Y | V22: 2026-08-17T11:20Z
A23: TC16 | B23: ORD-1021 | C23: PR/MNL/180826/0152 | D23: 1 | E23: LEG-26081417 | F23: FDP-1701 | G23: RP-C4128 | H23: MNL | I23: PPC | J23: 9151 | K23: KG | L23: INITIAL | M23: =SUMIFS(FUEL_TICKET!$Z:$Z,FUEL_TICKET!$I:$I,$B23) -> 9151.9 | N23: =COUNTIFS(FUEL_TICKET!$I:$I,$B23) -> 1 | O23: =ROUND(M23-J23,1) -> 0.9 | P23: =IF(J23=0,"",O23/ABS(J23)) -> 9.8349907e-05 | Q23: =MAX(50,0.01*ABS(J23)) -> 91.51 | R23: =IF(S23="SUPERSEDED","NOT_APPLICABLE",IF(N23=0,"NOT_DELIVERED",IF(ABS(O23)<=Q23,"WITHIN_TOLERANCE",IF(O23<0,"UNDER_DELIVERED","OVER_DELIVERED")))) -> WITHIN_TOLERANCE | S23: FULFILLED | U23: Y | V23: 2026-08-18T02:30Z
... A30: TC33 | B30: ORD-1028 | C30: PR/MNL/210826/0164 | D30: 1 | E30: LEG-26081424 | F30: FDP-2401 | G30: RP-C4140 | H30: MNL | I30: PPC | J30: 9151 | K30: KG | L30: INITIAL | M30: =SUMIFS(FUEL_TICKET!$Z:$Z,FUEL_TICKET!$I:$I,$B30) -> 9594 | N30: =COUNTIFS(FUEL_TICKET!$I:$I,$B30) -> 1 | O30: =ROUND(M30-J30,1) -> 443 | P30: =IF(J30=0,"",O30/ABS(J30)) -> 0.04841001 | Q30: =MAX(50,0.01*ABS(J30)) -> 91.51 | R30: =IF(S30="SUPERSEDED","NOT_APPLICABLE",IF(N30=0,"NOT_DELIVERED",IF(ABS(O30)<=Q30,"WITHIN_TOLERANCE",IF(O30<0,"UNDER_DELIVERED","OVER_DELIVERED")))) -> OVER_DELIVERED | S30: FULFILLED | U30: Y | V30: 2026-08-21T02:30Z

Sheet FUEL_TICKET
A1: FUEL_TICKET (fuel event) - PK ticket_id | UK supplier_code + station + supplier_ticket_no + uplift_date | order and plan FKs are NULLABLE
A2: TC_ID | B2: ticket_id | C2: supplier_code | D2: into_plane_agent_code | E2: station | F2: supplier_ticket_no | G2: uplift_date | H2: flight_leg_id | I2: fuel_order_id | J2: fd_fuel_plan_id | K2: registration | L2: event_type | M2: uplift_sequence | N2: is_partial | O2: fuel_grade | P2: saf_blend_pct | Q2: delivery_method | R2: bowser_id | S2: meter_start | T2: meter_end | U2: quantity_litres | V2: density_kg_per_l | W2: density_temp_c | X2: batch_coa_ref | Y2: quantity_kg_manual | Z2: quantity_kg | AA2: fob_before_kg | AB2: fob_after_kg | AC2: fob_delta_kg | AD2: recon_variance_kg | AE2: recon_status | AF2: water_check_result | AG2: uplift_start_utc | AH2: uplift_end_utc | AI2: fueller_id | AJ2: receiver_signature_ref | AK2: match_status | AL2: cost_allocation_basis | AM2: ticket_source | AN2: raw_payload_ref | AO2: created_by | AP2: created_utc | AQ2: changed_by | AR2: changed_utc | AS2: notes
A3: TC01 | B3: TK-2001 | C3: PPC | D3: PPC-IPA | E3: MNL | F3: 880101 | G3: 2026-08-14 | H3: LEG-26081401 | I3: ORD-1001 | J3: FDP-0101 | K3: RP-C4108 | L3: UPLIFT | M3: 1 | N3: N | O3: JET_A1 | P3: 0 | Q3: HYDRANT | R3: BW-11 | S3: 12000 | T3: 23446 | U3: 11446 | V3: 0.7995 | W3: 30.5 | X3: COA-PPC-8000 | Z3: =IF(U3="",Y3,ROUND(U3*V3,1)) -> 9151.1 | AA3: 2100 | AB3: 11251 | AC3: =IF(OR(AA3="",AB3=""),"",AB3-AA3) -> 9151 | AD3: =IF(AC3="","",ROUND(Z3-AC3,1)) -> 0.1 | AE3: =IF(AC3="","NOT_RECONCILED",IF(ABS(AD3)<=MAX(50,0.02*ABS(Z3)),"PASS","FAIL")) -> PASS | AF3: PASS | AG3: 2026-08-14T03:40:00Z | AH3: 2026-08-14T04:05:00Z | AI3: FL-100 | AJ3: SIG-880101 | AK3: MATCHED | AL3: FLIGHT_LEG | AM3: EDI | AN3: RAW-T9000 | AO3: IF_INTERFACE | AP3: 2026-08-14T2026-08-14T03:40:00ZZ | AS3: Baseline single uplift
A4: TC02 | B4: TK-2002 | C4: PPC | D4: PPC-IPA | E4: MNL | F4: 880115 | G4: 2026-08-14 | H4: LEG-26081402 | I4: ORD-1003 | J4: FDP-0202 | K4: RP-C4110 | L4: UPLIFT | M4: 1 | N4: N | O4: JET_A1 | P4: 0 | Q4: HYDRANT | R4: BW-11 | S4: 23446 | T4: 35310 | U4: 11864 | V4: 0.7995 | W4: 30.5 | X4: COA-PPC-8001 | Z4: =IF(U4="",Y4,ROUND(U4*V4,1)) -> 9485.3 | AA4: 2050 | AB4: 11535 | AC4: =IF(OR(AA4="",AB4=""),"",AB4-AA4) -> 9485 | AD4: =IF(AC4="","",ROUND(Z4-AC4,1)) -> 0.3 | AE4: =IF(AC4="","NOT_RECONCILED",IF(ABS(AD4)<=MAX(50,0.02*ABS(Z4)),"PASS","FAIL")) -> PASS | AF4: PASS | AG4: 2026-08-14T09:10:00Z | AH4: 2026-08-14T09:36:00Z | AI4: FL-101 | AJ4: SIG-880115 | AK4: MATCHED | AL4: FLIGHT_LEG | AM4: EDI | AN4: RAW-T9001 | AO4: IF_INTERFACE | AP4: 2026-08-14T2026-08-14T09:10:00ZZ | AS4: Uplift against amended order v2
A5: TC03 | B5: TK-2003 | C5: PPC | D5: PPC-IPA | E5: MNL | F5: 880131 | G5: 2026-08-14 | H5: LEG-26081403 | I5: ORD-1004 | J5: FDP-0301 | K5: RP-C4112 | L5: UPLIFT | M5: 1 | N5: N | O5: JET_A1 | P5: 0 | Q5: BOWSER | R5: BW-09 | S5: 40100 | T5: 51547 | U5: 11447 | V5: 0.7995 | W5: 30.5 | X5: COA-PPC-8002 | Z5: =IF(U5="",Y5,ROUND(U5*V5,1)) -> 9151.9 | AA5: 2100 | AB5: 11251 | AC5: =IF(OR(AA5="",AB5=""),"",AB5-AA5) -> 9151 | AD5: =IF(AC5="","",ROUND(Z5-AC5,1)) -> 0.9 | AE5: =IF(AC5="","NOT_RECONCILED",IF(ABS(AD5)<=MAX(50,0.02*ABS(Z5)),"PASS","FAIL")) -> PASS | AF5: PASS | AG5: 2026-08-14T12:20:00Z | AH5: 2026-08-14T12:48:00Z | AI5: FL-102 | AJ5: SIG-880131 | AK5: MATCHED | AL5: FLIGHT_LEG | AM5: EDI | AN5: RAW-T9002 | AO5: IF_INTERFACE | AP5: 2026-08-14T2026-08-14T12:20:00ZZ | AS5: Initial uplift against plan v1
A6: TC03 | B6: TK-2004 | C6: PPC | D6: PPC-IPA | E6: MNL | F6: 880140 | G6: 2026-08-14 | H6: LEG-26081403 | I6: ORD-1005 | J6: FDP-0302 | K6: RP-C4112 | L6: UPLIFT | M6: 2 | N6: N | O6: JET_A1 | P6: 0 | Q6: BOWSER | R6: BW-09 | S6: 51547 | T6: 52481 | U6: 934 | V6: 0.7995 | W6: 30.5 | X6: COA-PPC-8003 | Z6: =IF(U6="",Y6,ROUND(U6*V6,1)) -> 746.7 | AA6: 11251 | AC6: =IF(OR(AA6="",AB6=""),"",AB6-AA6) | AD6: =IF(AC6="","",ROUND(Z6-AC6,1)) | AE6: =IF(AC6="","NOT_RECONCILED",IF(ABS(AD6)<=MAX(50,0.02*ABS(Z6)),"PASS","FAIL")) -> NOT_RECONCILED | AF6: PASS | AG6: 2026-08-14T13:50:00Z | AH6: 2026-08-14T14:02:00Z | AI6: FL-103 | AJ6: SIG-880140 | AK6: MATCHED | AL6: FLIGHT_LEG | AM6: EDI | AN6: RAW-T9003 | AO6: IF_INTERFACE | AP6: 2026-08-14T2026-08-14T13:50:00ZZ | AS6: Top-up after re-plan; delta only
A7: TC04 | B7: TK-2005 | C7: PPC | D7: PPC-IPA | E7: MNL | F7: 880155 | G7: 2026-08-14 | I7: ORD-1006 | J7: FDP-0401 | K7: RP-C4108 | L7: UPLIFT | M7: 1 | N7: N | O7: JET_A1 | P7: 0 | Q7: HYDRANT | R7: BW-14 | S7: 60000 | T7: 71447 | U7: 11447 | V7: 0.7995 | W7: 30.5 | X7: COA-PPC-8004 | Z7: =IF(U7="",Y7,ROUND(U7*V7,1)) -> 9151.9 | AA7: 2100 | AB7: 11251 | AC7: =IF(OR(AA7="",AB7=""),"",AB7-AA7) -> 9151 | AD7: =IF(AC7="","",ROUND(Z7-AC7,1)) -> 0.9 | AE7: =IF(AC7="","NOT_RECONCILED",IF(ABS(AD7)<=MAX(50,0.02*ABS(Z7)),"PASS","FAIL")) -> PASS | AF7: PASS | AG7: 2026-08-14T15:05:00Z | AH7: 2026-08-14T15:33:00Z | AI7: FL-104 | AJ7: SIG-880155 | AK7: UNMATCHED | AL7: AIRCRAFT | AM7: EDI | AN7: RAW-T9004 | AO7: IF_INTERFACE | AP7: 2026-08-14T2026-08-14T15:05:00ZZ | AS7: Fuel stays with original tail after swap
A8: TC04 | B8: TK-2006 | C8: PPC | D8: PPC-IPA | E8: MNL | F8: 880162 | G8: 2026-08-14 | H8: LEG-26081404 | I8: ORD-1007 | J8: FDP-0402 | K8: RP-C4109 | L8: UPLIFT | M8: 1 | N8: N | O8: JET_A1 | P8: 0 | Q8: HYDRANT | R8: BW-14 | S8: 71447 | T8: 79509 | U8: 8062 | V8: 0.7995 | W8: 30.5 | X8: COA-PPC-8005 | Z8: =IF(U8="",Y8,ROUND(U8*V8,1)) -> 6445.6 | AA8: 4900 | AB8: 11346 | AC8: =IF(OR(AA8="",AB8=""),"",AB8-AA8) -> 6446 | AD8: =IF(AC8="","",ROUND(Z8-AC8,1)) -> -0.4 | AE8: =IF(AC8="","NOT_RECONCILED",IF(ABS(AD8)<=MAX(50,0.02*ABS(Z8)),"PASS","FAIL")) -> PASS | AF8: PASS | AG8: 2026-08-14T17:20:00Z | AH8: 2026-08-14T17:41:00Z | AI8: FL-105 | AJ8: SIG-880162 | AK8: MATCHED | AL8: FLIGHT_LEG | AM8: EDI | AN8: RAW-T9005 | AO8: IF_INTERFACE | AP8: 2026-08-14T2026-08-14T17:20:00ZZ | AS8: Uplift to replacement tail
A9: TC05 | B9: TK-2007 | C9: PPC | D9: PPC-IPA | E9: MNL | F9: 880201 | G9: 2026-08-14 | H9: LEG-26081405 | I9: ORD-1008 | J9: FDP-0501 | K9: RP-C3505 | L9: UPLIFT | M9: 1 | N9: Y | O9: JET_A1 | P9: 0 | Q9: HYDRANT | R9: BW-14 | S9: 4118 | T9: 79362 | U9: 75244 | V9: 0.7982 | W9: 30.5 | X9: COA-PPC-8006 | Z9: =IF(U9="",Y9,ROUND(U9*V9,1)) -> 60059.8 | AA9: 5200 | AB9: 65260 | AC9: =IF(OR(AA9="",AB9=""),"",AB9-AA9) -> 60060 | AD9: =IF(AC9="","",ROUND(Z9-AC9,1)) -> -0.2 | AE9: =IF(AC9="","NOT_RECONCILED",IF(ABS(AD9)<=MAX(50,0.02*ABS(Z9)),"PASS","FAIL")) -> PASS | AF9: PASS | AG9: 2026-08-14T09:55:00Z | AH9: 2026-08-14T11:05:00Z | AI9: FL-106 | AJ9: SIG-880201 | AK9: MATCHED | AL9: FLIGHT_LEG | AM9: EDI | AN9: RAW-T9006 | AO9: IF_INTERFACE | AP9: 2026-08-14T2026-08-14T09:55:00ZZ | AS9: Bowser 1 of 2
A10: TC05 | B10: TK-2008 | C10: PPC | D10: PPC-IPA | E10: MNL | F10: 880202 | G10: 2026-08-14 | H10: LEG-26081405 | I10: ORD-1008 | J10: FDP-0501 | K10: RP-C3505 | L10: UPLIFT | M10: 2 | N10: N | O10: JET_A1 | P10: 0 | Q10: BOWSER | R10: BW-09 | S10: 291770 | T10: 342048 | U10: 50278 | V10: 0.7982 | W10: 30.5 | X10: COA-PPC-8007 | Z10: =IF(U10="",Y10,ROUND(U10*V10,1)) -> 40131.9 | AA10: 65260 | AB10: 105392 | AC10: =IF(OR(AA10="",AB10=""),"",AB10-AA10) -> 40132 | AD10: =IF(AC10="","",ROUND(Z10-AC10,1)) -> -0.1 | AE10: =IF(AC10="","NOT_RECONCILED",IF(ABS(AD10)<=MAX(50,0.02*ABS(Z10)),"PASS","FAIL")) -> PASS | AF10: PASS | AG10: 2026-08-14T11:20:00Z | AH10: 2026-08-14T12:15:00Z | AI10: FL-107 | AJ10: SIG-880202 | AK10: MATCHED | AL10: FLIGHT_LEG | AM10: EDI | AN10: RAW-T9007 | AO10: IF_INTERFACE | AP10: 2026-08-14T2026-08-14T11:20:00ZZ | AS10: Bowser 2 of 2; same order
A11: TC06 | B11: TK-2009 | C11: PPC | D11: PPC-IPA | E11: MNL | F11: 880231 | G11: 2026-08-15 | H11: LEG-26081406 | I11: ORD-1009 | J11: FDP-0601 | K11: RP-C3507 | L11: UPLIFT | M11: 1 | N11: Y | O11: JET_A1 | P11: 0 | Q11: HYDRANT | R11: BW-14 | S11: 100000 | T11: 175244 | U11: 75244 | V11: 0.7982 | W11: 30.5 | X11: COA-PPC-8008 | Z11: =IF(U11="",Y11,ROUND(U11*V11,1)) -> 60059.8 | AA11: 5200 | AB11: 65260 | AC11: =IF(OR(AA11="",AB11=""),"",AB11-AA11) -> 60060 | AD11: =IF(AC11="","",ROUND(Z11-AC11,1)) -> -0.2 | AE11: =IF(AC11="","NOT_RECONCILED",IF(ABS(AD11)<=MAX(50,0.02*ABS(Z11)),"PASS","FAIL")) -> PASS | AF11: PASS | AG11: 2026-08-15T09:55:00Z | AH11: 2026-08-15T11:05:00Z | AI11: FL-108 | AJ11: SIG-880231 | AK11: MATCHED | AL11: FLIGHT_LEG | AM11: EDI | AN11: RAW-T9008 | AO11: IF_INTERFACE | AP11: 2026-08-15T2026-08-15T09:55:00ZZ | AS11: Bowser 1; interrupted at 11:05
A12: TC06 | B12: TK-2010 | C12: PPC | D12: PPC-IPA | E12: MNL | F12: 880232 | G12: 2026-08-15 | H12: LEG-26081406 | I12: ORD-1009 | J12: FDP-0601 | K12: RP-C3507 | L12: UPLIFT | M12: 2 | N12: N | O12: JET_A1 | P12: 0 | Q12: BOWSER | R12: BW-09 | S12: 400000 | T12: 405430 | U12: 5430 | V12: 0.7982 | W12: 30.5 | X12: COA-PPC-8009 | Z12: =IF(U12="",Y12,ROUND(U12*V12,1)) -> 4334.2 | AA12: 65260 | AB12: 69594 | AC12: =IF(OR(AA12="",AB12=""),"",AB12-AA12) -> 4334 | AD12: =IF(AC12="","",ROUND(Z12-AC12,1)) -> 0.2 | AE12: =IF(AC12="","NOT_RECONCILED",IF(ABS(AD12)<=MAX(50,0.02*ABS(Z12)),"PASS","FAIL")) -> PASS | AF12: PASS | AG12: 2026-08-15T11:20:00Z | AH12: 2026-08-15T11:38:00Z | AI12: FL-109 | AJ12: SIG-880232 | AK12: MATCHED | AL12: FLIGHT_LEG | AM12: EDI | AN12: RAW-T9009 | AO12: IF_INTERFACE | AP12: 2026-08-15T2026-08-15T11:20:00ZZ | AS12: Partial before re-plan; order under-delivered
A13: TC06 | B13: TK-2011 | C13: PPC | D13: PPC-IPA | E13: MNL | F13: 880255 | G13: 2026-08-15 | H13: LEG-26081406 | I13: ORD-1010 | J13: FDP-0602 | K13: RP-C3507 | L13: UPLIFT | M13: 3 | N13: N | O13: JET_A1 | P13: 0 | Q13: BOWSER | R13: BW-09 | S13: 405430 | T13: 453724 | U13: 48294 | V13: 0.7982 | W13: 30.5 | X13: COA-PPC-8010 | Z13: =IF(U13="",Y13,ROUND(U13*V13,1)) -> 38548.3 | AA13: 69594 | AB13: 108142 | AC13: =IF(OR(AA13="",AB13=""),"",AB13-AA13) -> 38548 | AD13: =IF(AC13="","",ROUND(Z13-AC13,1)) -> 0.3 | AE13: =IF(AC13="","NOT_RECONCILED",IF(ABS(AD13)<=MAX(50,0.02*ABS(Z13)),"PASS","FAIL")) -> PASS | AF13: PASS | AG13: 2026-08-15T12:04:00Z | AH13: 2026-08-15T12:58:00Z | AI13: FL-110 | AJ13: SIG-880255 | AK13: MATCHED | AL13: FLIGHT_LEG | AM13: EDI | AN13: RAW-T9010 | AO13: IF_INTERFACE | AP13: 2026-08-15T2026-08-15T12:04:00ZZ | AS13: Balance under new order
A14: TC07 | B14: TK-2012 | C14: PPC | D14: PPC-IPA | E14: MNL | F14: 880301 | G14: 2026-08-15 | H14: LEG-26081407 | I14: ORD-1011 | J14: FDP-0701 | K14: RP-C4114 | L14: UPLIFT | M14: 1 | N14: N | O14: JET_A1 | P14: 0 | Q14: HYDRANT | R14: BW-11 | S14: 90000 | T14: 101447 | U14: 11447 | V14: 0.7995 | W14: 30.5 | X14: COA-PPC-8011 | Z14: =IF(U14="",Y14,ROUND(U14*V14,1)) -> 9151.9 | AA14: 2100 | AB14: 11251 | AC14: =IF(OR(AA14="",AB14=""),"",AB14-AA14) -> 9151 | AD14: =IF(AC14="","",ROUND(Z14-AC14,1)) -> 0.9 | AE14: =IF(AC14="","NOT_RECONCILED",IF(ABS(AD14)<=MAX(50,0.02*ABS(Z14)),"PASS","FAIL")) -> PASS | AF14: PASS | AG14: 2026-08-15T03:40:00Z | AH14: 2026-08-15T04:08:00Z | AI14: FL-111 | AJ14: SIG-880301 | AK14: MATCHED | AL14: AIRCRAFT | AM14: EDI | AN14: RAW-T9011 | AO14: IF_INTERFACE | AP14: 2026-08-15T2026-08-15T03:40:00ZZ | AS14: Flight cancelled after uplift; fuel billable
A15: TC08 | B15: TK-2013 | C15: PPC | D15: PPC-IPA | E15: MNL | F15: 880321 | G15: 2026-08-15 | H15: LEG-26081408 | I15: ORD-1012 | J15: FDP-0801 | K15: RP-C4116 | L15: UPLIFT | M15: 1 | N15: N | O15: JET_A1 | P15: 0 | Q15: HYDRANT | R15: BW-11 | S15: 101447 | T15: 112894 | U15: 11447 | V15: 0.7995 | W15: 30.5 | X15: COA-PPC-8012 | Z15: =IF(U15="",Y15,ROUND(U15*V15,1)) -> 9151.9 | AA15: 2100 | AB15: 11251 | AC15: =IF(OR(AA15="",AB15=""),"",AB15-AA15) -> 9151 | AD15: =IF(AC15="","",ROUND(Z15-AC15,1)) -> 0.9 | AE15: =IF(AC15="","NOT_RECONCILED",IF(ABS(AD15)<=MAX(50,0.02*ABS(Z15)),"PASS","FAIL")) -> PASS | AF15: PASS | AG15: 2026-08-15T09:20:00Z | AH15: 2026-08-15T09:48:00Z | AI15: FL-112 | AJ15: SIG-880321 | AK15: MATCHED | AL15: FLIGHT_LEG | AM15: EDI | AN15: RAW-T9012 | AO15: IF_INTERFACE | AP15: 2026-08-15T2026-08-15T09:20:00ZZ | AS15: Initial uplift
A16: TC08 | B16: TK-2014 | C16: PPC | D16: PPC-IPA | E16: MNL | F16: 880340 | G16: 2026-08-15 | H16: LEG-26081408 | I16: ORD-1013 | J16: FDP-0802 | K16: RP-C4116 | L16: DEFUEL | M16: 2 | N16: N | O16: JET_A1 | P16: 0 | Q16: HYDRANT | R16: BW-11 | S16: 112894 | T16: 110898 | U16: -1996 | V16: 0.7995 | W16: 30.5 | X16: COA-PPC-8013 | Z16: =IF(U16="",Y16,ROUND(U16*V16,1)) -> -1595.8 | AA16: 11251 | AB16: 9655 | AC16: =IF(OR(AA16="",AB16=""),"",AB16-AA16) -> -1596 | AD16: =IF(AC16="","",ROUND(Z16-AC16,1)) -> 0.2 | AE16: =IF(AC16="","NOT_RECONCILED",IF(ABS(AD16)<=MAX(50,0.02*ABS(Z16)),"PASS","FAIL")) -> PASS | AF16: PASS | AG16: 2026-08-15T12:10:00Z | AH16: 2026-08-15T12:52:00Z | AI16: FL-113 | AJ16: SIG-880340 | AK16: MATCHED | AL16: FLIGHT_LEG | AM16: EDI | AN16: RAW-T9013 | AO16: IF_INTERFACE | AP16: 2026-08-15T2026-08-15T12:10:00ZZ | AS16: Ramp return; shorter re-route so fuel removed
A17: TC09 | B17: TK-2015 | C17: PPC | D17: PPC-IPA | E17: MNL | F17: 880361 | G17: 2026-08-15 | H17: LEG-26081409 | I17: ORD-1014 | J17: FDP-0901 | K17: RP-C3509 | L17: UPLIFT | M17: 1 | N17: N | O17: JET_A1 | P17: 0 | Q17: HYDRANT | R17: BW-14 | S17: 500000 | T17: 625493 | U17: 125493 | V17: 0.7982 | W17: 30.5 | X17: COA-PPC-8014 | Z17: =IF(U17="",Y17,ROUND(U17*V17,1)) -> 100168.5 | AA17: 5200 | AB17: 105392 | AC17: =IF(OR(AA17="",AB17=""),"",AB17-AA17) -> 100192 | AD17: =IF(AC17="","",ROUND(Z17-AC17,1)) -> -23.5 | AE17: =IF(AC17="","NOT_RECONCILED",IF(ABS(AD17)<=MAX(50,0.02*ABS(Z17)),"PASS","FAIL")) -> PASS | AF17: PASS | AG17: 2026-08-15T09:55:00Z | AH17: 2026-08-15T11:40:00Z | AI17: FL-114 | AJ17: SIG-880361 | AK17: MATCHED | AL17: FLIGHT_LEG | AM17: EDI | AN17: RAW-T9014 | AO17: IF_INTERFACE | AP17: 2026-08-15T2026-08-15T09:55:00ZZ | AS17: Full uplift before departure
A18: TC09 | B18: TK-2016 | F18: JETT-0901 | G18: 2026-08-15 | H18: LEG-26081409 | J18: FDP-0901 | K18: RP-C3509 | L18: JETTISON | M18: 2 | N18: N | O18: JET_A1 | P18: 0 | Y18: -21800 | Z18: =IF(U18="",Y18,ROUND(U18*V18,1)) -> -21800 | AA18: 96100 | AB18: 74300 | AC18: =IF(OR(AA18="",AB18=""),"",AB18-AA18) -> -21800 | AD18: =IF(AC18="","",ROUND(Z18-AC18,1)) -> 0 | AE18: =IF(AC18="","NOT_RECONCILED",IF(ABS(AD18)<=MAX(50,0.02*ABS(Z18)),"PASS","FAIL")) -> PASS | AG18: 2026-08-15T14:05:00Z | AH18: 2026-08-15T14:32:00Z | AJ18: FLT-CREW | AK18: N_A | AL18: FLIGHT_LEG | AM18: MANUAL | AN18: RAW-T9015 | AO18: OPS_CONTROLLER | AP18: 2026-08-15T2026-08-15T14:05:00ZZ | AS18: Air return; jettison to reach MLW. No meter, FQIS only
A19: TC10 | B19: TK-2017 | C19: PPC | D19: PPC-IPA | E19: MNL | F19: 880401 | G19: 2026-08-16 | H19: LEG-26081410 | K19: RP-C4118 | L19: UPLIFT | M19: 1 | N19: N | O19: JET_A1 | P19: 0 | Q19: HYDRANT | R19: BW-11 | S19: 200000 | T19: 200794 | U19: 794 | V19: 0.7995 | W19: 30.5 | X19: COA-PPC-8016 | Z19: =IF(U19="",Y19,ROUND(U19*V19,1)) -> 634.8 | AA19: 11251 | AB19: 11886 | AC19: =IF(OR(AA19="",AB19=""),"",AB19-AA19) -> 635 | AD19: =IF(AC19="","",ROUND(Z19-AC19,1)) -> -0.2 | AE19: =IF(AC19="","NOT_RECONCILED",IF(ABS(AD19)<=MAX(50,0.02*ABS(Z19)),"PASS","FAIL")) -> PASS | AF19: PASS | AG19: 2026-08-16T05:48:00Z | AH19: 2026-08-16T05:55:00Z | AI19: FL-116 | AJ19: SIG-880401 | AK19: UNMATCHED | AL19: FLIGHT_LEG | AM19: MANUAL | AN19: RAW-T9016 | AO19: STATION_OPS | AP19: 2026-08-16T2026-08-16T05:48:00ZZ | AS19: Verbal post-freeze top-up; no order raised
A20: TC11 | B20: TK-2018 | C20: PPC | D20: PPC-IPA | E20: MNL | F20: 880421 | G20: 2026-08-16 | H20: LEG-26081411 | I20: ORD-1015 | J20: FDP-1102 | K20: RP-C4120 | L20: UPLIFT | M20: 1 | N20: N | O20: JET_A1 | P20: 0 | Q20: HYDRANT | R20: BW-11 | S20: 200794 | T20: 213365 | U20: 12571 | V20: 0.7995 | W20: 30.5 | X20: COA-PPC-8017 | Z20: =IF(U20="",Y20,ROUND(U20*V20,1)) -> 10050.5 | AA20: 2100 | AB20: 12151 | AC20: =IF(OR(AA20="",AB20=""),"",AB20-AA20) -> 10051 | AD20: =IF(AC20="","",ROUND(Z20-AC20,1)) -> -0.5 | AE20: =IF(AC20="","NOT_RECONCILED",IF(ABS(AD20)<=MAX(50,0.02*ABS(Z20)),"PASS","FAIL")) -> PASS | AF20: PASS | AG20: 2026-08-16T09:15:00Z | AH20: 2026-08-16T09:46:00Z | AI20: FL-117 | AJ20: SIG-880421 | AK20: MATCHED | AL20: FLIGHT_LEG | AM20: EDI | AN20: RAW-T9017 | AO20: IF_INTERFACE | AP20: 2026-08-16T2026-08-16T09:15:00ZZ | AS20: Includes 900 kg commander discretionary
A21: TC12 | B21: TK-2019 | C21: PPC | D21: PPC-IPA | E21: MNL | F21: 880441 | G21: 2026-08-16 | H21: LEG-26081412 | I21: ORD-1016 | J21: FDP-1201 | K21: RP-C4122 | L21: UPLIFT | M21: 1 | N21: N | O21: JET_A1 | P21: 0 | Q21: BOWSER | R21: BW-09 | S21: 500000 | T21: 511353 | U21: 11353 | V21: 0.8062 | W21: 30.5 | X21: COA-PPC-8018 | Z21: =IF(U21="",Y21,ROUND(U21*V21,1)) -> 9152.8 | AA21: 2100 | AB21: 11190 | AC21: =IF(OR(AA21="",AB21=""),"",AB21-AA21) -> 9090 | AD21: =IF(AC21="","",ROUND(Z21-AC21,1)) -> 62.8 | AE21: =IF(AC21="","NOT_RECONCILED",IF(ABS(AD21)<=MAX(50,0.02*ABS(Z21)),"PASS","FAIL")) -> PASS | AF21: PASS | AG21: 2026-08-16T13:20:00Z | AH21: 2026-08-16T13:49:00Z | AI21: FL-118 | AJ21: SIG-880441 | AK21: MATCHED | AL21: FLIGHT_LEG | AM21: EDI | AN21: RAW-T9018 | AO21: IF_INTERFACE | AP21: 2026-08-16T2026-08-16T13:20:00ZZ | AS21: Delivered density above plan assumption
A22: TC13 | B22: TK-2020 | C22: PPC | D22: PPC-IPA | E22: MNL | F22: 880481 | G22: 2026-08-16 | H22: LEG-26081413 | I22: ORD-1017 | J22: FDP-1301 | K22: RP-C3511 | L22: UPLIFT | M22: 1 | N22: N | O22: JET_A1 | P22: 0 | Q22: HYDRANT | R22: BW-14 | S22: 700000 | T22: 825497 | U22: 125497 | V22: 0.7982 | W22: 30.5 | X22: COA-PPC-8019 | Z22: =IF(U22="",Y22,ROUND(U22*V22,1)) -> 100171.7 | AA22: 5200 | AB22: 105392 | AC22: =IF(OR(AA22="",AB22=""),"",AB22-AA22) -> 100192 | AD22: =IF(AC22="","",ROUND(Z22-AC22,1)) -> -20.3 | AE22: =IF(AC22="","NOT_RECONCILED",IF(ABS(AD22)<=MAX(50,0.02*ABS(Z22)),"PASS","FAIL")) -> PASS | AF22: PASS | AG22: 2026-08-16T09:55:00Z | AH22: 2026-08-16T11:40:00Z | AI22: FL-119 | AJ22: SIG-880481 | AK22: MATCHED | AL22: FLIGHT_LEG | AM22: EDI | AN22: RAW-T9019 | AO22: IF_INTERFACE | AP22: 2026-08-16T2026-08-16T09:55:00ZZ | AS22: Planned uplift at MNL before diversion
A23: TC13 | B23: TK-2020B | C23: SHL | D23: SHL-IPA | E23: CEB | F23: CB-7712 | G23: 2026-08-16 | H23: LEG-26081413 | K23: RP-C3511 | L23: UPLIFT | M23: 2 | N23: N | O23: JET_A1 | P23: 0 | Q23: BOWSER | R23: BW-03 | S23: 8000 | T23: 32056 | U23: 24056 | V23: 0.7975 | W23: 28.4 | X23: COA-SHL-4471 | Z23: =IF(U23="",Y23,ROUND(U23*V23,1)) -> 19184.7 | AA23: 18400 | AB23: 37600 | AC23: =IF(OR(AA23="",AB23=""),"",AB23-AA23) -> 19200 | AD23: =IF(AC23="","",ROUND(Z23-AC23,1)) -> -15.3 | AE23: =IF(AC23="","NOT_RECONCILED",IF(ABS(AD23)<=MAX(50,0.02*ABS(Z23)),"PASS","FAIL")) -> PASS | AF23: PASS | AG23: 2026-08-16T20:15:00Z | AH23: 2026-08-16T21:02:00Z | AI23: FL-120 | AJ23: SIG-CB-7712 | AK23: UNMATCHED | AL23: FLIGHT_LEG | AM23: OCR | AN23: RAW-T9020 | AO23: STATION_OPS | AP23: 2026-08-16T2026-08-16T20:15:00ZZ | AS23: Diversion station; no contract order in place
A24: TC14 | B24: TK-2021 | C24: PPC | D24: PPC-IPA | E24: MNL | F24: 880501 | G24: 2026-08-17 | H24: LEG-26081414 | I24: ORD-1018 | J24: FDP-1401 | K24: RP-C4124 | L24: UPLIFT | M24: 1 | N24: N | O24: JET_A1 | P24: 5 | Q24: HYDRANT | R24: BW-11 | S24: 300000 | T24: 315448 | U24: 15448 | V24: 0.7995 | W24: 30.5 | X24: COA-PPC-SAF-118 | Z24: =IF(U24="",Y24,ROUND(U24*V24,1)) -> 12350.7 | AA24: 2100 | AB24: 14451 | AC24: =IF(OR(AA24="",AB24=""),"",AB24-AA24) -> 12351 | AD24: =IF(AC24="","",ROUND(Z24-AC24,1)) -> -0.3 | AE24: =IF(AC24="","NOT_RECONCILED",IF(ABS(AD24)<=MAX(50,0.02*ABS(Z24)),"PASS","FAIL")) -> PASS | AF24: PASS | AG24: 2026-08-17T03:40:00Z | AH24: 2026-08-17T04:18:00Z | AI24: FL-121 | AJ24: SIG-880501 | AK24: MATCHED | AL24: FLIGHT_LEG | AM24: EDI | AN24: RAW-T9021 | AO24: IF_INTERFACE | AP24: 2026-08-17T2026-08-17T03:40:00ZZ | AS24: Includes 3200 kg tankering
A25: TC15 | B25: TK-2022 | C25: PPC | D25: PPC-IPA | E25: MNL | F25: 880521 | G25: 2026-08-17 | H25: LEG-26081415 | I25: ORD-1019 | J25: FDP-1501 | K25: RP-C4126 | L25: UPLIFT | M25: 1 | N25: N | O25: JET_A1 | P25: 0 | Q25: HYDRANT | R25: BW-11 | S25: 315448 | T25: 319882 | U25: 4434 | V25: 0.7995 | W25: 30.5 | X25: COA-PPC-8022 | Z25: =IF(U25="",Y25,ROUND(U25*V25,1)) -> 3545 | AA25: 1800 | AB25: 5345 | AC25: =IF(OR(AA25="",AB25=""),"",AB25-AA25) -> 3545 | AD25: =IF(AC25="","",ROUND(Z25-AC25,1)) -> 0 | AE25: =IF(AC25="","NOT_RECONCILED",IF(ABS(AD25)<=MAX(50,0.02*ABS(Z25)),"PASS","FAIL")) -> PASS | AF25: PASS | AG25: 2026-08-17T04:45:00Z | AH25: 2026-08-17T05:00:00Z | AI25: FL-122 | AJ25: SIG-880521 | AK25: MATCHED | AL25: FLIGHT_LEG | AM25: EDI | AN25: RAW-T9022 | AO25: IF_INTERFACE | AP25: 2026-08-17T2026-08-17T04:45:00ZZ | AS25: Rotation leg 1
A26: TC15 | B26: TK-2023 | C26: PPC | D26: PPC-IPA | E26: MNL | F26: 880540 | G26: 2026-08-17 | H26: LEG-26081416 | I26: ORD-1020 | J26: FDP-1601 | K26: RP-C4126 | L26: UPLIFT | M26: 1 | N26: N | O26: JET_A1 | P26: 0 | Q26: HYDRANT | R26: BW-11 | S26: 319882 | T26: 324504 | U26: 4622 | V26: 0.7995 | W26: 30.5 | X26: COA-PPC-8023 | Z26: =IF(U26="",Y26,ROUND(U26*V26,1)) -> 3695.3 | AA26: 1650 | AB26: 5345 | AC26: =IF(OR(AA26="",AB26=""),"",AB26-AA26) -> 3695 | AD26: =IF(AC26="","",ROUND(Z26-AC26,1)) -> 0.3 | AE26: =IF(AC26="","NOT_RECONCILED",IF(ABS(AD26)<=MAX(50,0.02*ABS(Z26)),"PASS","FAIL")) -> PASS | AF26: PASS | AG26: 2026-08-17T13:45:00Z | AH26: 2026-08-17T14:01:00Z | AI26: FL-123 | AJ26: SIG-880540 | AK26: MATCHED | AL26: FLIGHT_LEG | AM26: EDI | AN26: RAW-T9023 | AO26: IF_INTERFACE | AP26: 2026-08-17T2026-08-17T13:45:00ZZ | AS26: Rotation leg 2; same flight number and date
A27: TC16 | B27: TK-2024 | C27: PPC | D27: PPC-IPA | E27: MNL | F27: 880601 | G27: 2026-08-18 | H27: LEG-26081417 | I27: ORD-1021 | J27: FDP-1701 | K27: RP-C4128 | L27: UPLIFT | M27: 1 | N27: N | O27: JET_A1 | P27: 0 | Q27: HYDRANT | R27: BW-11 | S27: 324504 | T27: 335951 | U27: 11447 | V27: 0.7995 | W27: 30.5 | X27: COA-PPC-8024 | Z27: =IF(U27="",Y27,ROUND(U27*V27,1)) -> 9151.9 | AA27: 2100 | AB27: 11215 | AC27: =IF(OR(AA27="",AB27=""),"",AB27-AA27) -> 9115 | AD27: =IF(AC27="","",ROUND(Z27-AC27,1)) -> 36.9 | AE27: =IF(AC27="","NOT_RECONCILED",IF(ABS(AD27)<=MAX(50,0.02*ABS(Z27)),"PASS","FAIL")) -> PASS | AF27: PASS | AG27: 2026-08-18T03:40:00Z | AH27: 2026-08-18T04:06:00Z | AI27: FL-124 | AJ27: SIG-880601 | AK27: MATCHED | AL27: FLIGHT_LEG | AM27: EDI | AN27: RAW-T9024 | AO27: IF_INTERFACE | AP27: 2026-08-18T2026-08-18T03:40:00ZZ | AS27: FQIS 37 kg under metered mass; inside tolerance
A28: TC17 | B28: TK-2025 | C28: PPC | D28: PPC-IPA | E28: MNL | F28: 880621 | G28: 2026-08-18 | H28: LEG-26081418 | I28: ORD-1022 | J28: FDP-1801 | K28: RP-C4130 | L28: UPLIFT | M28: 1 | N28: N | O28: JET_A1 | P28: 0 | Q28: HYDRANT | R28: BW-17 | S28: 41000 | T28: 52447 | U28: 11447 | V28: 0.7995 | W28: 30.5 | X28: COA-PPC-8025 | Z28: =IF(U28="",Y28,ROUND(U28*V28,1)) -> 9151.9 | AA28: 2100 | AB28: 10951 | AC28: =IF(OR(AA28="",AB28=""),"",AB28-AA28) -> 8851 | AD28: =IF(AC28="","",ROUND(Z28-AC28,1)) -> 300.9 | AE28: =IF(AC28="","NOT_RECONCILED",IF(ABS(AD28)<=MAX(50,0.02*ABS(Z28)),"PASS","FAIL")) -> FAIL | AF28: PASS | AG28: 2026-08-18T09:10:00Z | AH28: 2026-08-18T09:38:00Z | AI28: FL-125 | AJ28: SIG-880621 | AK28: MATCHED | AL28: FLIGHT_LEG | AM28: EDI | AN28: RAW-T9025 | AO28: IF_INTERFACE | AP28: 2026-08-18T2026-08-18T09:10:00ZZ | AS28: FQIS 301 kg under metered mass; investigate meter or leak
A29: TC18 | B29: TK-2026 | C29: PPC | D29: PPC-IPA | E29: MNL | F29: 880641 | G29: 2026-08-18 | H29: LEG-26081419 | I29: ORD-1023 | J29: FDP-1901 | K29: RP-C4132 | L29: UPLIFT | M29: 1 | N29: N | O29: JET_A1 | P29: 0 | Q29: HYDRANT | R29: BW-17 | S29: 52447 | T29: 64447 | U29: 12000 | V29: 0.8 | W29: 30.5 | X29: COA-PPC-8891 | Z29: =IF(U29="",Y29,ROUND(U29*V29,1)) -> 9600 | AA29: 2100 | AB29: 11520 | AC29: =IF(OR(AA29="",AB29=""),"",AB29-AA29) -> 9420 | AD29: =IF(AC29="","",ROUND(Z29-AC29,1)) -> 180 | AE29: =IF(AC29="","NOT_RECONCILED",IF(ABS(AD29)<=MAX(50,0.02*ABS(Z29)),"PASS","FAIL")) -> PASS | AF29: PASS | AG29: 2026-08-18T13:20:00Z | AH29: 2026-08-18T13:50:00Z | AI29: FL-126 | AJ29: SIG-880641 | AK29: MATCHED | AL29: FLIGHT_LEG | AM29: EDI | AN29: RAW-T9026 | AO29: IF_INTERFACE | AP29: 2026-08-18T2026-08-18T13:20:00ZZ | AS29: Billed on default density 0.8000; batch certificate says 0.7850
A30: TC19 | B30: TK-2027 | C30: PPC | D30: PPC-IPA | E30: MNL | F30: 880661 | G30: 2026-08-19 | H30: LEG-26081420 | I30: ORD-1024 | J30: FDP-2001 | K30: RP-C4134 | L30: UPLIFT | M30: 2 | N30: N | O30: JET_A1 | P30: 0 | Q30: HYDRANT | R30: BW-11 | S30: 335951 | T30: 336451 | U30: 500 | V30: 0.7995 | W30: 30.5 | X30: COA-PPC-8027 | Z30: =IF(U30="",Y30,ROUND(U30*V30,1)) -> 399.8 | AA30: 11000 | AB30: 11430 | AC30: =IF(OR(AA30="",AB30=""),"",AB30-AA30) -> 430 | AD30: =IF(AC30="","",ROUND(Z30-AC30,1)) -> -30.2 | AE30: =IF(AC30="","NOT_RECONCILED",IF(ABS(AD30)<=MAX(50,0.02*ABS(Z30)),"PASS","FAIL")) -> PASS | AF30: PASS | AG30: 2026-08-19T05:20:00Z | AH30: 2026-08-19T05:26:00Z | AI30: FL-127 | AJ30: SIG-880661 | AK30: MATCHED | AL30: FLIGHT_LEG | AM30: EDI | AN30: RAW-T9027 | AO30: IF_INTERFACE | AP30: 2026-08-19T2026-08-19T05:20:00ZZ | AS30: Percentage breach but absolute variance below floor
A31: TC20 | B31: TK-2028 | C31: PPC | D31: PPC-IPA | E31: MNL | F31: 880681 | G31: 2026-08-19 | H31: LEG-26081421 | I31: ORD-1025 | J31: FDP-2101 | K31: RP-C4136 | L31: UPLIFT | M31: 1 | N31: N | O31: JET_A1 | P31: 0 | Q31: HYDRANT | R31: BW-11 | S31: 336451 | T31: 347898 | U31: 11447 | V31: 0.7995 | W31: 30.5 | X31: COA-PPC-8028 | Z31: =IF(U31="",Y31,ROUND(U31*V31,1)) -> 9151.9 | AC31: =IF(OR(AA31="",AB31=""),"",AB31-AA31) | AD31: =IF(AC31="","",ROUND(Z31-AC31,1)) | AE31: =IF(AC31="","NOT_RECONCILED",IF(ABS(AD31)<=MAX(50,0.02*ABS(Z31)),"PASS","FAIL")) -> NOT_RECONCILED | AF31: PASS | AG31: 2026-08-19T09:10:00Z | AH31: 2026-08-19T09:37:00Z | AI31: FL-128 | AJ31: SIG-880681 | AK31: MATCHED | AL31: FLIGHT_LEG | AM31: MANUAL | AN31: RAW-T9028 | AO31: IF_INTERFACE | AP31: 2026-08-19T2026-08-19T09:10:00ZZ | AS31: Crew did not report FOB; cannot reconcile
A32: TC21 | B32: TK-2029 | C32: PPC | D32: PPC-IPA | E32: MNL | F32: 880701 | G32: 2026-08-19 | H32: LEG-26081422 | I32: ORD-1026 | J32: FDP-2201 | K32: RP-C3513 | L32: UPLIFT | M32: 1 | N32: Y | O32: JET_A1 | P32: 0 | Q32: BOWSER | R32: BW-22 | S32: 10000 | T32: 50000 | U32: 40000 | V32: 0.7982 | W32: 30.5 | X32: COA-PPC-8029 | Z32: =IF(U32="",Y32,ROUND(U32*V32,1)) -> 31928 | AA32: 5200 | AB32: 36550 | AC32: =IF(OR(AA32="",AB32=""),"",AB32-AA32) -> 31350 | AD32: =IF(AC32="","",ROUND(Z32-AC32,1)) -> 578 | AE32: =IF(AC32="","NOT_RECONCILED",IF(ABS(AD32)<=MAX(50,0.02*ABS(Z32)),"PASS","FAIL")) -> PASS | AF32: PASS | AG32: 2026-08-19T09:55:00Z | AH32: 2026-08-19T10:35:00Z | AI32: FL-129 | AJ32: SIG-880701 | AK32: MATCHED | AL32: FLIGHT_LEG | AM32: EDI | AN32: RAW-T9029 | AO32: IF_INTERFACE | AP32: 2026-08-19T2026-08-19T09:55:00ZZ | AS32: Bowser 22 load 1 of 3
A33: TC21 | B33: TK-2030 | C33: PPC | D33: PPC-IPA | E33: MNL | F33: 880702 | G33: 2026-08-19 | H33: LEG-26081422 | I33: ORD-1026 | J33: FDP-2201 | K33: RP-C3513 | L33: UPLIFT | M33: 2 | N33: Y | O33: JET_A1 | P33: 0 | Q33: BOWSER | R33: BW-22 | S33: 50000 | T33: 85000 | U33: 35000 | V33: 0.7982 | W33: 30.5 | X33: COA-PPC-8030 | Z33: =IF(U33="",Y33,ROUND(U33*V33,1)) -> 27937 | AA33: 36550 | AB33: 63980 | AC33: =IF(OR(AA33="",AB33=""),"",AB33-AA33) -> 27430 | AD33: =IF(AC33="","",ROUND(Z33-AC33,1)) -> 507 | AE33: =IF(AC33="","NOT_RECONCILED",IF(ABS(AD33)<=MAX(50,0.02*ABS(Z33)),"PASS","FAIL")) -> PASS | AF33: PASS | AG33: 2026-08-19T10:50:00Z | AH33: 2026-08-19T11:25:00Z | AI33: FL-130 | AJ33: SIG-880702 | AK33: MATCHED | AL33: FLIGHT_LEG | AM33: EDI | AN33: RAW-T9030 | AO33: IF_INTERFACE | AP33: 2026-08-19T2026-08-19T10:50:00ZZ | AS33: Bowser 22 load 2 of 3
A34: TC21 | B34: TK-2031 | C34: PPC | D34: PPC-IPA | E34: MNL | F34: 880703 | G34: 2026-08-19 | H34: LEG-26081422 | I34: ORD-1026 | J34: FDP-2201 | K34: RP-C3513 | L34: UPLIFT | M34: 3 | N34: N | O34: JET_A1 | P34: 0 | Q34: BOWSER | R34: BW-22 | S34: 85000 | T34: 109456 | U34: 24456 | V34: 0.7982 | W34: 30.5 | X34: COA-PPC-8031 | Z34: =IF(U34="",Y34,ROUND(U34*V34,1)) -> 19520.8 | AA34: 63980 | AB34: 83152 | AC34: =IF(OR(AA34="",AB34=""),"",AB34-AA34) -> 19172 | AD34: =IF(AC34="","",ROUND(Z34-AC34,1)) -> 348.8 | AE34: =IF(AC34="","NOT_RECONCILED",IF(ABS(AD34)<=MAX(50,0.02*ABS(Z34)),"PASS","FAIL")) -> PASS | AF34: PASS | AG34: 2026-08-19T11:40:00Z | AH34: 2026-08-19T12:05:00Z | AI34: FL-131 | AJ34: SIG-880703 | AK34: MATCHED | AL34: FLIGHT_LEG | AM34: EDI | AN34: RAW-T9031 | AO34: IF_INTERFACE | AP34: 2026-08-19T2026-08-19T11:40:00ZZ | AS34: Bowser 22 load 3 of 3; same bias direction all three
A35: TC22 | B35: TK-2032 | C35: PPC | D35: PPC-IPA | E35: MNL | F35: 880721 | G35: 2026-08-20 | H35: LEG-26081423 | I35: ORD-1027 | J35: FDP-2301 | K35: RP-C4138 | L35: UPLIFT | M35: 1 | N35: N | O35: JET_A1 | P35: 0 | Q35: HYDRANT | R35: BW-11 | S35: 347898 | T35: 359345 | U35: 11447 | V35: 0.7995 | W35: 30.5 | X35: COA-PPC-8032 | Z35: =IF(U35="",Y35,ROUND(U35*V35,1)) -> 9151.9 | AA35: 1650 | AB35: 10801 | AC35: =IF(OR(AA35="",AB35=""),"",AB35-AA35) -> 9151 | AD35: =IF(AC35="","",ROUND(Z35-AC35,1)) -> 0.9 | AE35: =IF(AC35="","NOT_RECONCILED",IF(ABS(AD35)<=MAX(50,0.02*ABS(Z35)),"PASS","FAIL")) -> PASS | AF35: PASS | AG35: 2026-08-20T03:40:00Z | AH35: 2026-08-20T04:07:00Z | AI35: FL-132 | AJ35: SIG-880721 | AK35: MATCHED | AL35: FLIGHT_LEG | AM35: EDI | AN35: RAW-T9032 | AO35: IF_INTERFACE | AP35: 2026-08-20T2026-08-20T03:40:00ZZ | AS35: Ticket reconciles but arrival FOB 450 kg below plan assumption
A36: TC33 | B36: TK-2033 | C36: PPC | D36: PPC-IPA | E36: MNL | F36: 880741 | G36: 2026-08-21 | H36: LEG-26081424 | I36: ORD-1028 | J36: FDP-2401 | K36: RP-C4140 | L36: UPLIFT | M36: 1 | N36: N | O36: JET_A1 | P36: 0 | Q36: HYDRANT | R36: BW-11 | S36: 359345 | T36: 371345 | U36: 12000 | V36: 0.7995 | W36: 30.5 | X36: COA-PPC-8033 | Z36: =IF(U36="",Y36,ROUND(U36*V36,1)) -> 9594 | AA36: 2100 | AB36: 11694 | AC36: =IF(OR(AA36="",AB36=""),"",AB36-AA36) -> 9594 | AD36: =IF(AC36="","",ROUND(Z36-AC36,1)) -> 0 | AE36: =IF(AC36="","NOT_RECONCILED",IF(ABS(AD36)<=MAX(50,0.02*ABS(Z36)),"PASS","FAIL")) -> PASS | AF36: PASS | AG36: 2026-08-21T03:40:00Z | AH36: 2026-08-21T04:10:00Z | AI36: FL-133 | AJ36: SIG-880741 | AK36: MATCHED | AL36: FLIGHT_LEG | AM36: EDI | AN36: RAW-T9033 | AO36: IF_INTERFACE | AP36: 2026-08-21T2026-08-21T03:40:00ZZ | AS36: Fueller rounded to 12000 L; 443 kg above ordered quantity

Sheet Validation Rules
A1: Validation Rules
A2: Rule ID | B2: Applies To | C2: Assertion | D2: Related TC | E2: Severity
A3: VR01 | B3: FD_FUEL_PLAN | C3: block_fuel = trip + contingency + alternate + final_reserve + additional + taxi + extra | D3: All | E3: Error
A4: VR02 | B4: FD_FUEL_PLAN | C4: required_uplift = block_fuel - fuel_on_board, where fuel_on_board includes any fuel already delivered | D4: TC03, TC06 | E4: Error
A5: VR03 | B5: FD_FUEL_PLAN | C5: Exactly one row per plan_group_id may have plan_status = ACTIVE | D5: All | E5: Error
A6: VR04 | B6: FD_FUEL_PLAN | C6: A superseded version is never updated in place; a new row is inserted | D6: TC02, TC03, TC04 | E6: Error
A7: VR05 | B7: FD_FUEL_PLAN | C7: extra_fuel and additional_fuel are distinct fields and must not be merged | D7: TC11, TC14 | E7: Warning
A8: VR06 | B8: FUEL_ORDER | C8: delivered_qty is derived by summing linked tickets, never stored as a scalar | D8: TC05, TC06 | E8: Error
A9: VR07 | B9: FUEL_ORDER | C9: order_status = PART_FULFILLED requires a populated under_delivery_reason | D9: TC06 | E9: Error
A10: VR08 | B10: FUEL_ORDER | C10: A negative ordered_qty is valid and denotes a DEFUEL instruction | D10: TC08 | E10: Warning
A11: VR09 | B11: FUEL_TICKET | C11: quantity_kg = quantity_litres x density_kg_per_l, rounded at display only | D11: TC01, TC12 | E11: Error
A12: VR10 | B12: FUEL_TICKET | C12: fuel_order_id and fd_fuel_plan_id may be NULL; ticket must still be accepted at ingestion | D12: TC10, TC13 | E12: Error
A13: VR11 | B13: FUEL_TICKET | C13: A ticket links to the plan version it executed against, not the latest ACTIVE version | D13: TC03, TC06 | E13: Error
... A197: VR81 | B197: IF_RUN | C197: Divergence count is reported as an interface health metric, not only as individual exceptions | D197: TC62 | E197: Warning

Sheet FOB Reconciliation
A1: FOB RECONCILIATION - metered mass (bowser) vs FQIS gauge delta (aircraft). Tolerance = greater of 2% or 50 kg
A2: TC_ID | B2: ticket_id | C2: registration | D2: bowser_id | E2: event_type | F2: metered_kg | G2: fqis_delta_kg | H2: variance_kg | I2: variance_pct | J2: tolerance_kg | K2: recon_status | L2: likely_cause
A3: TC01 | B3: TK-2001 | C3: RP-C4108 | D3: BW-11 | E3: UPLIFT | F3: =INDEX(FUEL_TICKET!$Z:$Z,MATCH($B3,FUEL_TICKET!$B:$B,0)) -> 9151.1 | G3: =INDEX(FUEL_TICKET!$AC:$AC,MATCH($B3,FUEL_TICKET!$B:$B,0)) -> 9151 | H3: =IF(G3="","",ROUND(F3-G3,1)) -> 0.1 | I3: =IF(OR(G3="",F3=0),"",H3/F3) -> 1.0927648e-05 | J3: =MAX(50,0.02*ABS(F3)) -> 183.022 | K3: =IF(G3="","NOT_RECONCILED",IF(ABS(H3)<=J3,"PASS","FAIL")) -> PASS | L3: Baseline reference
A4: TC12 | B4: TK-2019 | C4: RP-C4122 | D4: BW-09 | E4: UPLIFT | F4: =INDEX(FUEL_TICKET!$Z:$Z,MATCH($B4,FUEL_TICKET!$B:$B,0)) -> 9152.8 | G4: =INDEX(FUEL_TICKET!$AC:$AC,MATCH($B4,FUEL_TICKET!$B:$B,0)) -> 9090 | H4: =IF(G4="","",ROUND(F4-G4,1)) -> 62.8 | I4: =IF(OR(G4="",F4=0),"",H4/F4) -> 0.0068612883 | J4: =MAX(50,0.02*ABS(F4)) -> 183.056 | K4: =IF(G4="","NOT_RECONCILED",IF(ABS(H4)<=J4,"PASS","FAIL")) -> PASS | L4: Delivered density above plan assumption
A5: TC16 | B5: TK-2024 | C5: RP-C4128 | D5: BW-11 | E5: UPLIFT | F5: =INDEX(FUEL_TICKET!$Z:$Z,MATCH($B5,FUEL_TICKET!$B:$B,0)) -> 9151.9 | G5: =INDEX(FUEL_TICKET!$AC:$AC,MATCH($B5,FUEL_TICKET!$B:$B,0)) -> 9115 | H5: =IF(G5="","",ROUND(F5-G5,1)) -> 36.9 | I5: =IF(OR(G5="",F5=0),"",H5/F5) -> 0.0040319496 | J5: =MAX(50,0.02*ABS(F5)) -> 183.038 | K5: =IF(G5="","NOT_RECONCILED",IF(ABS(H5)<=J5,"PASS","FAIL")) -> PASS | L5: Normal meter and gauge tolerance
A6: TC17 | B6: TK-2025 | C6: RP-C4130 | D6: BW-17 | E6: UPLIFT | F6: =INDEX(FUEL_TICKET!$Z:$Z,MATCH($B6,FUEL_TICKET!$B:$B,0)) -> 9151.9 | G6: =INDEX(FUEL_TICKET!$AC:$AC,MATCH($B6,FUEL_TICKET!$B:$B,0)) -> 8851 | H6: =IF(G6="","",ROUND(F6-G6,1)) -> 300.9 | I6: =IF(OR(G6="",F6=0),"",H6/F6) -> 0.032878419 | J6: =MAX(50,0.02*ABS(F6)) -> 183.038 | K6: =IF(G6="","NOT_RECONCILED",IF(ABS(H6)<=J6,"PASS","FAIL")) -> FAIL | L6: Meter over-read, leak or gauge fault - investigate
A7: TC18 | B7: TK-2026 | C7: RP-C4132 | D7: BW-17 | E7: UPLIFT | F7: =INDEX(FUEL_TICKET!$Z:$Z,MATCH($B7,FUEL_TICKET!$B:$B,0)) -> 9600 | G7: =INDEX(FUEL_TICKET!$AC:$AC,MATCH($B7,FUEL_TICKET!$B:$B,0)) -> 9420 | H7: =IF(G7="","",ROUND(F7-G7,1)) -> 180 | I7: =IF(OR(G7="",F7=0),"",H7/F7) -> 0.01875 | J7: =MAX(50,0.02*ABS(F7)) -> 192 | K7: =IF(G7="","NOT_RECONCILED",IF(ABS(H7)<=J7,"PASS","FAIL")) -> PASS | L7: Default density used instead of batch certificate value
A8: TC19 | B8: TK-2027 | C8: RP-C4134 | D8: BW-11 | E8: UPLIFT | F8: =INDEX(FUEL_TICKET!$Z:$Z,MATCH($B8,FUEL_TICKET!$B:$B,0)) -> 399.8 | G8: =INDEX(FUEL_TICKET!$AC:$AC,MATCH($B8,FUEL_TICKET!$B:$B,0)) -> 430 | H8: =IF(G8="","",ROUND(F8-G8,1)) -> -30.2 | I8: =IF(OR(G8="",F8=0),"",H8/F8) -> -0.075537769 | J8: =MAX(50,0.02*ABS(F8)) -> 50 | K8: =IF(G8="","NOT_RECONCILED",IF(ABS(H8)<=J8,"PASS","FAIL")) -> PASS | L8: FQIS resolution dominates on a small uplift
A9: TC20 | B9: TK-2028 | C9: RP-C4136 | D9: BW-11 | E9: UPLIFT | F9: =INDEX(FUEL_TICKET!$Z:$Z,MATCH($B9,FUEL_TICKET!$B:$B,0)) -> 9151.9 | G9: =INDEX(FUEL_TICKET!$AC:$AC,MATCH($B9,FUEL_TICKET!$B:$B,0)) | H9: =IF(G9="","",ROUND(F9-G9,1)) | I9: =IF(OR(G9="",F9=0),"",H9/F9) | J9: =MAX(50,0.02*ABS(F9)) -> 183.038 | K9: =IF(G9="","NOT_RECONCILED",IF(ABS(H9)<=J9,"PASS","FAIL")) -> NOT_RECONCILED | L9: FQIS not reported by crew
A10: TC21 | B10: TK-2029 | C10: RP-C3513 | D10: BW-22 | E10: UPLIFT | F10: =INDEX(FUEL_TICKET!$Z:$Z,MATCH($B10,FUEL_TICKET!$B:$B,0)) -> 31928 | G10: =INDEX(FUEL_TICKET!$AC:$AC,MATCH($B10,FUEL_TICKET!$B:$B,0)) -> 31350 | H10: =IF(G10="","",ROUND(F10-G10,1)) -> 578 | I10: =IF(OR(G10="",F10=0),"",H10/F10) -> 0.018103232 | J10: =MAX(50,0.02*ABS(F10)) -> 638.56 | K10: =IF(G10="","NOT_RECONCILED",IF(ABS(H10)<=J10,"PASS","FAIL")) -> PASS | L10: Bowser 22 - load 1
A11: TC21 | B11: TK-2030 | C11: RP-C3513 | D11: BW-22 | E11: UPLIFT | F11: =INDEX(FUEL_TICKET!$Z:$Z,MATCH($B11,FUEL_TICKET!$B:$B,0)) -> 27937 | G11: =INDEX(FUEL_TICKET!$AC:$AC,MATCH($B11,FUEL_TICKET!$B:$B,0)) -> 27430 | H11: =IF(G11="","",ROUND(F11-G11,1)) -> 507 | I11: =IF(OR(G11="",F11=0),"",H11/F11) -> 0.018147976 | J11: =MAX(50,0.02*ABS(F11)) -> 558.74 | K11: =IF(G11="","NOT_RECONCILED",IF(ABS(H11)<=J11,"PASS","FAIL")) -> PASS | L11: Bowser 22 - load 2
A12: TC21 | B12: TK-2031 | C12: RP-C3513 | D12: BW-22 | E12: UPLIFT | F12: =INDEX(FUEL_TICKET!$Z:$Z,MATCH($B12,FUEL_TICKET!$B:$B,0)) -> 19520.8 | G12: =INDEX(FUEL_TICKET!$AC:$AC,MATCH($B12,FUEL_TICKET!$B:$B,0)) -> 19172 | H12: =IF(G12="","",ROUND(F12-G12,1)) -> 348.8 | I12: =IF(OR(G12="",F12=0),"",H12/F12) -> 0.01786812 | J12: =MAX(50,0.02*ABS(F12)) -> 390.416 | K12: =IF(G12="","NOT_RECONCILED",IF(ABS(H12)<=J12,"PASS","FAIL")) -> PASS | L12: Bowser 22 - load 3
A13: TC22 | B13: TK-2032 | C13: RP-C4138 | D13: BW-11 | E13: UPLIFT | F13: =INDEX(FUEL_TICKET!$Z:$Z,MATCH($B13,FUEL_TICKET!$B:$B,0)) -> 9151.9 | G13: =INDEX(FUEL_TICKET!$AC:$AC,MATCH($B13,FUEL_TICKET!$B:$B,0)) -> 9151 | H13: =IF(G13="","",ROUND(F13-G13,1)) -> 0.9 | I13: =IF(OR(G13="",F13=0),"",H13/F13) -> 9.8340235e-05 | J13: =MAX(50,0.02*ABS(F13)) -> 183.038 | K13: =IF(G13="","NOT_RECONCILED",IF(ABS(H13)<=J13,"PASS","FAIL")) -> PASS | L13: Ticket reconciles; discrepancy is at plan level
A16: BOWSER BIAS ROLLUP - a consistent one directional variance indicates meter calibration drift
A17: bowser_id | B17: tickets | C17: total_metered_kg | D17: total_variance_kg | E17: bias_pct | F17: assessment
A18: BW-11 | B18: =COUNTIFS($D$3:$D$13,$A18) -> 5 | C18: =SUMIFS($F$3:$F$13,$D$3:$D$13,$A18) -> 37006.6 | D18: =SUMIFS($H$3:$H$13,$D$3:$D$13,$A18) -> 7.7 | E18: =IF(C18=0,"",D18/C18) -> 0.00020807099 | F18: =IF(C18=0,"NO DATA",IF(ABS(E18)>0.01,"CALIBRATION REVIEW","WITHIN RANGE")) -> WITHIN RANGE
A19: BW-17 | B19: =COUNTIFS($D$3:$D$13,$A19) -> 2 | C19: =SUMIFS($F$3:$F$13,$D$3:$D$13,$A19) -> 18751.9 | D19: =SUMIFS($H$3:$H$13,$D$3:$D$13,$A19) -> 480.9 | E19: =IF(C19=0,"",D19/C19) -> 0.025645401 | F19: =IF(C19=0,"NO DATA",IF(ABS(E19)>0.01,"CALIBRATION REVIEW","WITHIN RANGE")) -> CALIBRATION REVIEW
A20: BW-22 | B20: =COUNTIFS($D$3:$D$13,$A20) -> 3 | C20: =SUMIFS($F$3:$F$13,$D$3:$D$13,$A20) -> 79385.8 | D20: =SUMIFS($H$3:$H$13,$D$3:$D$13,$A20) -> 1433.8 | E20: =IF(C20=0,"",D20/C20) -> 0.018061165 | F20: =IF(C20=0,"NO DATA",IF(ABS(E20)>0.01,"CALIBRATION REVIEW","WITHIN RANGE")) -> CALIBRATION REVIEW
A21: BW-09 | B21: =COUNTIFS($D$3:$D$13,$A21) -> 1 | C21: =SUMIFS($F$3:$F$13,$D$3:$D$13,$A21) -> 9152.8 | D21: =SUMIFS($H$3:$H$13,$D$3:$D$13,$A21) -> 62.8 | E21: =IF(C21=0,"",D21/C21) -> 0.0068612883 | F21: =IF(C21=0,"NO DATA",IF(ABS(E21)>0.01,"CALIBRATION REVIEW","WITHIN RANGE")) -> WITHIN RANGE
A24: PLAN FOB vs ACTUAL FOB - assumed arrival fuel compared against the gauge at fuelling start
A25: TC_ID | B25: fd_fuel_plan_id | C25: ticket_id | D25: planned_fob_kg | E25: actual_fob_kg | F25: fob_variance_kg | G25: status
A26: TC01 | B26: FDP-0101 | C26: TK-2001 | D26: =INDEX(FD_FUEL_PLAN!$R:$R,MATCH($B26,FD_FUEL_PLAN!$B:$B,0)) -> 2100 | E26: =INDEX(FUEL_TICKET!$AA:$AA,MATCH($C26,FUEL_TICKET!$B:$B,0)) -> 2100 | F26: =IF(E26="","",E26-D26) -> 0 | G26: =IF(E26="","NO DATA",IF(ABS(F26)<=100,"PASS","PLAN FOB BREACH")) -> PASS
A27: TC16 | B27: FDP-1701 | C27: TK-2024 | D27: =INDEX(FD_FUEL_PLAN!$R:$R,MATCH($B27,FD_FUEL_PLAN!$B:$B,0)) -> 2100 | E27: =INDEX(FUEL_TICKET!$AA:$AA,MATCH($C27,FUEL_TICKET!$B:$B,0)) -> 2100 | F27: =IF(E27="","",E27-D27) -> 0 | G27: =IF(E27="","NO DATA",IF(ABS(F27)<=100,"PASS","PLAN FOB BREACH")) -> PASS
A28: TC22 | B28: FDP-2301 | C28: TK-2032 | D28: =INDEX(FD_FUEL_PLAN!$R:$R,MATCH($B28,FD_FUEL_PLAN!$B:$B,0)) -> 2100 | E28: =INDEX(FUEL_TICKET!$AA:$AA,MATCH($C28,FUEL_TICKET!$B:$B,0)) -> 1650 | F28: =IF(E28="","",E28-D28) -> -450 | G28: =IF(E28="","NO DATA",IF(ABS(F28)<=100,"PASS","PLAN FOB BREACH")) -> PLAN FOB BREACH

Sheet FUEL_INVOICE
A1: FUEL_INVOICE - PK fuel_invoice_id | header only; totals derived from FUEL_INVOICE_LINE
A2: fuel_invoice_id | B2: supplier_code | C2: invoice_number | D2: station | E2: period_from | F2: period_to | G2: currency | H2: line_count | I2: invoice_total | J2: supplier_stated_total | K2: header_variance | L2: invoice_status | M2: approved_by | N2: approved_utc | O2: posting_attempt_count | P2: last_posting_attempt_utc | Q2: erp_document_ref | R2: last_error_log_id | S2: received_utc | T2: due_date | U2: dispute_flag
A3: INV-0001 | B3: PPC | C3: PPC/2026/08/00412 | D3: MNL | E3: 2026-08-14 | F3: 2026-08-17 | G3: USD | H3: =COUNTIFS(FUEL_INVOICE_LINE!$C:$C,$A3) -> 8 | I3: =ROUND(SUMIFS(FUEL_INVOICE_LINE!$N:$N,FUEL_INVOICE_LINE!$C:$C,$A3),2) -> 154475.5 | J3: 121500 | K3: =IF(J3="","",ROUND(I3-J3,2)) -> 32975.5 | L3: UNDER_REVIEW | O3: 0 | S3: 2026-08-25T09:00Z | T3: 2026-09-24 | U3: Y
A4: INV-0002 | B4: PPC | C4: PPC/2026/08/00455 | D4: MNL | E4: 2026-08-18 | F4: 2026-08-20 | G4: USD | H4: =COUNTIFS(FUEL_INVOICE_LINE!$C:$C,$A4) -> 5 | I4: =ROUND(SUMIFS(FUEL_INVOICE_LINE!$N:$N,FUEL_INVOICE_LINE!$C:$C,$A4),2) -> 48953.87 | J4: 47800 | K4: =IF(J4="","",ROUND(I4-J4,2)) -> 1153.87 | L4: POSTING_ATTEMPTED | M4: L.TAN | N4: 2026-08-29T04:10Z | O4: 3 | P4: 2026-08-31T02:15Z | R4: LOG-0007 | S4: 2026-08-28T09:00Z | T4: 2026-09-27 | U4: Y
A5: INV-0003 | B5: SHL | C5: SHL/CEB/26-1188 | D5: CEB | E5: 2026-08-16 | F5: 2026-08-16 | G5: USD | H5: =COUNTIFS(FUEL_INVOICE_LINE!$C:$C,$A5) -> 1 | I5: =ROUND(SUMIFS(FUEL_INVOICE_LINE!$N:$N,FUEL_INVOICE_LINE!$C:$C,$A5),2) -> 22011.24 | J5: 22011.24 | K5: =IF(J5="","",ROUND(I5-J5,2)) -> 0 | L5: POSTED | M5: L.TAN | N5: 2026-08-23T06:00Z | O5: 1 | P5: 2026-08-23T06:05Z | Q5: 5100048812 | S5: 2026-08-22T09:00Z | T5: 2026-09-21 | U5: N
A6: INV-0004 | B6: PPC | C6: PPC/2026/08/00478 | D6: MNL | E6: 2026-08-21 | F6: 2026-08-21 | G6: USD | H6: =COUNTIFS(FUEL_INVOICE_LINE!$C:$C,$A6) -> 0 | I6: =ROUND(SUMIFS(FUEL_INVOICE_LINE!$N:$N,FUEL_INVOICE_LINE!$C:$C,$A6),2) -> 0 | J6: 8100 | K6: =IF(J6="","",ROUND(I6-J6,2)) -> -8100 | L6: POSTING_ATTEMPTED | M6: L.TAN | N6: 2026-08-30T04:10Z | O6: 1 | P6: 2026-08-31T02:15Z | R6: LOG-0011 | S6: 2026-08-29T09:00Z | T6: 2026-09-28 | U6: N
A7: INV-0005 | B7: PPC | C7: PPC/2026/08/00490 | D7: MNL | E7: 2026-08-14 | F7: 2026-08-14 | G7: USD | H7: =COUNTIFS(FUEL_INVOICE_LINE!$C:$C,$A7) -> 0 | I7: =ROUND(SUMIFS(FUEL_INVOICE_LINE!$N:$N,FUEL_INVOICE_LINE!$C:$C,$A7),2) -> 0 | J7: 9639.53 | K7: =IF(J7="","",ROUND(I7-J7,2)) -> -9639.53 | L7: REJECTED | O7: 0 | R7: LOG-0014 | S7: 2026-08-30T09:00Z | T7: 2026-09-29 | U7: Y

Sheet FUEL_INVOICE_LINE
A1: FUEL_INVOICE_LINE - PK fuel_invoice_line_id | FK ticket_id completes the three-way match: order / ticket / invoice
A2: TC_ID | B2: fuel_invoice_line_id | C2: fuel_invoice_id | D2: line_no | E2: ticket_id | F2: registration | G2: uplift_date | H2: invoiced_qty_litres | I2: invoiced_density | J2: invoiced_qty_kg | K2: ticket_qty_kg | L2: qty_variance_kg | M2: unit_price_per_litre | N2: line_amount | O2: contract_price_per_litre | P2: price_variance | Q2: three_way_status | R2: duplicate_check | S2: exception_reason
A3: TC23 | B3: ILN-0001 | C3: INV-0001 | D3: 1 | E3: TK-2001 | F3: RP-C4108 | G3: 2026-08-14 | H3: 11446 | I3: 0.7995 | J3: =ROUND(H3*I3,1) -> 9151.1 | K3: =IFERROR(INDEX(FUEL_TICKET!$Z:$Z,MATCH($E3,FUEL_TICKET!$B:$B,0)),"") -> 9151.1 | L3: =IF(K3="","",ROUND(J3-K3,1)) -> 0 | M3: 0.842 | N3: =ROUND(H3*M3,2) -> 9637.53 | O3: 0.842 | P3: =ROUND(M3-O3,4) -> 0 | Q3: =IF(K3="","NO_TICKET",IF(AND(ABS(L3)<=MAX(50,0.02*ABS(K3)),ABS(P3)<=0.0005),"MATCHED","EXCEPTION")) -> MATCHED | R3: =IF(COUNTIFS($E$3:$E$16,$E3)>1,"DUPLICATE","UNIQUE") -> DUPLICATE
A4: TC23 | B4: ILN-0002 | C4: INV-0001 | D4: 2 | E4: TK-2005 | F4: RP-C4108 | G4: 2026-08-14 | H4: 11447 | I4: 0.7995 | J4: =ROUND(H4*I4,1) -> 9151.9 | K4: =IFERROR(INDEX(FUEL_TICKET!$Z:$Z,MATCH($E4,FUEL_TICKET!$B:$B,0)),"") -> 9151.9 | L4: =IF(K4="","",ROUND(J4-K4,1)) -> 0 | M4: 0.842 | N4: =ROUND(H4*M4,2) -> 9638.37 | O4: 0.842 | P4: =ROUND(M4-O4,4) -> 0 | Q4: =IF(K4="","NO_TICKET",IF(AND(ABS(L4)<=MAX(50,0.02*ABS(K4)),ABS(P4)<=0.0005),"MATCHED","EXCEPTION")) -> MATCHED | R4: =IF(COUNTIFS($E$3:$E$16,$E4)>1,"DUPLICATE","UNIQUE") -> UNIQUE
A5: TC23 | B5: ILN-0003 | C5: INV-0001 | D5: 3 | E5: TK-2007 | F5: RP-C3505 | G5: 2026-08-14 | H5: 75244 | I5: 0.7982 | J5: =ROUND(H5*I5,1) -> 60059.8 | K5: =IFERROR(INDEX(FUEL_TICKET!$Z:$Z,MATCH($E5,FUEL_TICKET!$B:$B,0)),"") -> 60059.8 | L5: =IF(K5="","",ROUND(J5-K5,1)) -> 0 | M5: 0.842 | N5: =ROUND(H5*M5,2) -> 63355.45 | O5: 0.842 | P5: =ROUND(M5-O5,4) -> 0 | Q5: =IF(K5="","NO_TICKET",IF(AND(ABS(L5)<=MAX(50,0.02*ABS(K5)),ABS(P5)<=0.0005),"MATCHED","EXCEPTION")) -> MATCHED | R5: =IF(COUNTIFS($E$3:$E$16,$E5)>1,"DUPLICATE","UNIQUE") -> UNIQUE
A6: TC23 | B6: ILN-0004 | C6: INV-0001 | D6: 4 | E6: TK-2008 | F6: RP-C3505 | G6: 2026-08-14 | H6: 50278 | I6: 0.7982 | J6: =ROUND(H6*I6,1) -> 40131.9 | K6: =IFERROR(INDEX(FUEL_TICKET!$Z:$Z,MATCH($E6,FUEL_TICKET!$B:$B,0)),"") -> 40131.9 | L6: =IF(K6="","",ROUND(J6-K6,1)) -> 0 | M6: 0.842 | N6: =ROUND(H6*M6,2) -> 42334.08 | O6: 0.842 | P6: =ROUND(M6-O6,4) -> 0 | Q6: =IF(K6="","NO_TICKET",IF(AND(ABS(L6)<=MAX(50,0.02*ABS(K6)),ABS(P6)<=0.0005),"MATCHED","EXCEPTION")) -> MATCHED | R6: =IF(COUNTIFS($E$3:$E$16,$E6)>1,"DUPLICATE","UNIQUE") -> UNIQUE
A7: TC23 | B7: ILN-0005 | C7: INV-0001 | D7: 5 | E7: TK-2012 | F7: RP-C4114 | G7: 2026-08-15 | H7: 11447 | I7: 0.7995 | J7: =ROUND(H7*I7,1) -> 9151.9 | K7: =IFERROR(INDEX(FUEL_TICKET!$Z:$Z,MATCH($E7,FUEL_TICKET!$B:$B,0)),"") -> 9151.9 | L7: =IF(K7="","",ROUND(J7-K7,1)) -> 0 | M7: 0.842 | N7: =ROUND(H7*M7,2) -> 9638.37 | O7: 0.842 | P7: =ROUND(M7-O7,4) -> 0 | Q7: =IF(K7="","NO_TICKET",IF(AND(ABS(L7)<=MAX(50,0.02*ABS(K7)),ABS(P7)<=0.0005),"MATCHED","EXCEPTION")) -> MATCHED | R7: =IF(COUNTIFS($E$3:$E$16,$E7)>1,"DUPLICATE","UNIQUE") -> UNIQUE
A8: TC29 | B8: ILN-0006 | C8: INV-0001 | D8: 6 | E8: TK-2014 | F8: RP-C4116 | G8: 2026-08-15 | H8: -1996 | I8: 0.7995 | J8: =ROUND(H8*I8,1) -> -1595.8 | K8: =IFERROR(INDEX(FUEL_TICKET!$Z:$Z,MATCH($E8,FUEL_TICKET!$B:$B,0)),"") -> -1595.8 | L8: =IF(K8="","",ROUND(J8-K8,1)) -> 0 | M8: 0.842 | N8: =ROUND(H8*M8,2) -> -1680.63 | O8: 0.842 | P8: =ROUND(M8-O8,4) -> 0 | Q8: =IF(K8="","NO_TICKET",IF(AND(ABS(L8)<=MAX(50,0.02*ABS(K8)),ABS(P8)<=0.0005),"MATCHED","EXCEPTION")) -> MATCHED | R8: =IF(COUNTIFS($E$3:$E$16,$E8)>1,"DUPLICATE","UNIQUE") -> UNIQUE
A9: TC25 | B9: ILN-0007 | C9: INV-0001 | D9: 7 | E9: TK-2021 | F9: RP-C4124 | G9: 2026-08-17 | H9: 15448 | I9: 0.7995 | J9: =ROUND(H9*I9,1) -> 12350.7 | K9: =IFERROR(INDEX(FUEL_TICKET!$Z:$Z,MATCH($E9,FUEL_TICKET!$B:$B,0)),"") -> 12350.7 | L9: =IF(K9="","",ROUND(J9-K9,1)) -> 0 | M9: 0.861 | N9: =ROUND(H9*M9,2) -> 13300.73 | O9: 0.842 | P9: =ROUND(M9-O9,4) -> 0.019 | Q9: =IF(K9="","NO_TICKET",IF(AND(ABS(L9)<=MAX(50,0.02*ABS(K9)),ABS(P9)<=0.0005),"MATCHED","EXCEPTION")) -> EXCEPTION | R9: =IF(COUNTIFS($E$3:$E$16,$E9)>1,"DUPLICATE","UNIQUE") -> UNIQUE | S9: Differential above contract
A10: TC26 | B10: ILN-0008 | C10: INV-0001 | D10: 8 | E10: TK-9999 | F10: RP-C4108 | G10: 2026-08-16 | H10: 9800 | I10: 0.7995 | J10: =ROUND(H10*I10,1) -> 7835.1 | K10: =IFERROR(INDEX(FUEL_TICKET!$Z:$Z,MATCH($E10,FUEL_TICKET!$B:$B,0)),"") | L10: =IF(K10="","",ROUND(J10-K10,1)) | M10: 0.842 | N10: =ROUND(H10*M10,2) -> 8251.6 | O10: 0.842 | P10: =ROUND(M10-O10,4) -> 0 | Q10: =IF(K10="","NO_TICKET",IF(AND(ABS(L10)<=MAX(50,0.02*ABS(K10)),ABS(P10)<=0.0005),"MATCHED","EXCEPTION")) -> NO_TICKET | R10: =IF(COUNTIFS($E$3:$E$16,$E10)>1,"DUPLICATE","UNIQUE") -> UNIQUE | S10: No matching ticket in system
A11: TC23 | B11: ILN-0009 | C11: INV-0002 | D11: 1 | E11: TK-2024 | F11: RP-C4128 | G11: 2026-08-18 | H11: 11447 | I11: 0.7995 | J11: =ROUND(H11*I11,1) -> 9151.9 | K11: =IFERROR(INDEX(FUEL_TICKET!$Z:$Z,MATCH($E11,FUEL_TICKET!$B:$B,0)),"") -> 9151.9 | L11: =IF(K11="","",ROUND(J11-K11,1)) -> 0 | M11: 0.842 | N11: =ROUND(H11*M11,2) -> 9638.37 | O11: 0.842 | P11: =ROUND(M11-O11,4) -> 0 | Q11: =IF(K11="","NO_TICKET",IF(AND(ABS(L11)<=MAX(50,0.02*ABS(K11)),ABS(P11)<=0.0005),"MATCHED","EXCEPTION")) -> MATCHED | R11: =IF(COUNTIFS($E$3:$E$16,$E11)>1,"DUPLICATE","UNIQUE") -> UNIQUE
A12: TC24 | B12: ILN-0010 | C12: INV-0002 | D12: 2 | E12: TK-2025 | F12: RP-C4130 | G12: 2026-08-18 | H12: 11800 | I12: 0.7995 | J12: =ROUND(H12*I12,1) -> 9434.1 | K12: =IFERROR(INDEX(FUEL_TICKET!$Z:$Z,MATCH($E12,FUEL_TICKET!$B:$B,0)),"") -> 9151.9 | L12: =IF(K12="","",ROUND(J12-K12,1)) -> 282.2 | M12: 0.842 | N12: =ROUND(H12*M12,2) -> 9935.6 | O12: 0.842 | P12: =ROUND(M12-O12,4) -> 0 | Q12: =IF(K12="","NO_TICKET",IF(AND(ABS(L12)<=MAX(50,0.02*ABS(K12)),ABS(P12)<=0.0005),"MATCHED","EXCEPTION")) -> EXCEPTION | R12: =IF(COUNTIFS($E$3:$E$16,$E12)>1,"DUPLICATE","UNIQUE") -> UNIQUE | S12: Invoiced volume exceeds ticket
A13: TC27 | B13: ILN-0011 | C13: INV-0002 | D13: 3 | E13: TK-2026 | F13: RP-C4132 | G13: 2026-08-18 | H13: 12000 | I13: 0.8 | J13: =ROUND(H13*I13,1) -> 9600 | K13: =IFERROR(INDEX(FUEL_TICKET!$Z:$Z,MATCH($E13,FUEL_TICKET!$B:$B,0)),"") -> 9600 | L13: =IF(K13="","",ROUND(J13-K13,1)) -> 0 | M13: 0.842 | N13: =ROUND(H13*M13,2) -> 10104 | O13: 0.842 | P13: =ROUND(M13-O13,4) -> 0 | Q13: =IF(K13="","NO_TICKET",IF(AND(ABS(L13)<=MAX(50,0.02*ABS(K13)),ABS(P13)<=0.0005),"MATCHED","EXCEPTION")) -> MATCHED | R13: =IF(COUNTIFS($E$3:$E$16,$E13)>1,"DUPLICATE","UNIQUE") -> UNIQUE | S13: Density under review against certificate
A14: TC23 | B14: ILN-0012 | C14: INV-0002 | D14: 4 | E14: TK-2032 | F14: RP-C4138 | G14: 2026-08-20 | H14: 11447 | I14: 0.7995 | J14: =ROUND(H14*I14,1) -> 9151.9 | K14: =IFERROR(INDEX(FUEL_TICKET!$Z:$Z,MATCH($E14,FUEL_TICKET!$B:$B,0)),"") -> 9151.9 | L14: =IF(K14="","",ROUND(J14-K14,1)) -> 0 | M14: 0.842 | N14: =ROUND(H14*M14,2) -> 9638.37 | O14: 0.842 | P14: =ROUND(M14-O14,4) -> 0 | Q14: =IF(K14="","NO_TICKET",IF(AND(ABS(L14)<=MAX(50,0.02*ABS(K14)),ABS(P14)<=0.0005),"MATCHED","EXCEPTION")) -> MATCHED | R14: =IF(COUNTIFS($E$3:$E$16,$E14)>1,"DUPLICATE","UNIQUE") -> UNIQUE
A15: TC30 | B15: ILN-0013 | C15: INV-0003 | D15: 1 | E15: TK-2020B | F15: RP-C3511 | G15: 2026-08-16 | H15: 24056 | I15: 0.7975 | J15: =ROUND(H15*I15,1) -> 19184.7 | K15: =IFERROR(INDEX(FUEL_TICKET!$Z:$Z,MATCH($E15,FUEL_TICKET!$B:$B,0)),"") -> 19184.7 | L15: =IF(K15="","",ROUND(J15-K15,1)) -> 0 | M15: 0.915 | N15: =ROUND(H15*M15,2) -> 22011.24 | O15: 0.915 | P15: =ROUND(M15-O15,4) -> 0 | Q15: =IF(K15="","NO_TICKET",IF(AND(ABS(L15)<=MAX(50,0.02*ABS(K15)),ABS(P15)<=0.0005),"MATCHED","EXCEPTION")) -> MATCHED | R15: =IF(COUNTIFS($E$3:$E$16,$E15)>1,"DUPLICATE","UNIQUE") -> UNIQUE | S15: Ad hoc diversion pricing
A16: TC32 | B16: ILN-0014 | C16: INV-0002 | D16: 5 | E16: TK-2001 | F16: RP-C4108 | G16: 2026-08-14 | H16: 11446 | I16: 0.7995 | J16: =ROUND(H16*I16,1) -> 9151.1 | K16: =IFERROR(INDEX(FUEL_TICKET!$Z:$Z,MATCH($E16,FUEL_TICKET!$B:$B,0)),"") -> 9151.1 | L16: =IF(K16="","",ROUND(J16-K16,1)) -> 0 | M16: 0.842 | N16: =ROUND(H16*M16,2) -> 9637.53 | O16: 0.842 | P16: =ROUND(M16-O16,4) -> 0 | Q16: =IF(K16="","NO_TICKET",IF(AND(ABS(L16)<=MAX(50,0.02*ABS(K16)),ABS(P16)<=0.0005),"MATCHED","EXCEPTION")) -> MATCHED | R16: =IF(COUNTIFS($E$3:$E$16,$E16)>1,"DUPLICATE","UNIQUE") -> DUPLICATE | S16: Duplicate - already billed on ILN-0001
A19: UNBILLED TICKETS - delivered fuel with no invoice line. The inverse exposure to a phantom invoice line
A20: ticket_id | B20: registration | C20: uplift_date | D20: ticket_qty_kg | E20: invoice_lines | F20: status
A21: TK-2013 | B21: RP-C4116 | C21: 2026-08-15 | D21: =IFERROR(INDEX(FUEL_TICKET!$Z:$Z,MATCH($A21,FUEL_TICKET!$B:$B,0)),"") -> 9151.9 | E21: =COUNTIFS($E$3:$E$16,$A21) -> 0 | F21: =IF(E21=0,"UNBILLED","BILLED") -> UNBILLED
A22: TK-2017 | B22: RP-C4118 | C22: 2026-08-16 | D22: =IFERROR(INDEX(FUEL_TICKET!$Z:$Z,MATCH($A22,FUEL_TICKET!$B:$B,0)),"") -> 634.8 | E22: =COUNTIFS($E$3:$E$16,$A22) -> 0 | F22: =IF(E22=0,"UNBILLED","BILLED") -> UNBILLED
A23: TK-2019 | B23: RP-C4122 | C23: 2026-08-16 | D23: =IFERROR(INDEX(FUEL_TICKET!$Z:$Z,MATCH($A23,FUEL_TICKET!$B:$B,0)),"") -> 9152.8 | E23: =COUNTIFS($E$3:$E$16,$A23) -> 0 | F23: =IF(E23=0,"UNBILLED","BILLED") -> UNBILLED
A24: TK-2027 | B24: RP-C4134 | C24: 2026-08-19 | D24: =IFERROR(INDEX(FUEL_TICKET!$Z:$Z,MATCH($A24,FUEL_TICKET!$B:$B,0)),"") -> 399.8 | E24: =COUNTIFS($E$3:$E$16,$A24) -> 0 | F24: =IF(E24=0,"UNBILLED","BILLED") -> UNBILLED

Sheet FUEL_PARAMETER
A1: FUEL_PARAMETER - configuration. Most specific scope wins; resolved as of the UPLIFT date, never the query date
A2: parameter_id | B2: parameter_code | C2: parameter_name | D2: scope_level | E2: scope_key | F2: specificity_rank | G2: fuel_grade | H2: qty_band_from | I2: qty_band_to | J2: value_pct | K2: value_absolute | L2: value_decimal | M2: combine_rule | N2: unit | O2: valid_from | P2: valid_to | Q2: status | R2: approved_by | S2: change_reason
A3: PRM-0001 | B3: SG_CONVERSION | C3: Default conversion density | D3: GLOBAL | E3: * | F3: 0 | G3: JET_A1 | L3: 0.8 | N3: RATIO | O3: 2026-01-01 | Q3: ACTIVE | R3: R.DELACRUZ | S3: Initial baseline
A4: PRM-0002 | B4: SG_CONVERSION | C4: MNL PPC conversion density | D4: STATION_SUPPLIER | E4: MNL|PPC | F4: 40 | G4: JET_A1 | L4: 0.7995 | N4: RATIO | O4: 2026-07-01 | Q4: ACTIVE | R4: R.DELACRUZ | S4: Aligned to Q3 tank farm average
A5: PRM-0003 | B5: SG_CONVERSION | C5: MNL PPC conversion density | D5: STATION_SUPPLIER | E5: MNL|PPC | F5: 40 | G5: JET_A1 | L5: 0.801 | N5: RATIO | O5: 2026-01-01 | P5: 2026-06-30 | Q5: SUPERSEDED | R5: R.DELACRUZ | S5: Replaced by PRM-0002
A6: PRM-0004 | B6: SG_CONVERSION | C6: CEB SHL conversion density | D6: STATION_SUPPLIER | E6: CEB|SHL | F6: 40 | G6: JET_A1 | L6: 0.7975 | N6: RATIO | O6: 2026-01-01 | Q6: ACTIVE | R6: R.DELACRUZ | S6: Ad hoc station baseline
A7: PRM-0010 | B7: FOB_TOLERANCE | C7: Default FOB tolerance | D7: GLOBAL | E7: * | F7: 0 | J7: 0.02 | K7: 50 | M7: GREATER_OF | N7: KG | O7: 2026-01-01 | Q7: ACTIVE | R7: M.SANTOS | S7: Initial baseline
A8: PRM-0011 | B8: FOB_TOLERANCE | C8: A321 small uplift tolerance | D8: AIRCRAFT_TYPE | E8: A321 | F8: 30 | H8: 0 | I8: 5000 | J8: 0.03 | K8: 50 | M8: GREATER_OF | N8: KG | O8: 2026-01-01 | Q8: ACTIVE | R8: M.SANTOS | S8: FQIS resolution poor at low quantity
A9: PRM-0012 | B9: FOB_TOLERANCE | C9: Widebody large uplift tolerance | D9: AIRCRAFT_TYPE | E9: A350-900 | F9: 30 | H9: 50000 | J9: 0.015 | K9: 500 | M9: GREATER_OF | N9: KG | O9: 2026-01-01 | Q9: ACTIVE | R9: M.SANTOS | S9: Percentage too generous in absolute terms
A10: PRM-0020 | B10: ORDER_TOLERANCE | C10: Default order fulfilment tolerance | D10: GLOBAL | E10: * | F10: 0 | J10: 0.01 | K10: 50 | M10: GREATER_OF | N10: KG | O10: 2026-01-01 | Q10: ACTIVE | R10: M.SANTOS | S10: Initial baseline
A11: PRM-0021 | B11: ORDER_TOLERANCE | C11: MNL PPC order tolerance | D11: STATION_SUPPLIER | E11: MNL|PPC | F11: 40 | J11: 0.008 | K11: 50 | M11: GREATER_OF | N11: KG | O11: 2026-04-01 | Q11: ACTIVE | R11: M.SANTOS | S11: Tightened after Q1 meter calibration
A12: PRM-0030 | B12: DENSITY_MIN | C12: Jet A-1 minimum plausible density | D12: GRADE | E12: JET_A1 | F12: 10 | G12: JET_A1 | L12: 0.775 | M12: ABS_ONLY | N12: RATIO | O12: 2026-01-01 | Q12: ACTIVE | R12: A.REYES | S12: Per specification range
A13: PRM-0031 | B13: DENSITY_MAX | C13: Jet A-1 maximum plausible density | D13: GRADE | E13: JET_A1 | F13: 10 | G13: JET_A1 | L13: 0.84 | M13: ABS_ONLY | N13: RATIO | O13: 2026-01-01 | Q13: ACTIVE | R13: A.REYES | S13: Per specification range
A14: PRM-0050 | B14: AIRCRAFT_CONFIG_GRANULARITY | C14: Cabin configuration depth | D14: GLOBAL | E14: * | F14: 0 | N14: ENUM | O14: 2026-01-01 | Q14: ACTIVE | R14: IT.ARCH | S14: NONE or BY_CONFIG. Hides the config table entirely for airlines with one fit per type
A15: PRM-0051 | B15: PRIMARY_TYPE_CODE_SCHEME | C15: Type code shown on screen | D15: GLOBAL | E15: * | F15: 0 | N15: ENUM | O15: 2026-01-01 | Q15: ACTIVE | R15: IT.ARCH | S15: ICAO, IATA, MANUFACTURER or INTERNAL. Display and reporting only; resolution always uses the FK
A16: PRM-0052 | B16: ALLOW_PROVISIONAL_TYPE | C16: Auto provision unknown aircraft types | D16: GLOBAL | E16: * | F16: 0 | N16: BOOLEAN | O16: 2026-01-01 | Q16: ACTIVE | R16: IT.ARCH | S16: Removes setup burden at implementation
A17: PRM-0040 | B17: PRICE_TOLERANCE | C17: Unit price match tolerance | D17: GLOBAL | E17: * | F17: 0 | K17: 0.0005 | M17: ABS_ONLY | N17: USD | O17: 2026-01-01 | Q17: ACTIVE | R17: L.TAN | S17: Rounding allowance per litre

Sheet FUEL_PARAMETER_APPLIED
A1: FUEL_PARAMETER_APPLIED - immutable evidence. What DID apply to this transaction, and which config row produced it
A2: applied_id | B2: entity_type | C2: entity_id | D2: parameter_code | E2: parameter_id | F2: scope_key_resolved | G2: basis_qty | H2: value_pct | I2: value_absolute | J2: value_decimal | K2: combine_rule | L2: resolved_value | M2: resolved_utc | N2: as_of_date
A3: APP-0001 | B3: TICKET | C3: TK-2001 | D3: FOB_TOLERANCE | E3: PRM-0010 | F3: =INDEX(FUEL_PARAMETER!$E:$E,MATCH($E3,FUEL_PARAMETER!$A:$A,0)) -> * | G3: 9151.1 | H3: =INDEX(FUEL_PARAMETER!$J:$J,MATCH($E3,FUEL_PARAMETER!$A:$A,0)) -> 0.02 | I3: =INDEX(FUEL_PARAMETER!$K:$K,MATCH($E3,FUEL_PARAMETER!$A:$A,0)) -> 50 | J3: =INDEX(FUEL_PARAMETER!$L:$L,MATCH($E3,FUEL_PARAMETER!$A:$A,0)) -> 0 | K3: =INDEX(FUEL_PARAMETER!$M:$M,MATCH($E3,FUEL_PARAMETER!$A:$A,0)) -> GREATER_OF | L3: =IF(K3="ABS_ONLY",IF(I3="",J3,I3),IF(K3="PCT_ONLY",ROUND(H3*G3,1),IF(K3="GREATER_OF",ROUND(MAX(I3,H3*G3),1),IF(K3="LESSER_OF",ROUND(MIN(I3,H3*G3),1),J3)))) -> 183 | M3: 2026-08-31T00:00Z | N3: 2026-08-14
A4: APP-0002 | B4: TICKET | C4: TK-2019 | D4: FOB_TOLERANCE | E4: PRM-0010 | F4: =INDEX(FUEL_PARAMETER!$E:$E,MATCH($E4,FUEL_PARAMETER!$A:$A,0)) -> * | G4: 9152.8 | H4: =INDEX(FUEL_PARAMETER!$J:$J,MATCH($E4,FUEL_PARAMETER!$A:$A,0)) -> 0.02 | I4: =INDEX(FUEL_PARAMETER!$K:$K,MATCH($E4,FUEL_PARAMETER!$A:$A,0)) -> 50 | J4: =INDEX(FUEL_PARAMETER!$L:$L,MATCH($E4,FUEL_PARAMETER!$A:$A,0)) -> 0 | K4: =INDEX(FUEL_PARAMETER!$M:$M,MATCH($E4,FUEL_PARAMETER!$A:$A,0)) -> GREATER_OF | L4: =IF(K4="ABS_ONLY",IF(I4="",J4,I4),IF(K4="PCT_ONLY",ROUND(H4*G4,1),IF(K4="GREATER_OF",ROUND(MAX(I4,H4*G4),1),IF(K4="LESSER_OF",ROUND(MIN(I4,H4*G4),1),J4)))) -> 183.1 | M4: 2026-08-31T00:00Z | N4: 2026-08-16
A5: APP-0003 | B5: TICKET | C5: TK-2024 | D5: FOB_TOLERANCE | E5: PRM-0010 | F5: =INDEX(FUEL_PARAMETER!$E:$E,MATCH($E5,FUEL_PARAMETER!$A:$A,0)) -> * | G5: 9151.9 | H5: =INDEX(FUEL_PARAMETER!$J:$J,MATCH($E5,FUEL_PARAMETER!$A:$A,0)) -> 0.02 | I5: =INDEX(FUEL_PARAMETER!$K:$K,MATCH($E5,FUEL_PARAMETER!$A:$A,0)) -> 50 | J5: =INDEX(FUEL_PARAMETER!$L:$L,MATCH($E5,FUEL_PARAMETER!$A:$A,0)) -> 0 | K5: =INDEX(FUEL_PARAMETER!$M:$M,MATCH($E5,FUEL_PARAMETER!$A:$A,0)) -> GREATER_OF | L5: =IF(K5="ABS_ONLY",IF(I5="",J5,I5),IF(K5="PCT_ONLY",ROUND(H5*G5,1),IF(K5="GREATER_OF",ROUND(MAX(I5,H5*G5),1),IF(K5="LESSER_OF",ROUND(MIN(I5,H5*G5),1),J5)))) -> 183 | M5: 2026-08-31T00:00Z | N5: 2026-08-18
A6: APP-0004 | B6: TICKET | C6: TK-2025 | D6: FOB_TOLERANCE | E6: PRM-0010 | F6: =INDEX(FUEL_PARAMETER!$E:$E,MATCH($E6,FUEL_PARAMETER!$A:$A,0)) -> * | G6: 9151.9 | H6: =INDEX(FUEL_PARAMETER!$J:$J,MATCH($E6,FUEL_PARAMETER!$A:$A,0)) -> 0.02 | I6: =INDEX(FUEL_PARAMETER!$K:$K,MATCH($E6,FUEL_PARAMETER!$A:$A,0)) -> 50 | J6: =INDEX(FUEL_PARAMETER!$L:$L,MATCH($E6,FUEL_PARAMETER!$A:$A,0)) -> 0 | K6: =INDEX(FUEL_PARAMETER!$M:$M,MATCH($E6,FUEL_PARAMETER!$A:$A,0)) -> GREATER_OF | L6: =IF(K6="ABS_ONLY",IF(I6="",J6,I6),IF(K6="PCT_ONLY",ROUND(H6*G6,1),IF(K6="GREATER_OF",ROUND(MAX(I6,H6*G6),1),IF(K6="LESSER_OF",ROUND(MIN(I6,H6*G6),1),J6)))) -> 183 | M6: 2026-08-31T00:00Z | N6: 2026-08-18
A7: APP-0005 | B7: TICKET | C7: TK-2026 | D7: FOB_TOLERANCE | E7: PRM-0010 | F7: =INDEX(FUEL_PARAMETER!$E:$E,MATCH($E7,FUEL_PARAMETER!$A:$A,0)) -> * | G7: 9600 | H7: =INDEX(FUEL_PARAMETER!$J:$J,MATCH($E7,FUEL_PARAMETER!$A:$A,0)) -> 0.02 | I7: =INDEX(FUEL_PARAMETER!$K:$K,MATCH($E7,FUEL_PARAMETER!$A:$A,0)) -> 50 | J7: =INDEX(FUEL_PARAMETER!$L:$L,MATCH($E7,FUEL_PARAMETER!$A:$A,0)) -> 0 | K7: =INDEX(FUEL_PARAMETER!$M:$M,MATCH($E7,FUEL_PARAMETER!$A:$A,0)) -> GREATER_OF | L7: =IF(K7="ABS_ONLY",IF(I7="",J7,I7),IF(K7="PCT_ONLY",ROUND(H7*G7,1),IF(K7="GREATER_OF",ROUND(MAX(I7,H7*G7),1),IF(K7="LESSER_OF",ROUND(MIN(I7,H7*G7),1),J7)))) -> 192 | M7: 2026-08-31T00:00Z | N7: 2026-08-18
A8: APP-0006 | B8: TICKET | C8: TK-2027 | D8: FOB_TOLERANCE | E8: PRM-0011 | F8: =INDEX(FUEL_PARAMETER!$E:$E,MATCH($E8,FUEL_PARAMETER!$A:$A,0)) -> A321 | G8: 399.8 | H8: =INDEX(FUEL_PARAMETER!$J:$J,MATCH($E8,FUEL_PARAMETER!$A:$A,0)) -> 0.03 | I8: =INDEX(FUEL_PARAMETER!$K:$K,MATCH($E8,FUEL_PARAMETER!$A:$A,0)) -> 50 | J8: =INDEX(FUEL_PARAMETER!$L:$L,MATCH($E8,FUEL_PARAMETER!$A:$A,0)) -> 0 | K8: =INDEX(FUEL_PARAMETER!$M:$M,MATCH($E8,FUEL_PARAMETER!$A:$A,0)) -> GREATER_OF | L8: =IF(K8="ABS_ONLY",IF(I8="",J8,I8),IF(K8="PCT_ONLY",ROUND(H8*G8,1),IF(K8="GREATER_OF",ROUND(MAX(I8,H8*G8),1),IF(K8="LESSER_OF",ROUND(MIN(I8,H8*G8),1),J8)))) -> 50 | M8: 2026-08-31T00:00Z | N8: 2026-08-19
A9: APP-0007 | B9: TICKET | C9: TK-2029 | D9: FOB_TOLERANCE | E9: PRM-0010 | F9: =INDEX(FUEL_PARAMETER!$E:$E,MATCH($E9,FUEL_PARAMETER!$A:$A,0)) -> * | G9: 31928 | H9: =INDEX(FUEL_PARAMETER!$J:$J,MATCH($E9,FUEL_PARAMETER!$A:$A,0)) -> 0.02 | I9: =INDEX(FUEL_PARAMETER!$K:$K,MATCH($E9,FUEL_PARAMETER!$A:$A,0)) -> 50 | J9: =INDEX(FUEL_PARAMETER!$L:$L,MATCH($E9,FUEL_PARAMETER!$A:$A,0)) -> 0 | K9: =INDEX(FUEL_PARAMETER!$M:$M,MATCH($E9,FUEL_PARAMETER!$A:$A,0)) -> GREATER_OF | L9: =IF(K9="ABS_ONLY",IF(I9="",J9,I9),IF(K9="PCT_ONLY",ROUND(H9*G9,1),IF(K9="GREATER_OF",ROUND(MAX(I9,H9*G9),1),IF(K9="LESSER_OF",ROUND(MIN(I9,H9*G9),1),J9)))) -> 638.6 | M9: 2026-08-31T00:00Z | N9: 2026-08-19
A10: APP-0008 | B10: TICKET | C10: TK-2032 | D10: FOB_TOLERANCE | E10: PRM-0010 | F10: =INDEX(FUEL_PARAMETER!$E:$E,MATCH($E10,FUEL_PARAMETER!$A:$A,0)) -> * | G10: 9151.9 | H10: =INDEX(FUEL_PARAMETER!$J:$J,MATCH($E10,FUEL_PARAMETER!$A:$A,0)) -> 0.02 | I10: =INDEX(FUEL_PARAMETER!$K:$K,MATCH($E10,FUEL_PARAMETER!$A:$A,0)) -> 50 | J10: =INDEX(FUEL_PARAMETER!$L:$L,MATCH($E10,FUEL_PARAMETER!$A:$A,0)) -> 0 | K10: =INDEX(FUEL_PARAMETER!$M:$M,MATCH($E10,FUEL_PARAMETER!$A:$A,0)) -> GREATER_OF | L10: =IF(K10="ABS_ONLY",IF(I10="",J10,I10),IF(K10="PCT_ONLY",ROUND(H10*G10,1),IF(K10="GREATER_OF",ROUND(MAX(I10,H10*G10),1),IF(K10="LESSER_OF",ROUND(MIN(I10,H10*G10),1),J10)))) -> 183 | M10: 2026-08-31T00:00Z | N10: 2026-08-20
A11: APP-0009 | B11: TICKET | C11: TK-2033 | D11: FOB_TOLERANCE | E11: PRM-0010 | F11: =INDEX(FUEL_PARAMETER!$E:$E,MATCH($E11,FUEL_PARAMETER!$A:$A,0)) -> * | G11: 9594 | H11: =INDEX(FUEL_PARAMETER!$J:$J,MATCH($E11,FUEL_PARAMETER!$A:$A,0)) -> 0.02 | I11: =INDEX(FUEL_PARAMETER!$K:$K,MATCH($E11,FUEL_PARAMETER!$A:$A,0)) -> 50 | J11: =INDEX(FUEL_PARAMETER!$L:$L,MATCH($E11,FUEL_PARAMETER!$A:$A,0)) -> 0 | K11: =INDEX(FUEL_PARAMETER!$M:$M,MATCH($E11,FUEL_PARAMETER!$A:$A,0)) -> GREATER_OF | L11: =IF(K11="ABS_ONLY",IF(I11="",J11,I11),IF(K11="PCT_ONLY",ROUND(H11*G11,1),IF(K11="GREATER_OF",ROUND(MAX(I11,H11*G11),1),IF(K11="LESSER_OF",ROUND(MIN(I11,H11*G11),1),J11)))) -> 191.9 | M11: 2026-08-31T00:00Z | N11: 2026-08-21
A12: APP-0010 | B12: ORDER | C12: ORD-1001 | D12: ORDER_TOLERANCE | E12: PRM-0021 | F12: =INDEX(FUEL_PARAMETER!$E:$E,MATCH($E12,FUEL_PARAMETER!$A:$A,0)) -> MNL|PPC | G12: 9151 | H12: =INDEX(FUEL_PARAMETER!$J:$J,MATCH($E12,FUEL_PARAMETER!$A:$A,0)) -> 0.008 | I12: =INDEX(FUEL_PARAMETER!$K:$K,MATCH($E12,FUEL_PARAMETER!$A:$A,0)) -> 50 | J12: =INDEX(FUEL_PARAMETER!$L:$L,MATCH($E12,FUEL_PARAMETER!$A:$A,0)) -> 0 | K12: =INDEX(FUEL_PARAMETER!$M:$M,MATCH($E12,FUEL_PARAMETER!$A:$A,0)) -> GREATER_OF | L12: =IF(K12="ABS_ONLY",IF(I12="",J12,I12),IF(K12="PCT_ONLY",ROUND(H12*G12,1),IF(K12="GREATER_OF",ROUND(MAX(I12,H12*G12),1),IF(K12="LESSER_OF",ROUND(MIN(I12,H12*G12),1),J12)))) -> 73.2 | M12: 2026-08-31T00:00Z | N12: 2026-08-14
A13: APP-0011 | B13: ORDER | C13: ORD-1009 | D13: ORDER_TOLERANCE | E13: PRM-0021 | F13: =INDEX(FUEL_PARAMETER!$E:$E,MATCH($E13,FUEL_PARAMETER!$A:$A,0)) -> MNL|PPC | G13: 100192 | H13: =INDEX(FUEL_PARAMETER!$J:$J,MATCH($E13,FUEL_PARAMETER!$A:$A,0)) -> 0.008 | I13: =INDEX(FUEL_PARAMETER!$K:$K,MATCH($E13,FUEL_PARAMETER!$A:$A,0)) -> 50 | J13: =INDEX(FUEL_PARAMETER!$L:$L,MATCH($E13,FUEL_PARAMETER!$A:$A,0)) -> 0 | K13: =INDEX(FUEL_PARAMETER!$M:$M,MATCH($E13,FUEL_PARAMETER!$A:$A,0)) -> GREATER_OF | L13: =IF(K13="ABS_ONLY",IF(I13="",J13,I13),IF(K13="PCT_ONLY",ROUND(H13*G13,1),IF(K13="GREATER_OF",ROUND(MAX(I13,H13*G13),1),IF(K13="LESSER_OF",ROUND(MIN(I13,H13*G13),1),J13)))) -> 801.5 | M13: 2026-08-31T00:00Z | N13: 2026-08-15
A14: APP-0012 | B14: ORDER | C14: ORD-1028 | D14: ORDER_TOLERANCE | E14: PRM-0021 | F14: =INDEX(FUEL_PARAMETER!$E:$E,MATCH($E14,FUEL_PARAMETER!$A:$A,0)) -> MNL|PPC | G14: 9151 | H14: =INDEX(FUEL_PARAMETER!$J:$J,MATCH($E14,FUEL_PARAMETER!$A:$A,0)) -> 0.008 | I14: =INDEX(FUEL_PARAMETER!$K:$K,MATCH($E14,FUEL_PARAMETER!$A:$A,0)) -> 50 | J14: =INDEX(FUEL_PARAMETER!$L:$L,MATCH($E14,FUEL_PARAMETER!$A:$A,0)) -> 0 | K14: =INDEX(FUEL_PARAMETER!$M:$M,MATCH($E14,FUEL_PARAMETER!$A:$A,0)) -> GREATER_OF | L14: =IF(K14="ABS_ONLY",IF(I14="",J14,I14),IF(K14="PCT_ONLY",ROUND(H14*G14,1),IF(K14="GREATER_OF",ROUND(MAX(I14,H14*G14),1),IF(K14="LESSER_OF",ROUND(MIN(I14,H14*G14),1),J14)))) -> 73.2 | M14: 2026-08-31T00:00Z | N14: 2026-08-21
A15: APP-0013 | B15: ORDER | C15: ORD-1001 | D15: SG_CONVERSION | E15: PRM-0002 | F15: =INDEX(FUEL_PARAMETER!$E:$E,MATCH($E15,FUEL_PARAMETER!$A:$A,0)) -> MNL|PPC | H15: =INDEX(FUEL_PARAMETER!$J:$J,MATCH($E15,FUEL_PARAMETER!$A:$A,0)) -> 0 | I15: =INDEX(FUEL_PARAMETER!$K:$K,MATCH($E15,FUEL_PARAMETER!$A:$A,0)) -> 0 | J15: =INDEX(FUEL_PARAMETER!$L:$L,MATCH($E15,FUEL_PARAMETER!$A:$A,0)) -> 0.7995 | K15: =INDEX(FUEL_PARAMETER!$M:$M,MATCH($E15,FUEL_PARAMETER!$A:$A,0)) -> 0 | L15: =IF(K15="ABS_ONLY",IF(I15="",J15,I15),IF(K15="PCT_ONLY",ROUND(H15*G15,1),IF(K15="GREATER_OF",ROUND(MAX(I15,H15*G15),1),IF(K15="LESSER_OF",ROUND(MIN(I15,H15*G15),1),J15)))) -> 0.7995 | M15: 2026-08-31T00:00Z | N15: 2026-08-14
A16: APP-0014 | B16: ORDER | C16: ORD-1017 | D16: SG_CONVERSION | E16: PRM-0002 | F16: =INDEX(FUEL_PARAMETER!$E:$E,MATCH($E16,FUEL_PARAMETER!$A:$A,0)) -> MNL|PPC | H16: =INDEX(FUEL_PARAMETER!$J:$J,MATCH($E16,FUEL_PARAMETER!$A:$A,0)) -> 0 | I16: =INDEX(FUEL_PARAMETER!$K:$K,MATCH($E16,FUEL_PARAMETER!$A:$A,0)) -> 0 | J16: =INDEX(FUEL_PARAMETER!$L:$L,MATCH($E16,FUEL_PARAMETER!$A:$A,0)) -> 0.7995 | K16: =INDEX(FUEL_PARAMETER!$M:$M,MATCH($E16,FUEL_PARAMETER!$A:$A,0)) -> 0 | L16: =IF(K16="ABS_ONLY",IF(I16="",J16,I16),IF(K16="PCT_ONLY",ROUND(H16*G16,1),IF(K16="GREATER_OF",ROUND(MAX(I16,H16*G16),1),IF(K16="LESSER_OF",ROUND(MIN(I16,H16*G16),1),J16)))) -> 0.7995 | M16: 2026-08-31T00:00Z | N16: 2026-08-16
A17: APP-0015 | B17: TICKET | C17: TK-2020B | D17: SG_CONVERSION | E17: PRM-0004 | F17: =INDEX(FUEL_PARAMETER!$E:$E,MATCH($E17,FUEL_PARAMETER!$A:$A,0)) -> CEB|SHL | H17: =INDEX(FUEL_PARAMETER!$J:$J,MATCH($E17,FUEL_PARAMETER!$A:$A,0)) -> 0 | I17: =INDEX(FUEL_PARAMETER!$K:$K,MATCH($E17,FUEL_PARAMETER!$A:$A,0)) -> 0 | J17: =INDEX(FUEL_PARAMETER!$L:$L,MATCH($E17,FUEL_PARAMETER!$A:$A,0)) -> 0.7975 | K17: =INDEX(FUEL_PARAMETER!$M:$M,MATCH($E17,FUEL_PARAMETER!$A:$A,0)) -> 0 | L17: =IF(K17="ABS_ONLY",IF(I17="",J17,I17),IF(K17="PCT_ONLY",ROUND(H17*G17,1),IF(K17="GREATER_OF",ROUND(MAX(I17,H17*G17),1),IF(K17="LESSER_OF",ROUND(MIN(I17,H17*G17),1),J17)))) -> 0.7975 | M17: 2026-08-31T00:00Z | N17: 2026-08-16
A18: APP-0016 | B18: TICKET | C18: TK-2026 | D18: DENSITY_MAX | E18: PRM-0031 | F18: =INDEX(FUEL_PARAMETER!$E:$E,MATCH($E18,FUEL_PARAMETER!$A:$A,0)) -> JET_A1 | H18: =INDEX(FUEL_PARAMETER!$J:$J,MATCH($E18,FUEL_PARAMETER!$A:$A,0)) -> 0 | I18: =INDEX(FUEL_PARAMETER!$K:$K,MATCH($E18,FUEL_PARAMETER!$A:$A,0)) -> 0 | J18: =INDEX(FUEL_PARAMETER!$L:$L,MATCH($E18,FUEL_PARAMETER!$A:$A,0)) -> 0.84 | K18: =INDEX(FUEL_PARAMETER!$M:$M,MATCH($E18,FUEL_PARAMETER!$A:$A,0)) -> ABS_ONLY | L18: =IF(K18="ABS_ONLY",IF(I18="",J18,I18),IF(K18="PCT_ONLY",ROUND(H18*G18,1),IF(K18="GREATER_OF",ROUND(MAX(I18,H18*G18),1),IF(K18="LESSER_OF",ROUND(MIN(I18,H18*G18),1),J18)))) -> 0.84 | M18: 2026-08-31T00:00Z | N18: 2026-08-18
A19: APP-0017 | B19: INVOICE_LINE | C19: ILN-0007 | D19: PRICE_TOLERANCE | E19: PRM-0040 | F19: =INDEX(FUEL_PARAMETER!$E:$E,MATCH($E19,FUEL_PARAMETER!$A:$A,0)) -> * | H19: =INDEX(FUEL_PARAMETER!$J:$J,MATCH($E19,FUEL_PARAMETER!$A:$A,0)) -> 0 | I19: =INDEX(FUEL_PARAMETER!$K:$K,MATCH($E19,FUEL_PARAMETER!$A:$A,0)) -> 0.0005 | J19: =INDEX(FUEL_PARAMETER!$L:$L,MATCH($E19,FUEL_PARAMETER!$A:$A,0)) -> 0 | K19: =INDEX(FUEL_PARAMETER!$M:$M,MATCH($E19,FUEL_PARAMETER!$A:$A,0)) -> ABS_ONLY | L19: =IF(K19="ABS_ONLY",IF(I19="",J19,I19),IF(K19="PCT_ONLY",ROUND(H19*G19,1),IF(K19="GREATER_OF",ROUND(MAX(I19,H19*G19),1),IF(K19="LESSER_OF",ROUND(MIN(I19,H19*G19),1),J19)))) -> 0.0005 | M19: 2026-08-31T00:00Z | N19: 2026-08-17
A20: APP-0018 | B20: INVOICE_LINE | C20: ILN-0010 | D20: PRICE_TOLERANCE | E20: PRM-0040 | F20: =INDEX(FUEL_PARAMETER!$E:$E,MATCH($E20,FUEL_PARAMETER!$A:$A,0)) -> * | H20: =INDEX(FUEL_PARAMETER!$J:$J,MATCH($E20,FUEL_PARAMETER!$A:$A,0)) -> 0 | I20: =INDEX(FUEL_PARAMETER!$K:$K,MATCH($E20,FUEL_PARAMETER!$A:$A,0)) -> 0.0005 | J20: =INDEX(FUEL_PARAMETER!$L:$L,MATCH($E20,FUEL_PARAMETER!$A:$A,0)) -> 0 | K20: =INDEX(FUEL_PARAMETER!$M:$M,MATCH($E20,FUEL_PARAMETER!$A:$A,0)) -> ABS_ONLY | L20: =IF(K20="ABS_ONLY",IF(I20="",J20,I20),IF(K20="PCT_ONLY",ROUND(H20*G20,1),IF(K20="GREATER_OF",ROUND(MAX(I20,H20*G20),1),IF(K20="LESSER_OF",ROUND(MIN(I20,H20*G20),1),J20)))) -> 0.0005 | M20: 2026-08-31T00:00Z | N20: 2026-08-18

Sheet APPLICATION_LOG
A1: APPLICATION_LOG - PK log_id | every posting attempt, error and warning; drilled into from the posting error screens
A2: log_id | B2: log_utc | C2: severity | D2: process_code | E2: entity_type | F2: entity_id | G2: message_code | H2: message_text | I2: error_category | J2: technical_detail | K2: target_system | L2: attempt_no | M2: retryable | N2: resolution_status | O2: resolved_by | P2: resolved_utc | Q2: correlation_id
A3: LOG-0007 | B3: 2026-08-31T02:15:04Z | C3: ERROR | D3: INV_POSTING | E3: FUEL_INVOICE | F3: INV-0002 | G3: FI_ACCT_MISSING | H3: GL account not found for expense type AVFUEL at company code 1000 | I3: MASTER_DATA | J3: SAP RFC: KI235 Account 0000512100 not created in CoCd 1000 | K3: SAP_S4 | L3: 3 | M3: Y | N3: OPEN | Q3: CORR-99120
A4: LOG-0008 | B4: 2026-08-31T02:15:04Z | C4: ERROR | D4: INV_POSTING | E4: FUEL_INVOICE_LINE | F4: ILN-0010 | G4: FI_TAX_CODE_INVALID | H4: Tax code V0 not permitted for supplier PPC in country PH | I4: MASTER_DATA | J4: SAP RFC: FF805 Tax code V0 country PH | K4: SAP_S4 | L4: 3 | M4: Y | N4: OPEN | Q4: CORR-99120
A5: LOG-0009 | B5: 2026-08-31T02:15:05Z | C5: WARNING | D5: INV_POSTING | E5: FUEL_INVOICE_LINE | F5: ILN-0011 | G5: PRICE_VAR_TOLERANCE | H5: Line held: density under review against batch certificate | I5: BUSINESS_RULE | J5: Internal rule VR36 | K5: FUELSPHERE | L5: 3 | M5: N | N5: OPEN | Q5: CORR-99120
A6: LOG-0010 | B6: 2026-08-30T22:04:11Z | C6: INFO | D6: INV_POSTING | E6: FUEL_INVOICE | F6: INV-0003 | G6: FI_POST_SUCCESS | H6: Invoice posted successfully | I6: NONE | J6: SAP document 5100048812 company code 1000 | K6: SAP_S4 | L6: 1 | M6: N | N6: CLOSED | O6: SYSTEM | P6: 2026-08-30T22:04:11Z | Q6: CORR-99101
A7: LOG-0011 | B7: 2026-08-31T02:15:09Z | C7: ERROR | D7: INV_POSTING | E7: FUEL_INVOICE | F7: INV-0004 | G7: FI_PERIOD_CLOSED | H7: Posting period 08/2026 is closed for company code 1000 | I7: PERIOD_CONTROL | J7: SAP RFC: F5201 Posting period 008 2026 not open | K7: SAP_S4 | L7: 1 | M7: Y | N7: OPEN | Q7: CORR-99133
A8: LOG-0012 | B8: 2026-08-31T02:15:09Z | C8: ERROR | D8: INV_POSTING | E8: FUEL_INVOICE | F8: INV-0002 | G8: FI_VENDOR_BLOCKED | H8: Vendor PPC is blocked for posting in company code 1000 | I8: MASTER_DATA | J8: SAP RFC: F5138 Vendor blocked | K8: SAP_S4 | L8: 2 | M8: Y | N8: OPEN | Q8: CORR-99115
A9: LOG-0013 | B9: 2026-08-29T04:12:33Z | C9: ERROR | D9: INV_POSTING | E9: FUEL_INVOICE | F9: INV-0002 | G9: IF_TIMEOUT | H9: Connection to target system timed out after 30s | I9: CONNECTIVITY | J9: HTTP 504 gateway timeout on /sap/opu/odata/… | K9: SAP_S4 | L9: 1 | M9: Y | N9: CLOSED | O9: A.REYES | P9: 2026-08-29T09:00Z | Q9: CORR-99108
A10: LOG-0014 | B10: 2026-08-30T09:12:00Z | C10: ERROR | D10: INV_VALIDATION | E10: FUEL_INVOICE | F10: INV-0005 | G10: DUP_TICKET_BILLED | H10: Ticket TK-2001 already billed on invoice line ILN-0001 | I10: DUPLICATE | J10: Internal rule VR33 | K10: FUELSPHERE | L10: 1 | M10: N | N10: OPEN | Q10: CORR-99140
A11: LOG-0015 | B11: 2026-08-31T02:15:12Z | C11: ERROR | D11: INV_POSTING | E11: FUEL_INVOICE_LINE | F11: ILN-0008 | G11: FI_REF_NOT_FOUND | H11: No goods receipt reference found for invoice line | I11: MASTER_DATA | J11: SAP RFC: M8147 Reference document missing | K11: SAP_S4 | L11: 1 | M11: Y | N11: OPEN | Q11: CORR-99133
A12: LOG-0016 | B12: 2026-08-31T02:15:14Z | C12: ERROR | D12: INV_POSTING | E12: FUEL_INVOICE | F12: INV-0004 | G12: FI_CURRENCY_RATE | H12: Exchange rate for USD to PHP not maintained on 2026-08-21 | I12: MASTER_DATA | J12: SAP RFC: SG105 Rate type M missing | K12: SAP_S4 | L12: 1 | M12: Y | N12: OPEN | Q12: CORR-99133

Sheet AI_SETTING
A1: AI_SETTING - configuration so the AI features bind to whatever ecosystem the organisation runs. Secrets held by reference only
A2: setting_id | B2: setting_group | C2: setting_key | D2: setting_value | E2: value_type | F2: scope_level | G2: scope_key | H2: is_secret | I2: status | J2: valid_from | K2: valid_to | L2: approved_by | M2: description
A3: AIS-0001 | B3: PROVIDER | C3: AI_PROVIDER | D3: ANTHROPIC | E3: ENUM | F3: GLOBAL | G3: * | H3: N | I3: ACTIVE | J3: 2026-01-01 | L3: IT.ARCH | M3: Which AI vendor the organisation uses
A4: AIS-0002 | B4: PROVIDER | C4: AI_ENDPOINT_URL | D4: https://<tenant-endpoint>/v1/messages | E4: URL | F4: GLOBAL | G4: * | H4: N | I4: ACTIVE | J4: 2026-01-01 | L4: IT.ARCH | M4: Base endpoint; may point at a private gateway
A5: AIS-0003 | B5: PROVIDER | C5: AI_MODEL | D5: <model-identifier> | E5: STRING | F5: GLOBAL | G5: * | H5: N | I5: ACTIVE | J5: 2026-01-01 | L5: IT.ARCH | M5: Model used for error summarisation
A6: AIS-0004 | B6: PROVIDER | C6: AI_API_KEY_REF | D6: VAULT://fuelsphere/ai/key | E6: SECRET_REF | F6: GLOBAL | G6: * | H6: Y | I6: ACTIVE | J6: 2026-01-01 | L6: IT.SEC | M6: Reference only; never store the key itself
A7: AIS-0005 | B7: PROVIDER | C7: AI_AUTH_MODE | D7: API_KEY | E7: ENUM | F7: GLOBAL | G7: * | H7: N | I7: ACTIVE | J7: 2026-01-01 | L7: IT.SEC | M7: API_KEY / OAUTH2 / MTLS / IAM_ROLE
A8: AIS-0010 | B8: LIMITS | C8: AI_MAX_TOKENS | D8: 2000 | E8: INT | F8: GLOBAL | G8: * | H8: N | I8: ACTIVE | J8: 2026-01-01 | L8: IT.ARCH | M8: Response ceiling per call
A9: AIS-0011 | B9: LIMITS | C9: AI_TIMEOUT_SEC | D9: 45 | E9: INT | F9: GLOBAL | G9: * | H9: N | I9: ACTIVE | J9: 2026-01-01 | L9: IT.ARCH | M9: Call timeout
A10: AIS-0012 | B10: LIMITS | C10: AI_MAX_ERRORS_PER_BATCH | D10: 200 | E10: INT | F10: GLOBAL | G10: * | H10: N | I10: ACTIVE | J10: 2026-01-01 | L10: IT.ARCH | M10: Log rows sent in one analysis request
A11: AIS-0013 | B11: LIMITS | C11: AI_MONTHLY_CALL_CAP | D11: 5000 | E11: INT | F11: GLOBAL | G11: * | H11: N | I11: ACTIVE | J11: 2026-01-01 | L11: FIN.OPS | M11: Cost control
A12: AIS-0020 | B12: GOVERNANCE | C12: AI_FEATURE_ENABLED | D12: Y | E12: BOOLEAN | F12: GLOBAL | G12: * | H12: N | I12: ACTIVE | J12: 2026-01-01 | L12: IT.ARCH | M12: Master switch; system must work fully with AI off
A13: AIS-0021 | B13: GOVERNANCE | C13: AI_DATA_REDACTION | D13: Y | E13: BOOLEAN | F13: GLOBAL | G13: * | H13: N | I13: ACTIVE | J13: 2026-01-01 | L13: IT.SEC | M13: Strip supplier names, prices and IDs before sending
A14: AIS-0022 | B14: GOVERNANCE | C14: AI_RETENTION_DAYS | D14: 90 | E14: INT | F14: GLOBAL | G14: * | H14: N | I14: ACTIVE | J14: 2026-01-01 | L14: IT.SEC | M14: How long AI_ANALYSIS rows are kept
... A17: AIS-0030 | B17: PROMPT | C17: PROMPT_ERROR_SUMMARY | D17: TEMPLATE://error_summary_v3 | E17: TEMPLATE_REF | F17: GLOBAL | G17: * | H17: N | I17: ACTIVE | J17: 2026-06-01 | L17: FIN.OPS | M17: Versioned prompt for grouping and resolution proposal
A18: AIS-0031 | B18: PROMPT | C18: PROMPT_ERROR_SUMMARY | D18: TEMPLATE://error_summary_v2 | E18: TEMPLATE_REF | F18: GLOBAL | G18: * | H18: N | I18: SUPERSEDED | J18: 2026-01-01 | K18: 2026-05-31 | L18: FIN.OPS | M18: Replaced by v3

Sheet AI_ANALYSIS
A1: AI_ANALYSIS - AI grouped errors by resolution type and proposed steps. Every group carries a human status; nothing acts unattended
A2: analysis_id | B2: requested_utc | C2: requested_by | D2: scope_description | E2: log_count_analysed | F2: group_no | G2: group_label | H2: error_category | I2: log_ids_in_group | J2: root_cause_summary | K2: proposed_resolution | L2: resolution_owner | M2: confidence | N2: human_status | O2: reviewed_by | P2: reviewed_utc | Q2: prompt_version | R2: model_used | S2: tokens_used
A3: AIA-0001 | B3: 2026-08-31T08:00Z | C3: A.REYES | D3: All OPEN posting errors, MNL, Aug 2026 | E3: 9 | F3: 1 | G3: Missing finance master data | H3: MASTER_DATA | I3: LOG-0007, LOG-0012, LOG-0016 | J3: Three distinct master data objects are absent in the target system: an expense GL account, a vendor posting block, and a currency rate. All three block posting at the header or line level. | K3: Raise a master data request covering all three objects together rather than individually. Sequence: unblock vendor, create GL account, maintain rate for the affected dates. Reprocess as a single batch afterwards. | L3: FINANCE_MDM | M3: HIGH | N3: ACCEPTED | O3: A.REYES | P3: 2026-08-31T09:20Z | Q3: error_summary_v3 | R3: <model-identifier> | S3: 1840
A4: AIA-0001 | B4: 2026-08-31T08:00Z | C4: A.REYES | D4: All OPEN posting errors, MNL, Aug 2026 | E4: 9 | F4: 2 | G4: Period control | H4: PERIOD_CONTROL | I4: LOG-0011 | J4: Posting period 08/2026 is closed for the company code. This is a timing issue, not a data defect. | K4: Confirm with financial control whether the period reopens or the document should post to the next open period. If the latter, adjust the posting date and reprocess. No data correction needed. | L4: FINANCE_CONTROL | M4: HIGH | N4: ACCEPTED | O4: A.REYES | P4: 2026-08-31T09:22Z | Q4: error_summary_v3 | R4: <model-identifier> | S4: 1840
A5: AIA-0001 | B5: 2026-08-31T08:00Z | C5: A.REYES | D5: All OPEN posting errors, MNL, Aug 2026 | E5: 9 | F5: 3 | G5: Tax configuration | H5: MASTER_DATA | I5: LOG-0008 | J5: The tax code applied to the line is not valid for this supplier and country combination. | K5: Verify the correct tax code with tax accounting, then correct the determination rule so future lines derive it automatically rather than fixing this line in isolation. | L5: FINANCE_TAX | M5: MEDIUM | N5: UNDER_REVIEW | Q5: error_summary_v3 | R5: <model-identifier> | S5: 1840
A6: AIA-0001 | B6: 2026-08-31T08:00Z | C6: A.REYES | D6: All OPEN posting errors, MNL, Aug 2026 | E6: 9 | F6: 4 | G6: Reference document missing | H6: MASTER_DATA | I6: LOG-0015 | J6: The invoice line has no goods receipt reference. This traces back to ILN-0008, which has no matching fuel ticket. | K6: Do not resolve in the target system. This is the phantom billing case: the line must be disputed with the supplier and removed from the invoice before posting is retried. | L6: FUEL_OPS | M6: HIGH | N6: ACCEPTED | O6: A.REYES | P6: 2026-08-31T09:25Z | Q6: error_summary_v3 | R6: <model-identifier> | S6: 1840
A7: AIA-0001 | B7: 2026-08-31T08:00Z | C7: A.REYES | D7: All OPEN posting errors, MNL, Aug 2026 | E7: 9 | F7: 5 | G7: Business rule hold | H7: BUSINESS_RULE | I7: LOG-0009, LOG-0014 | J7: Two internal holds, not target system errors: a density under review and a duplicate ticket already billed. | K7: These require a business decision before posting is attempted at all. The duplicate should be rejected outright; the density case needs the batch certificate comparison completed first. | L7: FUEL_OPS | M7: MEDIUM | N7: UNDER_REVIEW | Q7: error_summary_v3 | R7: <model-identifier> | S7: 1840
A8: AIA-0001 | B8: 2026-08-31T08:00Z | C8: A.REYES | D8: All OPEN posting errors, MNL, Aug 2026 | E8: 9 | F8: 6 | G8: Transient connectivity | H8: CONNECTIVITY | I8: LOG-0013 | J8: A single gateway timeout, already closed. No pattern across the batch. | K8: No action. Confirm the retry policy already covers transient failures so these do not reach the manual queue. | L8: IT_INTEGRATION | M8: HIGH | N8: ACCEPTED | O8: A.REYES | P8: 2026-08-31T09:26Z | Q8: error_summary_v3 | R8: <model-identifier> | S8: 1840

Sheet UI Inventory
A1: UI INVENTORY - screens required across the fuel data model
A2: Screen ID | B2: Screen Name | C2: Primary Entity | D2: Screen Type | E2: Purpose | F2: Key Data Shown | G2: Navigates To | H2: Roles
A3: UI-01 | B3: Flight Leg Worklist | C3: FLIGHT_OPERATIONS | D3: List / search | E3: Find legs by date, station, tail or status | F3: Flight no, date, route, status, ops phase, fuel reconciled flag | G3: UI-02 | H3: Fuel Ops, Dispatch, Read only
A4: UI-02 | B4: Flight Leg Detail | C4: FLIGHT_OPERATIONS | D4: Detail | E4: Single leg with all fuel activity in one place | F4: Leg header, plan versions, orders, tickets, variances | G4: UI-04, UI-06, UI-09 | H4: Fuel Ops, Dispatch
A5: UI-03 | B5: Plan Version List | C5: FD_FUEL_PLAN | D5: List | E5: All plan versions for a leg in sequence | F5: Version, status, change reason, block fuel, required uplift | G5: UI-04 | H5: Fuel Ops, Dispatch
A6: UI-04 | B6: Fuel Plan Detail | C6: FD_FUEL_PLAN | D6: Detail | E6: Full fuel breakdown for one version | F6: Trip, contingency, alternate, reserve, taxi, extra, FOB, uplift | G6: UI-05 | H6: Fuel Ops, Dispatch
A7: UI-05 | B7: Plan Version Compare | C7: FD_FUEL_PLAN | D7: Comparison | E7: Side by side diff of two versions | F7: Field level deltas with change reason | H7: Fuel Ops, Dispatch
A8: UI-06 | B8: Fuel Order Worklist | C8: FUEL_ORDER | D8: List / search | E8: Orders by station, supplier, status, fulfilment check | F8: Order no, version, ordered, delivered, variance, fulfilment check | G8: UI-07 | H8: Fuel Ops
A9: UI-07 | B9: Fuel Order Detail | C9: FUEL_ORDER | D9: Detail | E9: One order with all linked tickets | F9: Order header, ticket list, rollup, tolerance applied | G9: UI-10, UI-19 | H9: Fuel Ops
A10: UI-08 | B10: Order Fulfilment Exceptions | C10: FUEL_ORDER | D10: Exception queue | E10: Under and over delivered orders needing action | F10: Variance, tolerance, reason code, ageing | G10: UI-07 | H10: Fuel Ops, Supervisor
A11: UI-09 | B11: Fuel Ticket Worklist | C11: FUEL_TICKET | D11: List / search | E11: Tickets by station, supplier, tail, date, match status | F11: Ticket no, registration, quantity, match status, recon status | G11: UI-10 | H11: Fuel Ops
A12: UI-10 | B12: Fuel Ticket Detail | C12: FUEL_TICKET | D12: Detail | E12: One fuel event end to end | F12: Meter, density, FQIS, variance, signatures, source, raw payload | G12: UI-19, UI-24 | H12: Fuel Ops
A13: UI-11 | B13: Manual Ticket Entry | C13: FUEL_TICKET | D13: Data entry | E13: Capture a ticket with no electronic feed | F13: Entry form with plausibility checks on density and quantity | G13: UI-10 | H13: Fuel Ops
A14: UI-12 | B14: Unmatched Ticket Workbench | C14: FUEL_TICKET | D14: Exception queue | E14: Tickets with no order or no leg | F14: Ticket, registration, station, time, candidate legs | G14: UI-10 | H14: Fuel Ops
A15: UI-13 | B15: FOB Reconciliation Review | C15: FUEL_TICKET | D15: Exception queue | E15: Metered mass versus FQIS beyond tolerance | F15: Metered, FQIS, variance, tolerance applied, status | G15: UI-10 | H15: Fuel Ops, Supervisor
A16: UI-14 | B16: Bowser Bias Report | C16: FUEL_TICKET | D16: Analytics | E16: One directional variance by bowser over time | F16: Bowser, ticket count, total variance, bias percent, trend | G16: UI-13 | H16: Fuel Ops, Supervisor
A17: UI-15 | B17: Invoice Worklist | C17: FUEL_INVOICE | D17: List / search | E17: Invoices by supplier, station, period, status | F17: Invoice no, period, total, status, dispute flag, attempts | G17: UI-16 | H17: Finance, Fuel Ops
A18: UI-16 | B18: Invoice Detail | C18: FUEL_INVOICE | D18: Detail | E18: Header plus all lines with match results | F18: Header, derived total vs stated total, line grid | G18: UI-17, UI-18, UI-23 | H18: Finance, Fuel Ops
A19: UI-17 | B19: Invoice Line Exceptions | C19: FUEL_INVOICE_LINE | D19: Exception queue | E19: Lines failing quantity, price, duplicate or no ticket checks | F19: Line, ticket, variance, three way status, duplicate check | G19: UI-10, UI-16 | H19: Finance, Fuel Ops
... A93: UI-91 | B93: Expired Claims Report | C93: FUEL_CLAIM_WINDOW | D93: Analytics | E93: Value lost to expired claim windows, by supplier and station | F93: Supplier, station, claims expired, value lost, trend | G93: UI-90 | H93: Finance, Supervisor

Sheet Action Catalogue
A1: ACTION CATALOGUE - what users and the system can do, and under what conditions
A2: Action ID | B2: Screen | C2: Action | D2: Trigger | E2: Selection | F2: Preconditions | G2: Effect | H2: Audit / Log | I2: Roles
A3: AC-01 | B3: UI-06 | C3: Amend order | D3: User | E3: Single | F3: Order not frozen and fuelling not started | G3: Creates order version n+1; supersedes previous | H3: Order version history | I3: Fuel Ops
A4: AC-02 | B4: UI-06 | C4: Cancel order | D4: User | E4: Single / multiple | F4: No ticket linked | G4: Order status CANCELLED | H4: Audit fields | I4: Fuel Ops
A5: AC-03 | B5: UI-07 | C5: Raise top up order | D5: User | E5: Single | F5: Prior order fulfilled or frozen | G5: New order of type TOP_UP against the active plan | H5: Order version history | I5: Fuel Ops
A6: AC-04 | B6: UI-08 | C6: Set under delivery reason | D6: User | E6: Single / multiple | F6: fulfilment_check is UNDER_DELIVERED | G6: Reason code stored; exception cleared | H6: Audit fields | I6: Fuel Ops
A7: AC-05 | B7: UI-09 | C7: Import tickets | D7: Scheduled / User | E7: Batch | F7: Feed available | G7: Tickets created; auto match attempted | H7: APPLICATION_LOG | I7: System, Fuel Ops
A8: AC-06 | B8: UI-11 | C8: Create manual ticket | D8: User | E8: Single | F8: Plausibility checks pass | G8: Ticket created with source MANUAL | H8: Audit fields | I8: Fuel Ops
A9: AC-07 | B9: UI-12 | C9: Match ticket to leg or order | D9: User | E9: Single / multiple | F9: Ticket is UNMATCHED | G9: FKs populated; match_status MATCHED | H9: Audit fields | I9: Fuel Ops
A10: AC-08 | B10: UI-12 | C10: Mark ticket unallocatable | D10: User | E10: Single | F10: No candidate leg found | G10: cost_allocation_basis set to AIRCRAFT or STATION_OVERHEAD | H10: Audit fields | I10: Fuel Ops, Supervisor
A11: AC-09 | B11: UI-13 | C11: Accept variance with reason | D11: User | E11: Single / multiple | F11: recon_status is FAIL | G11: Variance accepted; reason recorded | H11: Audit fields | I11: Supervisor
A12: AC-10 | B12: UI-13 | C12: Raise supplier dispute | D12: User | E12: Single / multiple | F12: recon_status is FAIL | G12: Dispute record created; ticket flagged DISPUTED | H12: APPLICATION_LOG | I12: Fuel Ops, Finance
A13: AC-11 | B13: UI-15 | C13: Import invoice | D13: Scheduled / User | E13: Batch | F13: Feed or file available | G13: Invoice and lines created; three way match run | H13: APPLICATION_LOG | I13: System, Finance
... A115: AC-113 | B115: System | C115: Escalate approaching deadline | D115: Automatic | E115: Batch | F115: Days remaining below the escalation threshold | G115: Notification raised to the claim owner and supervisor | H115: APPLICATION_LOG | I115: System

Sheet CRITICAL_FIELD_CONFIG
A1: CRITICAL_FIELD_CONFIG - which inbound field changes force PENDING_UPDATE. Configuration, not code
A2: config_id | B2: table_name | C2: field_name | D2: is_critical | E2: on_change_action | F2: requires_confirmation | G2: blocks_actions | H2: cascade_reprocess | I2: rationale | J2: valid_from | K2: status
A3: CFC-01 | B3: FLIGHT_OPERATIONS | C3: actual_registration | D3: Y | E3: PENDING_UPDATE | F3: Y | G3: ORDER_CREATE, ORDER_SEND, INVOICE_POST | H3: FD_FUEL_PLAN, FUEL_ORDER | I3: Drives plan, order and ticket matching | J3: 2026-01-01 | K3: ACTIVE
A4: CFC-02 | B4: FLIGHT_OPERATIONS | C4: aircraft_type | D4: Y | E4: PENDING_UPDATE | F4: Y | G4: ORDER_CREATE | H4: FD_FUEL_PLAN | I4: Sets performance factor, tank capacity and tolerance band | J4: 2026-01-01 | K4: ACTIVE
A5: CFC-03 | B5: FLIGHT_OPERATIONS | C5: departure_station | D5: Y | E5: PENDING_UPDATE | F5: Y | G5: ORDER_CREATE, ORDER_SEND | H5: FUEL_ORDER | I5: Determines supplier contract and conversion density | J5: 2026-01-01 | K5: ACTIVE
A6: CFC-04 | B6: FLIGHT_OPERATIONS | C6: arrival_station | D6: Y | E6: PENDING_UPDATE | F6: N | H6: FD_FUEL_PLAN | I6: Changes trip fuel and tankering economics | J6: 2026-01-01 | K6: ACTIVE
A7: CFC-05 | B7: FLIGHT_OPERATIONS | C7: std_utc | D7: Y | E7: PENDING_UPDATE | F7: N | G7: ORDER_SEND | H7: FUEL_ORDER | I7: Sets the fuelling window and order timing | J7: 2026-01-01 | K7: ACTIVE
A8: CFC-06 | B8: FLIGHT_OPERATIONS | C8: sta_utc | D8: N | E8: PARTIAL_APPLY | F8: N | I8: Informational for fuel purposes | J8: 2026-01-01 | K8: ACTIVE
A9: CFC-07 | B9: FLIGHT_OPERATIONS | C9: flight_status | D9: Y | E9: PENDING_UPDATE | F9: N | H9: FUEL_ORDER, FUEL_TICKET | I9: Drives freeze logic and cost allocation | J9: 2026-01-01 | K9: ACTIVE
A10: CFC-08 | B10: FLIGHT_OPERATIONS | C10: service_type | D10: Y | E10: PENDING_UPDATE | F10: N | G10: ORDER_CREATE | I10: Decides whether a fuel plan and order are expected at all | J10: 2026-01-01 | K10: ACTIVE
A11: CFC-09 | B11: FLIGHT_OPERATIONS | C11: operating_carrier | D11: Y | E11: PENDING_UPDATE | F11: Y | G11: ORDER_CREATE, INVOICE_POST | H11: FUEL_ORDER, FUEL_INVOICE | I11: Determines which contract applies and who is invoiced | J11: 2026-01-01 | K11: ACTIVE
A12: CFC-10 | B12: FLIGHT_OPERATIONS | C12: delay_code | D12: N | E12: PARTIAL_APPLY | F12: N | I12: Reporting only | J12: 2026-01-01 | K12: ACTIVE
A13: CFC-11 | B13: FLIGHT_OPERATIONS | C13: atd_utc | D13: N | E13: PARTIAL_APPLY | F13: N | I13: Actuals; no forward dependency | J13: 2026-01-01 | K13: ACTIVE
A14: CFC-12 | B14: FLIGHT_OPERATIONS | C14: ata_utc | D14: N | E14: PARTIAL_APPLY | F14: N | I14: Actuals; no forward dependency | J14: 2026-01-01 | K14: ACTIVE
A15: CFC-13 | B15: FLIGHT_OPERATIONS | C15: ops_phase | D15: N | E15: PARTIAL_APPLY | F15: N | I15: High frequency; would flood the queue if critical | J15: 2026-01-01 | K15: ACTIVE

Sheet IF_FLIGHT_OPERATIONS_STG
A1: IF_FLIGHT_OPERATIONS_STG - inbound staging. change_type compares against the LATEST STAGING record, not the target, so reversals are not misread as no-ops
A2: TC_ID | B2: stg_id | C2: if_run_id | D2: source_system | E2: source_record_key | F2: source_change_utc | G2: received_utc | H2: operation | I2: resolved_business_key | J2: resolved_flight_leg_id | K2: m_registration | L2: m_departure_station | M2: m_std_utc | N2: m_service_type | O2: m_operating_carrier | P2: m_delay_code | Q2: critical_field_changed | R2: payload_hash | S2: prior_latest_stg_id | T2: prior_latest_hash | U2: target_applied_hash | V2: change_type | W2: record_status | X2: is_latest_for_key | Y2: superseded_by_stg_id | Z2: first_error_code | AA2: error_field | AB2: attempt_count | AC2: target_sync_status | AD2: note
A3: TC34 | B3: STG-0001 | C3: RUN-101 | D3: OPS_SYS | E3: PR0132-14AUG-1 | F3: 2026-08-14T01:00Z | G3: 2026-08-14T01:05Z | H3: UPDATE | I3: PR|0132|2026-08-14|1 | J3: LEG-26081404 | K3: RP-C4108 | L3: MNL | M3: 18:00 | N3: J | O3: PR | Q3: actual_registration | R3: H-A1 | V3: =IF(T3="","INITIAL",IF(R3=T3,"NO_CHANGE",IF(AND(U3<>"",R3=U3),"REVERSAL","CHANGE"))) -> INITIAL | W3: APPLIED | X3: N | Y3: STG-0002 | AB3: 1 | AC3: CURRENT | AD3: Day 1 - tail in master, applies cleanly
A4: TC34 | B4: STG-0002 | C4: RUN-118 | D4: OPS_SYS | E4: PR0132-14AUG-1 | F4: 2026-08-15T02:00Z | G4: 2026-08-15T02:04Z | H4: UPDATE | I4: PR|0132|2026-08-14|1 | J4: LEG-26081404 | K4: RP-C4109 | L4: MNL | M4: 18:00 | N4: J | O4: PR | Q4: actual_registration | R4: H-A2 | S4: STG-0001 | T4: H-A1 | U4: H-A1 | V4: =IF(T4="","INITIAL",IF(R4=T4,"NO_CHANGE",IF(AND(U4<>"",R4=U4),"REVERSAL","CHANGE"))) -> CHANGE | W4: SUPERSEDED_ERROR | X4: N | Y4: STG-0003 | Z4: AC_NOT_IN_MASTER | AA4: actual_registration | AB4: 1 | AC4: PENDING_UPDATE | AD4: Tail not in aircraft master
A5: TC34 | B5: STG-0003 | C5: RUN-127 | D5: OPS_SYS | E5: PR0132-14AUG-1 | F5: 2026-08-15T09:00Z | G5: 2026-08-15T09:03Z | H5: UPDATE | I5: PR|0132|2026-08-14|1 | J5: LEG-26081404 | K5: RP-C4109 | L5: MNL | M5: 18:00 | N5: J | O5: PR | Q5: actual_registration | R5: H-A2 | S5: STG-0002 | T5: H-A2 | U5: H-A1 | V5: =IF(T5="","INITIAL",IF(R5=T5,"NO_CHANGE",IF(AND(U5<>"",R5=U5),"REVERSAL","CHANGE"))) -> NO_CHANGE | W5: SUPERSEDED_ERROR | X5: N | Y5: STG-0004 | Z5: AC_NOT_IN_MASTER | AA5: actual_registration | AB5: 1 | AC5: PENDING_UPDATE | AD5: Same payload resent - still errors, superseded by next
A6: TC34 | B6: STG-0004 | C6: RUN-141 | D6: OPS_SYS | E6: PR0132-14AUG-1 | F6: 2026-08-16T02:00Z | G6: 2026-08-16T02:06Z | H6: UPDATE | I6: PR|0132|2026-08-14|1 | J6: LEG-26081404 | K6: RP-C4109 | L6: MNL | M6: 18:00 | N6: J | O6: PR | Q6: actual_registration | R6: H-A2 | S6: STG-0003 | T6: H-A2 | U6: H-A1 | V6: =IF(T6="","INITIAL",IF(R6=T6,"NO_CHANGE",IF(AND(U6<>"",R6=U6),"REVERSAL","CHANGE"))) -> NO_CHANGE | W6: ERROR | X6: Y | Z6: AC_NOT_IN_MASTER | AA6: actual_registration | AB6: 3 | AC6: STALE | AD6: The only row in the error worklist for this key
A7: TC35 | B7: STG-0005 | C7: RUN-101 | D7: OPS_SYS | E7: PR0126-14AUG-1 | F7: 2026-08-14T01:00Z | G7: 2026-08-14T01:05Z | H7: UPDATE | I7: PR|0126|2026-08-14|1 | J7: LEG-26081401 | K7: RP-C4108 | L7: MNL | M7: 06:00 | N7: J | O7: PR | R7: H-B1 | V7: =IF(T7="","INITIAL",IF(R7=T7,"NO_CHANGE",IF(AND(U7<>"",R7=U7),"REVERSAL","CHANGE"))) -> INITIAL | W7: APPLIED | X7: N | Y7: STG-0006 | AB7: 1 | AC7: CURRENT | AD7: Baseline apply
A8: TC35 | B8: STG-0006 | C8: RUN-118 | D8: OPS_SYS | E8: PR0126-14AUG-1 | F8: 2026-08-14T04:00Z | G8: 2026-08-14T04:03Z | H8: UPDATE | I8: PR|0126|2026-08-14|1 | J8: LEG-26081401 | K8: RP-C4108 | L8: MNL | M8: 06:00 | N8: J | O8: PR | R8: H-B1 | S8: STG-0005 | T8: H-B1 | U8: H-B1 | V8: =IF(T8="","INITIAL",IF(R8=T8,"NO_CHANGE",IF(AND(U8<>"",R8=U8),"REVERSAL","CHANGE"))) -> NO_CHANGE | W8: IGNORED_NO_CHANGE | X8: Y | AB8: 0 | AC8: CURRENT | AD8: Identical resend - never enters the worklist
A9: TC36 | B9: STG-0007 | C9: RUN-150 | D9: OPS_SYS | E9: PR0152-18AUG-1 | F9: 2026-08-18T01:00Z | G9: 2026-08-18T01:04Z | H9: UPDATE | I9: PR|0152|2026-08-18|1 | J9: LEG-26081417 | K9: RP-C4128 | L9: MNL | M9: 06:00 | N9: J | O9: PR | R9: H-C1 | V9: =IF(T9="","INITIAL",IF(R9=T9,"NO_CHANGE",IF(AND(U9<>"",R9=U9),"REVERSAL","CHANGE"))) -> INITIAL | W9: APPLIED | X9: N | Y9: STG-0008 | AB9: 1 | AC9: CURRENT | AD9: Applied - target now holds RP-C4128
A10: TC36 | B10: STG-0008 | C10: RUN-158 | D10: OPS_SYS | E10: PR0152-18AUG-1 | F10: 2026-08-18T05:00Z | G10: 2026-08-18T05:02Z | H10: UPDATE | I10: PR|0152|2026-08-18|1 | J10: LEG-26081417 | K10: RP-C4131 | L10: MNL | M10: 06:00 | N10: J | O10: PR | Q10: actual_registration | R10: H-C2 | S10: STG-0007 | T10: H-C1 | U10: H-C1 | V10: =IF(T10="","INITIAL",IF(R10=T10,"NO_CHANGE",IF(AND(U10<>"",R10=U10),"REVERSAL","CHANGE"))) -> CHANGE | W10: SUPERSEDED_ERROR | X10: N | Y10: STG-0009 | Z10: AC_NOT_IN_MASTER | AA10: actual_registration | AB10: 1 | AC10: PENDING_UPDATE | AD10: Tail change fails - leg goes PENDING_UPDATE
A11: TC36 | B11: STG-0009 | C11: RUN-166 | D11: OPS_SYS | E11: PR0152-18AUG-1 | F11: 2026-08-18T07:00Z | G11: 2026-08-18T07:01Z | H11: UPDATE | I11: PR|0152|2026-08-18|1 | J11: LEG-26081417 | K11: RP-C4128 | L11: MNL | M11: 06:00 | N11: J | O11: PR | Q11: actual_registration | R11: H-C1 | S11: STG-0008 | T11: H-C2 | U11: H-C1 | V11: =IF(T11="","INITIAL",IF(R11=T11,"NO_CHANGE",IF(AND(U11<>"",R11=U11),"REVERSAL","CHANGE"))) -> REVERSAL | W11: APPLIED | X11: Y | AB11: 1 | AC11: CURRENT | AD11: REVERSAL - matches target but not latest staging. Clears PENDING_UPDATE
A12: TC37 | B12: STG-0010 | C12: RUN-170 | D12: OPS_SYS | E12: PR0126-14AUG-1 | F12: 2026-08-14T00:30Z | G12: 2026-08-18T09:00Z | H12: UPDATE | I12: PR|0126|2026-08-14|1 | J12: LEG-26081401 | K12: RP-C4106 | L12: MNL | M12: 06:00 | N12: J | O12: PR | Q12: actual_registration | R12: H-B0 | S12: STG-0006 | T12: H-B1 | U12: H-B1 | V12: =IF(T12="","INITIAL",IF(R12=T12,"NO_CHANGE",IF(AND(U12<>"",R12=U12),"REVERSAL","CHANGE"))) -> CHANGE | W12: IGNORED_STALE | X12: N | AB12: 0 | AC12: CURRENT | AD12: source_change_utc older than last applied - ordered by source, not receipt
A13: TC38 | B13: STG-0011 | C13: RUN-175 | D13: OPS_SYS | E13: PR0170-22AUG-1 | F13: 2026-08-22T01:00Z | G13: 2026-08-22T01:03Z | H13: INSERT | I13: PR|0170|2026-08-22|1 | K13: RP-C4142 | L13: ZZZ | M13: 06:00 | N13: J | O13: PR | Q13: departure_station | R13: H-D1 | V13: =IF(T13="","INITIAL",IF(R13=T13,"NO_CHANGE",IF(AND(U13<>"",R13=U13),"REVERSAL","CHANGE"))) -> INITIAL | W13: ERROR | X13: Y | Z13: STN_NOT_IN_MASTER | AA13: departure_station | AB13: 2 | AD13: Unknown station - critical field, whole record held
A14: TC39 | B14: STG-0012 | C14: RUN-180 | D14: OPS_SYS | E14: PR0126-14AUG-1 | F14: 2026-08-14T08:00Z | G14: 2026-08-14T08:02Z | H14: UPDATE | I14: PR|0126|2026-08-14|1 | J14: LEG-26081401 | K14: RP-C4108 | L14: MNL | M14: 06:00 | N14: J | O14: PR | P14: 89 | R14: H-B2 | S14: STG-0006 | T14: H-B1 | U14: H-B1 | V14: =IF(T14="","INITIAL",IF(R14=T14,"NO_CHANGE",IF(AND(U14<>"",R14=U14),"REVERSAL","CHANGE"))) -> CHANGE | W14: APPLIED_PARTIAL | X14: Y | AB14: 1 | AC14: CURRENT | AD14: Only delay_code changed - non critical, applies without gating
A15: TC40 | B15: STG-0013 | C15: RUN-185 | D15: OPS_SYS | E15: PR0164-21AUG-1 | F15: 2026-08-21T01:00Z | G15: 2026-08-21T01:04Z | H15: UPDATE | I15: PR|0164|2026-08-21|1 | J15: LEG-26081424 | K15: RP-C4140 | L15: MNL | M15: 06:00 | N15: J | O15: PR | Q15: actual_registration | R15: H-E1 | V15: =IF(T15="","INITIAL",IF(R15=T15,"NO_CHANGE",IF(AND(U15<>"",R15=U15),"REVERSAL","CHANGE"))) -> INITIAL | W15: APPLIED | X15: Y | AB15: 1 | AC15: CURRENT | AD15: New tail auto provisioned - flight operations record applies, orders blocked
A16: TC41 | B16: STG-0014 | C16: RUN-190 | D16: OPS_SYS | E16: 5J0126-14AUG-1 | F16: 2026-08-23T01:00Z | G16: 2026-08-23T01:05Z | H16: UPDATE | I16: PR|0180|2026-08-23|1 | J16: LEG-26081425 | K16: RP-C4144 | L16: MNL | M16: 06:00 | N16: J | O16: 5J | Q16: operating_carrier | R16: H-F1 | V16: =IF(T16="","INITIAL",IF(R16=T16,"NO_CHANGE",IF(AND(U16<>"",R16=U16),"REVERSAL","CHANGE"))) -> INITIAL | W16: ERROR | X16: Y | Z16: CARRIER_NO_CONTRACT | AA16: operating_carrier | AB16: 1 | AC16: PENDING_UPDATE | AD16: Codeshare - operating carrier differs from marketing carrier, no fuel contract
A17: TC42 | B17: STG-0015 | C17: RUN-195 | D17: OPS_SYS | E17: PR9001-24AUG-1 | F17: 2026-08-24T01:00Z | G17: 2026-08-24T01:03Z | H17: INSERT | I17: PR|9001|2026-08-24|1 | J17: LEG-26081426 | K17: RP-C4146 | L17: MNL | M17: 09:00 | N17: P | O17: PR | Q17: service_type | R17: H-G1 | V17: =IF(T17="","INITIAL",IF(R17=T17,"NO_CHANGE",IF(AND(U17<>"",R17=U17),"REVERSAL","CHANGE"))) -> INITIAL | W17: APPLIED | X17: Y | AB17: 1 | AC17: CURRENT | AD17: Positioning flight - no payload, fuel plan still expected

Sheet AIRCRAFT_MASTER
A1: AIRCRAFT_MASTER - PROVISIONAL on auto creation, CONFIRMED by a person, COMPLETE when performance data is loaded
A2: registration | B2: record_status | C2: source_of_creation | D2: created_from_stg_id | E2: first_seen_utc | F2: aircraft_type | G2: operator_code | H2: icao_type_code | I2: aircraft_sub_type | J2: msn | K2: fleet_code | L2: ownership_type | M2: status | N2: dry_operating_weight | O2: max_takeoff_weight | P2: max_landing_weight | Q2: max_zero_fuel_weight | R2: max_usable_fuel_kg | S2: performance_factor_pct | T2: apu_burn_rate_kg_hr | U2: fqis_accuracy_pct | V2: etops_capability | W2: defuel_capable | X2: jettison_capable | Y2: confirmed_by | Z2: confirmed_utc | AA2: completed_by | AB2: completed_utc | AC2: completeness
A3: RP-C4108 | B3: COMPLETE | C3: FLEET_FEED | E3: 2024-03-01T00:00Z | F3: A321 | G3: PR | H3: A21N | I3: A321-271NX | J3: 10412 | K3: NB-NEO | L3: OWNED | M3: ACTIVE | N3: 50100 | O3: 97000 | P3: 79200 | Q3: 75600 | R3: 24500 | S3: 1.8 | T3: 105 | U3: 1.5 | V3: N | W3: Y | X3: N | Y3: M.SANTOS | Z3: 2024-03-02T00:00Z | AA3: M.SANTOS | AB3: 2024-03-05T00:00Z | AC3: =IF(N3="","PROVISIONAL_OR_CONFIRMED",IF(COUNT(N3:U3)=8,"COMPLETE","PARTIAL")) -> COMPLETE
A4: RP-C3505 | B4: COMPLETE | C4: FLEET_FEED | E4: 2023-06-01T00:00Z | F4: A350-900 | G4: PR | H4: A359 | I4: A350-941 | J4: 0421 | K4: WB-A350 | L4: LEASED | M4: ACTIVE | N4: 145200 | O4: 280000 | P4: 207000 | Q4: 195700 | R4: 110500 | S4: 2.4 | T4: 132 | U4: 1.2 | V4: Y | W4: Y | X4: Y | Y4: M.SANTOS | Z4: 2023-06-03T00:00Z | AA4: M.SANTOS | AB4: 2023-06-10T00:00Z | AC4: =IF(N4="","PROVISIONAL_OR_CONFIRMED",IF(COUNT(N4:U4)=8,"COMPLETE","PARTIAL")) -> COMPLETE
A5: RP-C4109 | B5: CONFIRMED | C5: AUTO_PROVISION | D5: STG-0004 | E5: 2026-08-16T02:06Z | F5: A321 | G5: PR | H5: A21N | I5: A321-271NX | J5: 10488 | K5: NB-NEO | L5: OWNED | M5: ACTIVE | V5: N | W5: Y | X5: N | Y5: M.SANTOS | Z5: 2026-08-16T08:30Z | AC5: =IF(N5="","PROVISIONAL_OR_CONFIRMED",IF(COUNT(N5:U5)=8,"COMPLETE","PARTIAL")) -> PROVISIONAL_OR_CONFIRMED
A6: RP-C4140 | B6: PROVISIONAL | C6: AUTO_PROVISION | D6: STG-0013 | E6: 2026-08-21T01:04Z | F6: A321 | G6: PR | AC6: =IF(N6="","PROVISIONAL_OR_CONFIRMED",IF(COUNT(N6:U6)=8,"COMPLETE","PARTIAL")) -> PROVISIONAL_OR_CONFIRMED
A7: RP-C4131 | B7: PROVISIONAL | C7: AUTO_PROVISION | D7: STG-0008 | E7: 2026-08-18T05:02Z | F7: A321 | G7: PR | AC7: =IF(N7="","PROVISIONAL_OR_CONFIRMED",IF(COUNT(N7:U7)=8,"COMPLETE","PARTIAL")) -> PROVISIONAL_OR_CONFIRMED

Sheet CARRIER_ARRANGEMENT
A1: CARRIER_ARRANGEMENT - buys_fuel and bears_cost are independent. Processing mode is DERIVED from the pair, not keyed. Most specific scope wins
A2: arrangement_id | B2: arrangement_type | C2: scope_level | D2: specificity_rank | E2: scope_key | F2: counterparty_carrier | G2: buys_fuel | H2: bears_cost | I2: fuel_processing_mode | J2: create_order_flag | K2: send_order_flag | L2: expect_ticket_flag | M2: expect_supplier_invoice_flag | N2: expect_counterparty_invoice_flag | O2: raise_recharge_flag | P2: aircraft_master_required | Q2: cost_allocation_basis | R2: counterparty_party | S2: contract_ref | T2: valid_from | U2: valid_to | V2: status | W2: note
A3: CAR-01 | B3: OWN_METAL | C3: GLOBAL | D3: 0 | E3: * | G3: SELF | H3: SELF | I3: =IF(AND(G3="SELF",H3="SELF"),"FULL",IF(AND(G3="SELF",H3="COUNTERPARTY"),"RECHARGE_OUT",IF(AND(G3="COUNTERPARTY",H3="SELF"),"RECHARGE_IN","NONE"))) -> FULL | J3: =IF(G3="SELF","Y","N") -> Y | K3: =IF(G3="SELF","Y","N") -> Y | L3: =IF(G3="SELF","Y","N") -> Y | M3: =IF(G3="SELF","Y","N") -> Y | N3: =IF(I3="RECHARGE_IN","Y","N") -> N | O3: =IF(I3="RECHARGE_OUT","Y","N") -> N | P3: Y | Q3: FLIGHT_LEG | T3: 2026-01-01 | V3: ACTIVE | W3: Default. Everything else is an exception to this
A4: CAR-02 | B4: CODESHARE_MARKETING | C4: CARRIER_PAIR | D4: 10 | E4: 5J|PR | F4: 5J | G4: COUNTERPARTY | H4: COUNTERPARTY | I4: =IF(AND(G4="SELF",H4="SELF"),"FULL",IF(AND(G4="SELF",H4="COUNTERPARTY"),"RECHARGE_OUT",IF(AND(G4="COUNTERPARTY",H4="SELF"),"RECHARGE_IN","NONE"))) -> NONE | J4: =IF(G4="SELF","Y","N") -> N | K4: =IF(G4="SELF","Y","N") -> N | L4: =IF(G4="SELF","Y","N") -> N | M4: =IF(G4="SELF","Y","N") -> N | N4: =IF(I4="RECHARGE_IN","Y","N") -> N | O4: =IF(I4="RECHARGE_OUT","Y","N") -> N | P4: N | Q4: NOT_APPLICABLE | S4: CS-5J-2026 | T4: 2026-01-01 | V4: ACTIVE | W4: Partner operates and fuels. No fuel processing at all
A5: CAR-03 | B5: CODESHARE_OPERATING | C5: CARRIER_PAIR | D5: 10 | E5: PR|KE | F5: KE | G5: SELF | H5: SELF | I5: =IF(AND(G5="SELF",H5="SELF"),"FULL",IF(AND(G5="SELF",H5="COUNTERPARTY"),"RECHARGE_OUT",IF(AND(G5="COUNTERPARTY",H5="SELF"),"RECHARGE_IN","NONE"))) -> FULL | J5: =IF(G5="SELF","Y","N") -> Y | K5: =IF(G5="SELF","Y","N") -> Y | L5: =IF(G5="SELF","Y","N") -> Y | M5: =IF(G5="SELF","Y","N") -> Y | N5: =IF(I5="RECHARGE_IN","Y","N") -> N | O5: =IF(I5="RECHARGE_OUT","Y","N") -> N | P5: Y | Q5: FLIGHT_LEG | S5: CS-KE-2026 | T5: 2026-01-01 | V5: ACTIVE | W5: We operate under a partner code. Identical to own metal for fuel
A6: CAR-04 | B6: WET_LEASE_IN | C6: REGISTRATION_PERIOD | D6: 50 | E6: XX-ABC | F6: XX | G6: SELF | H6: SELF | I6: =IF(AND(G6="SELF",H6="SELF"),"FULL",IF(AND(G6="SELF",H6="COUNTERPARTY"),"RECHARGE_OUT",IF(AND(G6="COUNTERPARTY",H6="SELF"),"RECHARGE_IN","NONE"))) -> FULL | J6: =IF(G6="SELF","Y","N") -> Y | K6: =IF(G6="SELF","Y","N") -> Y | L6: =IF(G6="SELF","Y","N") -> Y | M6: =IF(G6="SELF","Y","N") -> Y | N6: =IF(I6="RECHARGE_IN","Y","N") -> N | O6: =IF(I6="RECHARGE_OUT","Y","N") -> N | P6: N | Q6: FLIGHT_LEG | S6: ACMI-XX-26 | T6: 2026-06-01 | U6: 2026-12-31 | V6: ACTIVE | W6: Standard ACMI. We buy and bear fuel on a tail that never enters our fleet master
A7: CAR-05 | B7: WET_LEASE_IN | C7: REGISTRATION_PERIOD | D7: 50 | E7: XX-DEF | F7: XX | G7: SELF | H7: COUNTERPARTY | I7: =IF(AND(G7="SELF",H7="SELF"),"FULL",IF(AND(G7="SELF",H7="COUNTERPARTY"),"RECHARGE_OUT",IF(AND(G7="COUNTERPARTY",H7="SELF"),"RECHARGE_IN","NONE"))) -> RECHARGE_OUT | J7: =IF(G7="SELF","Y","N") -> Y | K7: =IF(G7="SELF","Y","N") -> Y | L7: =IF(G7="SELF","Y","N") -> Y | M7: =IF(G7="SELF","Y","N") -> Y | N7: =IF(I7="RECHARGE_IN","Y","N") -> N | O7: =IF(I7="RECHARGE_OUT","Y","N") -> Y | P7: N | Q7: RECHARGE | R7: XX | S7: ACMI-XX-27 | T7: 2026-06-01 | U7: 2026-12-31 | V7: ACTIVE | W7: We buy using our station contracts, lessor bears the cost. Recharge out
A8: CAR-06 | B8: WET_LEASE_IN | C8: REGISTRATION_PERIOD | D8: 50 | E8: XX-GHI | F8: XX | G8: COUNTERPARTY | H8: SELF | I8: =IF(AND(G8="SELF",H8="SELF"),"FULL",IF(AND(G8="SELF",H8="COUNTERPARTY"),"RECHARGE_OUT",IF(AND(G8="COUNTERPARTY",H8="SELF"),"RECHARGE_IN","NONE"))) -> RECHARGE_IN | J8: =IF(G8="SELF","Y","N") -> N | K8: =IF(G8="SELF","Y","N") -> N | L8: =IF(G8="SELF","Y","N") -> N | M8: =IF(G8="SELF","Y","N") -> N | N8: =IF(I8="RECHARGE_IN","Y","N") -> Y | O8: =IF(I8="RECHARGE_OUT","Y","N") -> N | P8: N | Q8: FLIGHT_LEG | R8: XX | S8: ACMI-XX-28 | T8: 2026-06-01 | U8: 2026-12-31 | V8: ACTIVE | W8: Lessor buys, we bear the cost. No supplier ticket; cost arrives as a counterparty invoice
A9: CAR-07 | B9: WET_LEASE_IN | C9: REGISTRATION_PERIOD | D9: 50 | E9: XX-JKL | F9: XX | G9: COUNTERPARTY | H9: COUNTERPARTY | I9: =IF(AND(G9="SELF",H9="SELF"),"FULL",IF(AND(G9="SELF",H9="COUNTERPARTY"),"RECHARGE_OUT",IF(AND(G9="COUNTERPARTY",H9="SELF"),"RECHARGE_IN","NONE"))) -> NONE | J9: =IF(G9="SELF","Y","N") -> N | K9: =IF(G9="SELF","Y","N") -> N | L9: =IF(G9="SELF","Y","N") -> N | M9: =IF(G9="SELF","Y","N") -> N | N9: =IF(I9="RECHARGE_IN","Y","N") -> N | O9: =IF(I9="RECHARGE_OUT","Y","N") -> N | P9: N | Q9: NOT_APPLICABLE | S9: ACMI-XX-29 | T9: 2026-06-01 | U9: 2026-12-31 | V9: ACTIVE | W9: Fuel inclusive wet lease. Bundled into the block hour rate. No fuel processing
A10: CAR-08 | B10: WET_LEASE_OUT | C10: REGISTRATION_PERIOD | D10: 50 | E10: RP-C4126 | F10: YY | G10: SELF | H10: COUNTERPARTY | I10: =IF(AND(G10="SELF",H10="SELF"),"FULL",IF(AND(G10="SELF",H10="COUNTERPARTY"),"RECHARGE_OUT",IF(AND(G10="COUNTERPARTY",H10="SELF"),"RECHARGE_IN","NONE"))) -> RECHARGE_OUT | J10: =IF(G10="SELF","Y","N") -> Y | K10: =IF(G10="SELF","Y","N") -> Y | L10: =IF(G10="SELF","Y","N") -> Y | M10: =IF(G10="SELF","Y","N") -> Y | N10: =IF(I10="RECHARGE_IN","Y","N") -> N | O10: =IF(I10="RECHARGE_OUT","Y","N") -> Y | P10: Y | Q10: RECHARGE | R10: YY | S10: WL-YY-26 | T10: 2026-05-01 | U10: 2026-10-31 | V10: ACTIVE | W10: Our metal out. We buy on our contracts and recharge the lessee
A11: CAR-09 | B11: WET_LEASE_OUT | C11: REGISTRATION_PERIOD | D11: 50 | E11: RP-C4128 | F11: YY | G11: COUNTERPARTY | H11: COUNTERPARTY | I11: =IF(AND(G11="SELF",H11="SELF"),"FULL",IF(AND(G11="SELF",H11="COUNTERPARTY"),"RECHARGE_OUT",IF(AND(G11="COUNTERPARTY",H11="SELF"),"RECHARGE_IN","NONE"))) -> NONE | J11: =IF(G11="SELF","Y","N") -> N | K11: =IF(G11="SELF","Y","N") -> N | L11: =IF(G11="SELF","Y","N") -> N | M11: =IF(G11="SELF","Y","N") -> N | N11: =IF(I11="RECHARGE_IN","Y","N") -> N | O11: =IF(I11="RECHARGE_OUT","Y","N") -> N | P11: Y | Q11: NOT_APPLICABLE | S11: WL-YY-27 | T11: 2026-05-01 | U11: 2026-10-31 | V11: ACTIVE | W11: Lessee buys and bears. We do no fuel processing on our own aircraft
A12: CAR-10 | B12: DAMP_LEASE_IN | C12: REGISTRATION_PERIOD | D12: 50 | E12: XX-MNO | F12: XX | G12: SELF | H12: SELF | I12: =IF(AND(G12="SELF",H12="SELF"),"FULL",IF(AND(G12="SELF",H12="COUNTERPARTY"),"RECHARGE_OUT",IF(AND(G12="COUNTERPARTY",H12="SELF"),"RECHARGE_IN","NONE"))) -> FULL | J12: =IF(G12="SELF","Y","N") -> Y | K12: =IF(G12="SELF","Y","N") -> Y | L12: =IF(G12="SELF","Y","N") -> Y | M12: =IF(G12="SELF","Y","N") -> Y | N12: =IF(I12="RECHARGE_IN","Y","N") -> N | O12: =IF(I12="RECHARGE_OUT","Y","N") -> N | P12: N | Q12: FLIGHT_LEG | S12: DL-XX-26 | T12: 2026-07-01 | U12: 2026-11-30 | V12: ACTIVE | W12: Aircraft and cockpit crew leased, cabin crew ours. Fuel treated as ACMI
A13: CAR-11 | B13: DRY_LEASE_IN | C13: GLOBAL | D13: 0 | E13: * | G13: SELF | H13: SELF | I13: =IF(AND(G13="SELF",H13="SELF"),"FULL",IF(AND(G13="SELF",H13="COUNTERPARTY"),"RECHARGE_OUT",IF(AND(G13="COUNTERPARTY",H13="SELF"),"RECHARGE_IN","NONE"))) -> FULL | J13: =IF(G13="SELF","Y","N") -> Y | K13: =IF(G13="SELF","Y","N") -> Y | L13: =IF(G13="SELF","Y","N") -> Y | M13: =IF(G13="SELF","Y","N") -> Y | N13: =IF(I13="RECHARGE_IN","Y","N") -> N | O13: =IF(I13="RECHARGE_OUT","Y","N") -> N | P13: Y | Q13: FLIGHT_LEG | T13: 2026-01-01 | V13: ACTIVE | W13: Deliberate non exception. Aircraft is on our AOC and register. Do NOT create an arrangement row
A14: CAR-12 | B14: CHARTER | C14: FLIGHT_NUMBER_RANGE | D14: 30 | E14: PR|8000-8999 | G14: SELF | H14: SELF | I14: =IF(AND(G14="SELF",H14="SELF"),"FULL",IF(AND(G14="SELF",H14="COUNTERPARTY"),"RECHARGE_OUT",IF(AND(G14="COUNTERPARTY",H14="SELF"),"RECHARGE_IN","NONE"))) -> FULL | J14: =IF(G14="SELF","Y","N") -> Y | K14: =IF(G14="SELF","Y","N") -> Y | L14: =IF(G14="SELF","Y","N") -> Y | M14: =IF(G14="SELF","Y","N") -> Y | N14: =IF(I14="RECHARGE_IN","Y","N") -> N | O14: =IF(I14="RECHARGE_OUT","Y","N") -> N | P14: Y | Q14: FLIGHT_LEG | T14: 2026-01-01 | V14: ACTIVE | W14: Fuel absorbed in the charter price
A15: CAR-13 | B15: CHARTER | C15: FLIGHT_NUMBER | D15: 40 | E15: PR|8412 | G15: SELF | H15: COUNTERPARTY | I15: =IF(AND(G15="SELF",H15="SELF"),"FULL",IF(AND(G15="SELF",H15="COUNTERPARTY"),"RECHARGE_OUT",IF(AND(G15="COUNTERPARTY",H15="SELF"),"RECHARGE_IN","NONE"))) -> RECHARGE_OUT | J15: =IF(G15="SELF","Y","N") -> Y | K15: =IF(G15="SELF","Y","N") -> Y | L15: =IF(G15="SELF","Y","N") -> Y | M15: =IF(G15="SELF","Y","N") -> Y | N15: =IF(I15="RECHARGE_IN","Y","N") -> N | O15: =IF(I15="RECHARGE_OUT","Y","N") -> Y | P15: Y | Q15: RECHARGE | R15: CHARTERER | S15: CHT-8412 | T15: 2026-08-01 | U15: 2026-08-31 | V15: ACTIVE | W15: Charter terms pass fuel to the customer at cost plus handling
A16: CAR-14 | B16: CAPACITY_PURCHASE | C16: CARRIER_PAIR | D16: 10 | E16: 2P|PR | F16: 2P | G16: SELF | H16: SELF | I16: =IF(AND(G16="SELF",H16="SELF"),"FULL",IF(AND(G16="SELF",H16="COUNTERPARTY"),"RECHARGE_OUT",IF(AND(G16="COUNTERPARTY",H16="SELF"),"RECHARGE_IN","NONE"))) -> FULL | J16: =IF(G16="SELF","Y","N") -> Y | K16: =IF(G16="SELF","Y","N") -> Y | L16: =IF(G16="SELF","Y","N") -> Y | M16: =IF(G16="SELF","Y","N") -> Y | N16: =IF(I16="RECHARGE_IN","Y","N") -> N | O16: =IF(I16="RECHARGE_OUT","Y","N") -> N | P16: N | Q16: FLIGHT_LEG | S16: CPA-2P-26 | T16: 2026-01-01 | V16: ACTIVE | W16: Partner metal and crew, our flight number, fuel often ours. Contract dependent
A17: CAR-15 | B17: SUBCHARTER | C17: SPECIFIC_LEG | D17: 60 | E17: LEG-26081430 | F17: ZZ | G17: COUNTERPARTY | H17: COUNTERPARTY | I17: =IF(AND(G17="SELF",H17="SELF"),"FULL",IF(AND(G17="SELF",H17="COUNTERPARTY"),"RECHARGE_OUT",IF(AND(G17="COUNTERPARTY",H17="SELF"),"RECHARGE_IN","NONE"))) -> NONE | J17: =IF(G17="SELF","Y","N") -> N | K17: =IF(G17="SELF","Y","N") -> N | L17: =IF(G17="SELF","Y","N") -> N | M17: =IF(G17="SELF","Y","N") -> N | N17: =IF(I17="RECHARGE_IN","Y","N") -> N | O17: =IF(I17="RECHARGE_OUT","Y","N") -> N | P17: N | Q17: NOT_APPLICABLE | S17: SUB-0091 | T17: 2026-08-25 | U17: 2026-08-25 | V17: ACTIVE | W17: One off ad hoc charter in. Leg level override; standing rows cannot cover this
A18: CAR-16 | B18: OWN_METAL | C18: CARRIER_PAIR_STATION | D18: 20 | E18: PR|PR|CEB | G18: SELF | H18: SELF | I18: =IF(AND(G18="SELF",H18="SELF"),"FULL",IF(AND(G18="SELF",H18="COUNTERPARTY"),"RECHARGE_OUT",IF(AND(G18="COUNTERPARTY",H18="SELF"),"RECHARGE_IN","NONE"))) -> FULL | J18: =IF(G18="SELF","Y","N") -> Y | K18: =IF(G18="SELF","Y","N") -> Y | L18: =IF(G18="SELF","Y","N") -> Y | M18: =IF(G18="SELF","Y","N") -> Y | N18: =IF(I18="RECHARGE_IN","Y","N") -> N | O18: =IF(I18="RECHARGE_OUT","Y","N") -> N | P18: Y | Q18: FLIGHT_LEG | T18: 2026-01-01 | V18: ACTIVE | W18: Station override: order created but not transmitted, no contract supplier at CEB
A21: SCOPE RESOLUTION - highest specificity_rank whose scope, counterparty and date window all match. Registration outranks flight number: if leased metal is flying, lease terms govern whatever the flight number
A22: specificity_rank | B22: scope_level | C22: scope_key format | D22: Used for
A23: 0 | B23: GLOBAL | C23: * | D23: Own metal default and dry lease
A24: 10 | B24: CARRIER_PAIR | C24: operating|marketing | D24: Codeshare, capacity purchase
A25: 20 | B25: CARRIER_PAIR_STATION | C25: operating|marketing|station | D25: Station specific overrides
A26: 30 | B26: FLIGHT_NUMBER_RANGE | C26: carrier|from-to | D26: Charter number blocks
A27: 40 | B27: FLIGHT_NUMBER | C27: carrier|number | D27: Named charter series
A28: 50 | B28: REGISTRATION_PERIOD | C28: registration + valid_from/to | D28: Wet and damp lease in or out
A29: 60 | B29: SPECIFIC_LEG | C29: flight_leg_id | D29: Subcharter and genuine one offs
A32: DERIVED PROCESSING MODE - buys_fuel determines whether an order and ticket exist. bears_cost determines allocation and recharge direction
A33: buys_fuel | B33: bears_cost | C33: fuel_processing_mode | D33: Order | E33: Ticket | F33: Supplier invoice | G33: Counterparty invoice | H33: Recharge document
A34: SELF | B34: SELF | C34: FULL | D34: Yes | E34: Yes | F34: Yes | G34: No | H34: None
A35: SELF | B35: COUNTERPARTY | C35: RECHARGE_OUT | D35: Yes | E35: Yes | F35: Yes | G35: No | H35: Outbound to counterparty
A36: COUNTERPARTY | B36: SELF | C36: RECHARGE_IN | D36: No | E36: No | F36: No | G36: Yes | H36: Inbound from counterparty
A37: COUNTERPARTY | B37: COUNTERPARTY | C37: NONE | D37: No | E37: No | F37: No | G37: No | H37: None

Sheet Mandatory Criteria
A1: MANDATORY IMPLEMENTATION CRITERIA - prerequisites, not design options. A source unable to meet one of these is an impediment to escalate
A2: Criterion | B2: Area | C2: Requirement | D2: Rationale | E2: Workaround Exists | F2: Status
A3: MC-01 | B3: Inbound interface | C3: Every inbound record carries a source change timestamp, distinct from receipt time | D3: Without a source side ordering token, out of order arrivals silently regress the target. Receipt time cannot substitute: queues reorder, retries replay, and a record received later may legitimately be older | E3: NONE | F3: MANDATORY
A4: MC-01a | B4: Inbound interface | C4: In a snapshot run, each record carries that record's own last change time, not the snapshot generation time | D4: If every snapshot record is stamped with the run time, all snapshot records appear newer than all delta records. Stale detection fails and a stale snapshot overwrites fresher intraday data | E4: NONE | F4: MANDATORY
A5: MC-02 | B5: Inbound interface | C5: Every inbound record carries a stable source record key | D5: Identity must resolve independently of content validation, so a failing record still knows which leg it concerns | E5: NONE | F5: MANDATORY
A6: MC-03 | B6: Inbound interface | C6: The feed pattern is declared and does not change without notice | D6: Apply logic differs fundamentally between delta and snapshot | E6: NONE | F6: MANDATORY
A7: MC-04 | B7: Inbound interface | C7: Where a full snapshot is used, the rolling window is declared | D7: Absence outside a declared window cannot be interpreted as cancellation | E7: NONE | F7: MANDATORY
A8: MC-05 | B8: Inbound interface | C8: Cancellations are transmitted as explicit full records on both streams | D8: Removes absence inference entirely. The single change that most simplifies snapshot handling | E8: NONE | F8: MANDATORY
A9: MC-06 | B9: Inbound interface | C9: Delta stream records carry a sequence number permitting gap detection | D9: Delta failure is otherwise silent and permanent. Applies to the delta stream only; snapshot runs are self baselining | E9: NONE | F9: MANDATORY
A10: MC-06a | B10: Inbound interface | C10: Critical field changes are transmitted as explicit full records, never inferred | D10: Ensures a gating change is never missed between snapshot runs | E10: NONE | F10: MANDATORY
A11: MC-07 | B11: Inbound interface | C11: All timestamps are UTC with an explicit offset | D11: Local time is ambiguous across DST boundaries | E11: NONE | F11: MANDATORY
A12: MC-08 | B12: Snapshot control | C12: Completeness check on every snapshot run before absences are evaluated | D12: Defence in depth. Relaxed to advisory because MC-05 makes cancellation explicit, so absence never implies cancellation | E12: MC-05 covers | F12: ADVISORY
A13: MC-09 | B13: Snapshot control | C13: Absence inside the declared window raises a divergence exception, never an automatic cancellation | D13: Absence has too many benign explanations once cancellation is explicit | E13: NONE | F13: MANDATORY
... A21: MC-15 | B21: AI | C21: AI never triggers a posting or repost unattended | D21: Automated action against a finance system on AI output is an unacceptable risk class | E21: NONE | F21: MANDATORY

Sheet IF_FD_FUEL_PLAN_STG
A1: IF_FD_FUEL_PLAN_STG - dispatch sends the CURRENT plan only. Version gaps are flagged and applied, never held: the missing versions will never arrive
A2: TC_ID | B2: stg_id | C2: if_run_id | D2: source_system | E2: source_record_key | F2: source_change_utc | G2: received_utc | H2: resolved_business_key | I2: resolved_flight_leg_id | J2: m_ofp_reference | K2: m_plan_version | L2: m_registration | M2: m_block_fuel | N2: m_fuel_on_board | O2: m_change_reason | P2: payload_hash | Q2: prior_applied_version | R2: version_gap | S2: versions_skipped | T2: record_status | U2: is_latest_for_key | V2: superseded_by_stg_id | W2: first_error_code | X2: error_field | Y2: blocking_ref | Z2: attempt_count | AA2: note
A3: TC68 | B3: PSG-0001 | C3: RUN-201 | D3: LIDO | E3: PR126-14AUG-1-V1 | F3: 2026-08-14T02:14Z | G3: 2026-08-14T02:16Z | H3: LEG-26081401|1 | I3: LEG-26081401 | J3: PR126/14AUG/01 | K3: 1 | L3: RP-C4108 | M3: 11251 | N3: 2100 | P3: P-A1 | R3: =IF(Q3="","N/A",IF(K3-Q3>1,"Y","N")) -> N/A | S3: =IF(R3="Y",K3-Q3-1,0) -> 0 | T3: APPLIED | U3: Y | Z3: 1 | AA3: First plan for the leg. No prior version, no gap possible
A4: TC69 | B4: PSG-0002 | C4: RUN-205 | D4: LIDO | E4: PR128-14AUG-1-V2 | F4: 2026-08-14T08:05Z | G4: 2026-08-14T08:07Z | H4: LEG-26081402|2 | I4: LEG-26081402 | J4: PR128/14AUG/02 | K4: 2 | L4: RP-C4110 | M4: 11535 | N4: 2050 | O4: PAYLOAD_INCREASE | P4: P-B2 | Q4: 1 | R4: =IF(Q4="","N/A",IF(K4-Q4>1,"Y","N")) -> N | S4: =IF(R4="Y",K4-Q4-1,0) -> 0 | T4: APPLIED | U4: Y | Z4: 1 | AA4: Consecutive version. Normal apply
A5: TC70 | B5: PSG-0003 | C5: RUN-212 | D5: LIDO | E5: PR130-14AUG-1-V5 | F5: 2026-08-14T13:22Z | G5: 2026-08-14T13:24Z | H5: LEG-26081403|5 | I5: LEG-26081403 | J5: PR130/14AUG/05 | K5: 5 | L5: RP-C4112 | M5: 12287 | N5: 11540 | O5: ATC_REROUTE | P5: P-C5 | Q5: 2 | R5: =IF(Q5="","N/A",IF(K5-Q5>1,"Y","N")) -> Y | S5: =IF(R5="Y",K5-Q5-1,0) -> 2 | T5: APPLIED_WITH_GAP | U5: Y | W5: PLAN_VERSION_GAP | X5: plan_version | Z5: 1 | AA5: Latest only feed. v3 and v4 never transmitted and never will be. Applied and flagged
A6: TC71 | B6: PSG-0004 | C6: RUN-218 | D6: LIDO | E6: PR130-14AUG-1-V5 | F6: 2026-08-14T13:22Z | G6: 2026-08-14T14:00Z | H6: LEG-26081403|5 | I6: LEG-26081403 | J6: PR130/14AUG/05 | K6: 5 | L6: RP-C4112 | M6: 12287 | N6: 11540 | O6: ATC_REROUTE | P6: P-C5 | Q6: 5 | R6: =IF(Q6="","N/A",IF(K6-Q6>1,"Y","N")) -> N | S6: =IF(R6="Y",K6-Q6-1,0) -> 0 | T6: IGNORED_DUPLICATE | U6: N | Z6: 0 | AA6: Same version resent. Already applied, no action
A7: TC72 | B7: PSG-0005 | C7: RUN-222 | D7: LIDO | E7: PR190-25AUG-1-V1 | F7: 2026-08-25T01:00Z | G7: 2026-08-25T01:02Z | H7: LEG-26082501|1 | J7: PR190/25AUG/01 | K7: 1 | L7: RP-C4150 | M7: 11251 | N7: 2100 | P7: P-D1 | R7: =IF(Q7="","N/A",IF(K7-Q7>1,"Y","N")) -> N/A | S7: =IF(R7="Y",K7-Q7-1,0) -> 0 | T7: HELD_AWAITING_LEG | U7: Y | W7: LEG_NOT_FOUND | X7: flight_leg_id | Z7: 1 | AA7: Plan ahead of the flight operations feed. Not an error; resolves itself when the leg lands
A8: TC73 | B8: PSG-0006 | C8: RUN-226 | D8: LIDO | E8: PR132-14AUG-1-V2 | F8: 2026-08-15T02:30Z | G8: 2026-08-15T02:32Z | H8: LEG-26081404|2 | I8: LEG-26081404 | J8: PR132/14AUG/02 | K8: 2 | L8: RP-C4109 | M8: 11346 | N8: 4900 | O8: TAIL_SWAP | P8: P-E2 | Q8: 1 | R8: =IF(Q8="","N/A",IF(K8-Q8>1,"Y","N")) -> N | S8: =IF(R8="Y",K8-Q8-1,0) -> 0 | T8: HELD_STALE_LEG | U8: Y | W8: LEG_STALE_PENDING_TAIL | X8: registration | Y8: STG-0004 | Z8: 1 | AA8: Plan carries the new tail; the leg still holds the old one. Blocking staging record named
A9: TC74 | B9: PSG-0007 | C9: RUN-230 | D9: LIDO | E9: PR130-14AUG-1-V4 | F9: 2026-08-14T12:50Z | G9: 2026-08-14T15:10Z | H9: LEG-26081403|4 | I9: LEG-26081403 | J9: PR130/14AUG/04 | K9: 4 | L9: RP-C4112 | M9: 12100 | N9: 11540 | O9: ATC_REROUTE | P9: P-C4 | Q9: 5 | R9: =IF(Q9="","N/A",IF(K9-Q9>1,"Y","N")) -> N | S9: =IF(R9="Y",K9-Q9-1,0) -> 0 | T9: IGNORED_STALE | U9: N | Z9: 0 | AA9: Lower version arriving after a higher one is applied. Never regress
A10: TC75 | B10: PSG-0008 | C10: RUN-234 | D10: LIDO | E10: PR152-18AUG-1-V1 | F10: 2026-08-18T02:14Z | G10: 2026-08-18T02:16Z | H10: LEG-26081417|1 | I10: LEG-26081417 | J10: PR152/18AUG/01 | K10: 1 | L10: RP-C4128 | M10: 99999 | N10: 2100 | P10: P-F1 | R10: =IF(Q10="","N/A",IF(K10-Q10>1,"Y","N")) -> N/A | S10: =IF(R10="Y",K10-Q10-1,0) -> 0 | T10: ERROR | U10: Y | W10: BLOCK_FUEL_MISMATCH | X10: block_fuel | Z10: 2 | AA10: block_fuel does not equal the sum of components. Genuine validation failure
A11: TC76 | B11: PSG-0009 | C11: RUN-240 | D11: LIDO | E11: PR154-18AUG-1-V3 | F11: 2026-08-18T09:40Z | G11: 2026-08-18T09:42Z | H11: LEG-26081418|3 | I11: LEG-26081418 | J11: PR154/18AUG/03 | K11: 3 | L11: RP-C4130 | M11: 11400 | N11: 2100 | O11: ALTERNATE_CHANGE | P11: P-G3 | Q11: 1 | R11: =IF(Q11="","N/A",IF(K11-Q11>1,"Y","N")) -> Y | S11: =IF(R11="Y",K11-Q11-1,0) -> 1 | T11: APPLIED_WITH_GAP | U11: Y | W11: PLAN_VERSION_GAP | X11: plan_version | Z11: 1 | AA11: Uplift occurred while v2 was active. Ticket cannot bind to a version never received
A14: RECORD STATUS - HELD is not ERROR. Held records resolve themselves when the blocking condition clears and belong in a separate queue
A15: record_status | B15: Actionable | C15: Queue | D15: Meaning
A16: APPLIED | B16: No | C16: None | D16: Plan version inserted as a new row
A17: APPLIED_WITH_GAP | B17: No | C17: Health metric | D17: Applied, but one or more versions were never transmitted
A18: HELD_AWAITING_LEG | B18: No, until aged | C18: Held queue | D18: Plan arrived before its flight leg. Retries automatically
A19: HELD_STALE_LEG | B19: No, until aged | C19: Held queue | D19: Leg has an unapplied critical change. Fix the leg first
A20: ERROR | B20: Yes | C20: Error worklist | D20: Genuine validation failure in the record itself
A21: SUPERSEDED_ERROR | B21: No | C21: History | D21: Failed, but a newer record for the key exists
A22: IGNORED_DUPLICATE | B22: No | C22: None | D22: This version is already applied
A23: IGNORED_STALE | B23: No | C23: None | D23: Lower version arriving after a higher one is applied

Sheet AIRCRAFT_TYPE_MASTER
A1: AIRCRAFT_TYPE_MASTER - the aircraft. AIRCRAFT_TYPE is a parameter scope level, so it is an FK, never free text on the tail
A2: aircraft_type_id | B2: record_status | C2: icao_type_code | D2: iata_type_code | E2: manufacturer_type | F2: manufacturer | G2: family | H2: body_type | I2: fleet_code | J2: engine_type | K2: default_max_usable_fuel_kg | L2: default_performance_factor_pct | M2: default_apu_burn_kg_hr | N2: default_fqis_accuracy_pct | O2: etops_certified_minutes | P2: jettison_capable | Q2: defuel_capable | R2: apu_reporting_available | S2: apu_minutes_default_source | T2: created_from_stg_id | U2: confirmed_by | V2: confirmed_utc | W2: note
A3: ATM-001 | B3: CONFIRMED | C3: A21N | D3: 32Q | E3: A321-271NX | F3: Airbus | G3: A320 | H3: NB | I3: A321NEO | J3: PW1133G | K3: 24500 | L3: 1.8 | M3: 105 | N3: 1.5 | O3: 0 | P3: N | Q3: Y | R3: Y | S3: ACARS_EVENT | U3: M.SANTOS | V3: 2024-03-02T00:00Z | W3: AMI includes an APU report. Automated capture available
A4: ATM-002 | B4: CONFIRMED | C4: A21N | D4: 32Q | E4: A321-253NX | F4: Airbus | G4: A320 | H4: NB | I4: A321NEO | J4: LEAP-1A33 | K4: 24500 | L4: 2.1 | M4: 105 | N4: 1.5 | O4: 0 | P4: N | Q4: Y | R4: Y | S4: ACARS_EVENT | U4: M.SANTOS | V4: 2024-03-02T00:00Z | W4: Same ICAO code, different engine, different burn
A5: ATM-003 | B5: CONFIRMED | C5: A320 | D5: 320 | E5: A320-214 | F5: Airbus | G5: A320 | H5: NB | I5: A320CEO | J5: CFM56-5B4 | K5: 18730 | L5: 3.2 | M5: 100 | N5: 1.6 | O5: 0 | P5: N | Q5: Y | R5: N | S5: GROUND_TIME_EST | U5: M.SANTOS | V5: 2023-01-10T00:00Z | W5: Older fleet. AMI has no APU report. Estimation is the default, not the exception
A6: ATM-004 | B6: CONFIRMED | C6: A359 | D6: 359 | E6: A350-941 | F6: Airbus | G6: A350 | H6: WB | I6: A350 | J6: Trent XWB-84 | K6: 110500 | L6: 2.4 | M6: 132 | N6: 1.2 | O6: 180 | P6: Y | Q6: Y | R6: Y | S6: ACARS_EVENT | U6: M.SANTOS | V6: 2023-06-03T00:00Z | W6: Jettison capable, ETOPS 180
A7: ATM-005 | B7: PROVISIONAL | R7: UNKNOWN | S7: MANUAL | T7: STG-0021 | W7: Auto provisioned. APU capability unknown until confirmed

Sheet AIRCRAFT_CONFIG_MASTER
A1: AIRCRAFT_CONFIG_MASTER - how WE configured it. Hidden entirely when AIRCRAFT_CONFIG_GRANULARITY is NONE
A2: config_id | B2: aircraft_type_id | C2: internal_config_code | D2: config_name | E2: seats_first | F2: seats_business | G2: seats_premium | H2: seats_economy | I2: total_seats | J2: dry_operating_weight | K2: max_zero_fuel_weight | L2: max_takeoff_weight | M2: max_landing_weight | N2: galley_fit | O2: crew_complement | P2: cabin_layout_ref | Q2: status | R2: note
A3: CFG-001 | B3: ATM-001 | C3: 321N-J | D3: A321neo domestic | E3: 0 | F3: 12 | G3: 0 | H3: 187 | I3: =SUM(E3:H3) -> 199 | J3: 50100 | K3: 75600 | L3: 97000 | M3: 79200 | N3: STD-DOM | O3: 6 | P3: LOPA-321N-D | Q3: ACTIVE | R3: High density domestic fit
A4: CFG-002 | B4: ATM-001 | C4: 321N-I | D4: A321neo regional international | E4: 0 | F4: 12 | G4: 24 | H4: 132 | I4: =SUM(E4:H4) -> 168 | J4: 51400 | K4: 75600 | L4: 97000 | M4: 79200 | N4: FULL-INT | O4: 7 | P4: LOPA-321N-I | Q4: ACTIVE | R4: Same type and same ICAO code, 1300 kg heavier DOW
A5: CFG-003 | B5: ATM-003 | C5: 320-J | D5: A320 domestic | E5: 0 | F5: 12 | G5: 0 | H5: 156 | I5: =SUM(E5:H5) -> 168 | J5: 42600 | K5: 62800 | L5: 78000 | M5: 66000 | N5: STD-DOM | O5: 5 | P5: LOPA-320-D | Q5: ACTIVE
A6: CFG-004 | B6: ATM-004 | C6: 350-I | D6: A350 long haul | E6: 0 | F6: 30 | G6: 24 | H6: 241 | I6: =SUM(E6:H6) -> 295 | J6: 145200 | K6: 195700 | L6: 280000 | M6: 207000 | N6: FULL-LH | O6: 12 | P6: LOPA-350-LH | Q6: ACTIVE

Sheet AIRCRAFT_TYPE_ALIAS
A1: AIRCRAFT_TYPE_ALIAS - inbound codes vary by airline and by feed. This is what removes per customer code changes
A2: alias_id | B2: aircraft_type_id | C2: source_system | D2: code_scheme | E2: alias_code | F2: is_primary | G2: valid_from | H2: status | I2: note
A3: ALS-001 | B3: ATM-001 | C3: OPS_SYS | D3: IATA | E3: 32Q | F3: Y | G3: 2026-01-01 | H3: ACTIVE | I3: Schedule feed sends the IATA code
A4: ALS-002 | B4: ATM-001 | C4: DISPATCH | D4: ICAO | E4: A21N | F4: N | G4: 2026-01-01 | H4: ACTIVE | I4: Dispatch sends ICAO
A5: ALS-003 | B5: ATM-001 | C5: DISPATCH | D5: MANUFACTURER | E5: A321-271NX | F5: N | G5: 2026-01-01 | H5: ACTIVE | I5: OFP header carries the exact variant
A6: ALS-004 | B6: ATM-001 | C6: SAP | D6: INTERNAL | E6: A321NEO | F6: N | G6: 2026-01-01 | H6: ACTIVE | I6: SAP material or asset grouping
A7: ALS-005 | B7: ATM-002 | C7: OPS_SYS | D7: IATA | E7: 32Q | F7: N | G7: 2026-01-01 | H7: ACTIVE | I7: IATA code is AMBIGUOUS - shared with ATM-001. Never resolve on IATA alone
A8: ALS-006 | B8: ATM-002 | C8: DISPATCH | D8: MANUFACTURER | E8: A321-253NX | F8: Y | G8: 2026-01-01 | H8: ACTIVE | I8: Only the manufacturer code separates the two engine variants
A9: ALS-007 | B9: ATM-004 | C9: OPS_SYS | D9: IATA | E9: 359 | F9: Y | G9: 2026-01-01 | H9: ACTIVE
A10: ALS-008 | B10: ATM-004 | C10: DISPATCH | D10: ICAO | E10: A359 | F10: N | G10: 2026-01-01 | H10: ACTIVE
A11: ALS-009 | B11: ATM-003 | C11: OPS_SYS | D11: FREE_TEXT | E11: A320 CEO | F11: Y | G11: 2026-01-01 | H11: ACTIVE | I11: Legacy feed sends free text with a space
A14: PRODUCT CONFIGURABILITY - normalised where it protects correctness, flat looking wherever the user touches it
A15: Concern | B15: Mechanism | C15: Effect
A16: Setup burden | B16: Auto provision unknown types as PROVISIONAL | C16: Nothing configured up front; rows appear and are enriched later
A17: Airlines without multiple cabin fits | B17: Parameter AIRCRAFT_CONFIG_GRANULARITY = NONE | C17: Config table invisible; DOW sits on the tail
A18: Airlines with multiple cabin fits | B18: Parameter AIRCRAFT_CONFIG_GRANULARITY = BY_CONFIG | C18: Full structure available
A19: Different inbound code schemes | B19: AIRCRAFT_TYPE_ALIAS | C19: One customer sends 32Q, another A21N, another A321NEO. All resolve
A20: Different vocabularies on screen | B20: Parameter PRIMARY_TYPE_CODE_SCHEME | C20: Each customer sees their own code. UI and reporting only
A21: Type looks like an attribute | B21: Read through on the tail screen | C21: Four codes shown inline; storage stays normalised

Sheet FUEL_BURN_ACTUAL
A1: FUEL_BURN_ACTUAL - burn is DERIVED from four gauge points, never measured. One primary row per leg; lower priority sources retained
A2: TC_ID | B2: burn_id | C2: flight_leg_id | D2: registration | E2: burn_source | F2: source_priority | G2: is_primary | H2: fob_offblocks_kg | I2: fob_takeoff_kg | J2: fob_touchdown_kg | K2: fob_onblocks_kg | L2: block_burn_kg | M2: trip_burn_kg | N2: taxi_out_burn_kg | O2: taxi_in_burn_kg | P2: apu_burn_kg | Q2: engine_burn_kg | R2: planned_trip_burn_kg | S2: burn_variance_kg | T2: burn_variance_pct | U2: burn_confidence | V2: data_completeness | W2: reported_utc | X2: note
A3: TC83 | B3: BRN-0001 | C3: LEG-26081401 | D3: RP-C4108 | E3: ACARS | F3: 1 | G3: Y | H3: 11251 | I3: 11071 | J3: 2790 | K3: 2610 | L3: =IF(OR(H3="",K3=""),"",H3-K3) -> 8641 | M3: =IF(OR(I3="",J3=""),"",I3-J3) -> 8281 | N3: =IF(OR(H3="",I3=""),"",H3-I3) -> 180 | O3: =IF(OR(J3="",K3=""),"",J3-K3) -> 180 | P3: 148 | Q3: =IF(L3="","",L3-P3) -> 8493 | R3: 8420 | S3: =IF(M3="","",M3-R3) -> -139 | T3: =IF(OR(M3="",R3=0),"",S3/R3) -> -0.016508314 | U3: HIGH | V3: COMPLETE | W3: 2026-08-14T09:55Z | X3: Full four point capture from ACARS
A4: TC83 | B4: BRN-0002 | C4: LEG-26081401 | D4: RP-C4108 | E4: FQIS_MANUAL | F4: 2 | G4: N | H4: 11251 | I4: 11050 | J4: 2800 | K4: 2600 | L4: =IF(OR(H4="",K4=""),"",H4-K4) -> 8651 | M4: =IF(OR(I4="",J4=""),"",I4-J4) -> 8250 | N4: =IF(OR(H4="",I4=""),"",H4-I4) -> 201 | O4: =IF(OR(J4="",K4=""),"",J4-K4) -> 200 | P4: 148 | Q4: =IF(L4="","",L4-P4) -> 8503 | R4: 8420 | S4: =IF(M4="","",M4-R4) -> -170 | T4: =IF(OR(M4="",R4=0),"",S4/R4) -> -0.020190024 | U4: MEDIUM | V4: COMPLETE | W4: 2026-08-14T10:10Z | X4: Crew reported. Retained as secondary, not primary
A5: TC84 | B5: BRN-0003 | C5: LEG-26081405 | D5: RP-C3505 | E5: ACARS | F5: 1 | G5: Y | H5: 105392 | I5: 104792 | J5: 9800 | K5: 9200 | L5: =IF(OR(H5="",K5=""),"",H5-K5) -> 96192 | M5: =IF(OR(I5="",J5=""),"",I5-J5) -> 94992 | N5: =IF(OR(H5="",I5=""),"",H5-I5) -> 600 | O5: =IF(OR(J5="",K5=""),"",J5-K5) -> 600 | P5: 396 | Q5: =IF(L5="","",L5-P5) -> 95796 | R5: 96400 | S5: =IF(M5="","",M5-R5) -> -1408 | T5: =IF(OR(M5="",R5=0),"",S5/R5) -> -0.014605809 | U5: HIGH | V5: COMPLETE | W5: 2026-08-15T01:38Z | X5: Long haul, widebody
A6: TC85 | B6: BRN-0004 | C6: LEG-26081402 | D6: RP-C4110 | E6: FQIS_MANUAL | F6: 2 | G6: Y | H6: 11535 | K6: 2790 | L6: =IF(OR(H6="",K6=""),"",H6-K6) -> 8745 | M6: =IF(OR(I6="",J6=""),"",I6-J6) | N6: =IF(OR(H6="",I6=""),"",H6-I6) | O6: =IF(OR(J6="",K6=""),"",J6-K6) | P6: 152 | Q6: =IF(L6="","",L6-P6) -> 8593 | R6: 8690 | S6: =IF(M6="","",M6-R6) | T6: =IF(OR(M6="",R6=0),"",S6/R6) | U6: MEDIUM | V6: PARTIAL | W6: 2026-08-14T14:50Z | X6: Only block figures reported. Trip and taxi split not derivable
A7: TC86 | B7: BRN-0005 | C7: LEG-26081403 | D7: RP-C4112 | E7: DERIVED_CHAIN | F7: 3 | G7: Y | H7: 12287 | K7: 2960 | L7: =IF(OR(H7="",K7=""),"",H7-K7) -> 9327 | M7: =IF(OR(I7="",J7=""),"",I7-J7) | N7: =IF(OR(H7="",I7=""),"",H7-I7) | O7: =IF(OR(J7="",K7=""),"",J7-K7) | P7: 210 | Q7: =IF(L7="","",L7-P7) -> 9117 | R7: 9140 | S7: =IF(M7="","",M7-R7) | T7: =IF(OR(M7="",R7=0),"",S7/R7) | U7: LOW | V7: PARTIAL | W7: 2026-08-14T18:50Z | X7: No gauge reading. Derived from uplift chain across the rotation
A8: TC87 | B8: BRN-0006 | C8: LEG-26081411 | D8: RP-C4120 | E8: ESTIMATED | F8: 4 | G8: Y | L8: =IF(OR(H8="",K8=""),"",H8-K8) | M8: =IF(OR(I8="",J8=""),"",I8-J8) | N8: =IF(OR(H8="",I8=""),"",H8-I8) | O8: =IF(OR(J8="",K8=""),"",J8-K8) | P8: 145 | Q8: =IF(L8="","",L8-P8) | R8: 8420 | S8: =IF(M8="","",M8-R8) | T8: =IF(OR(M8="",R8=0),"",S8/R8) | U8: LOW | V8: ESTIMATED | W8: 2026-08-16T14:50Z | X8: Nothing reported. Plan multiplied by historical factor. Excluded from variance statistics
A9: TC88 | B9: BRN-0007 | C9: LEG-26081409 | D9: RP-C3509 | E9: ACARS | F9: 1 | G9: Y | H9: 105392 | I9: 104792 | J9: 74300 | K9: 73900 | L9: =IF(OR(H9="",K9=""),"",H9-K9) -> 31492 | M9: =IF(OR(I9="",J9=""),"",I9-J9) -> 30492 | N9: =IF(OR(H9="",I9=""),"",H9-I9) -> 600 | O9: =IF(OR(J9="",K9=""),"",J9-K9) -> 400 | P9: 320 | Q9: =IF(L9="","",L9-P9) -> 31172 | R9: 96400 | S9: =IF(M9="","",M9-R9) -> -65908 | T9: =IF(OR(M9="",R9=0),"",S9/R9) -> -0.68369295 | U9: HIGH | V9: COMPLETE | W9: 2026-08-15T15:10Z | X9: Air return with jettison. Burn excludes the jettisoned quantity
A12: DERIVATION - burn is the difference between gauge readings. APU burn is never metered; it is minutes multiplied by rate
A13: Quantity | B13: Formula | C13: Note
A14: Block burn | B14: FOB off-blocks minus FOB on-blocks | C14: Total consumed gate to gate. Includes APU
A15: Trip burn | B15: FOB takeoff minus FOB touchdown | C15: Compared against planned trip fuel
A16: Taxi out burn | B16: FOB off-blocks minus FOB takeoff | C16: Includes APU running before departure
A17: Taxi in burn | B17: FOB touchdown minus FOB on-blocks | C17: Includes APU after arrival
A18: APU burn | B18: Running minutes divided by 60, times burn rate | C18: Derived from APU_USAGE. No meter exists
A19: Engine burn | B19: Block burn minus APU burn | C19: The separation that fuel efficiency reporting needs

Sheet APU_USAGE
A1: APU_USAGE - ONE ROW PER CYCLE, not per phase. Full UTC timestamps so overnight cycles compute. APU fuel is never metered
A2: TC_ID | B2: apu_cycle_id | C2: flight_leg_id | D2: registration | E2: turn_id | F2: cycle_seq | G2: usage_phase | H2: apu_start_utc | I2: apu_stop_utc | J2: cycle_open_flag | K2: running_minutes_derived | L2: running_minutes_reported | M2: running_minutes | N2: minutes_source | O2: burn_rate_kg_hr | P2: apu_burn_kg | Q2: stand_id | R2: stand_type | S2: gpu_available | T2: gpu_source | U2: gpu_used | V2: avoidable_minutes | W2: avoidable_burn_kg | X2: avoidable_confidence | Y2: note
A3: TC89 | B3: APU-1001 | C3: LEG-26081401 | D3: RP-C4108 | E3: TRN-4108-01 | F3: 1 | G3: POST_ARRIVAL | H3: 46247.944 | I3: 46247.962 | J3: N | K3: =IF(OR(H3="",I3=""),"",IF((I3-H3)<0,"INVALID",ROUND((I3-H3)*1440,0))) -> 25 | M3: =IF(J3="Y","OPEN",IF(K3="INVALID","REJECTED",IF(K3<>"",K3,L3))) -> 25 | N3: ACARS_EVENT | O3: 105 | P3: =IF(OR(M3="OPEN",M3="REJECTED",M3=""),"",ROUND(M3/60*O3,1)) -> 43.8 | Q3: S12 | R3: CONTACT | S3: Y | T3: HANDLER | U3: Y | V3: =IF(OR(S3="",U3="",NOT(ISNUMBER(M3))),"",IF(AND(S3="Y",U3="N"),M3,0)) -> 0 | W3: =IF(OR(V3="",NOT(ISNUMBER(V3))),"",ROUND(V3/60*O3,1)) -> 0 | X3: =IF(T3="NONE","NOT_COMPUTED",IF(T3="HANDLER","HIGH",IF(T3="STAND_TYPE","MEDIUM","LOW"))) -> HIGH | Y3: Prior leg arrival. GPU connected promptly
A4: TC89 | B4: APU-1002 | C4: LEG-26081401 | D4: RP-C4108 | E4: TRN-4108-01 | F4: 2 | G4: PRE_DEPARTURE | H4: 46248.217 | I4: 46248.23 | J4: N | K4: =IF(OR(H4="",I4=""),"",IF((I4-H4)<0,"INVALID",ROUND((I4-H4)*1440,0))) -> 19 | M4: =IF(J4="Y","OPEN",IF(K4="INVALID","REJECTED",IF(K4<>"",K4,L4))) -> 19 | N4: ACARS_EVENT | O4: 105 | P4: =IF(OR(M4="OPEN",M4="REJECTED",M4=""),"",ROUND(M4/60*O4,1)) -> 33.3 | Q4: S12 | R4: CONTACT | S4: Y | T4: HANDLER | U4: N | V4: =IF(OR(S4="",U4="",NOT(ISNUMBER(M4))),"",IF(AND(S4="Y",U4="N"),M4,0)) -> 19 | W4: =IF(OR(V4="",NOT(ISNUMBER(V4))),"",ROUND(V4/60*O4,1)) -> 33.3 | X4: =IF(T4="NONE","NOT_COMPUTED",IF(T4="HANDLER","HIGH",IF(T4="STAND_TYPE","MEDIUM","LOW"))) -> HIGH | Y4: First pre departure cycle. GPU available, unused
A5: TC89 | B5: APU-1003 | C5: LEG-26081401 | D5: RP-C4108 | E5: TRN-4108-01 | F5: 3 | G5: PRE_DEPARTURE | H5: 46248.242 | I5: 46248.253 | J5: N | K5: =IF(OR(H5="",I5=""),"",IF((I5-H5)<0,"INVALID",ROUND((I5-H5)*1440,0))) -> 16 | M5: =IF(J5="Y","OPEN",IF(K5="INVALID","REJECTED",IF(K5<>"",K5,L5))) -> 16 | N5: ACARS_EVENT | O5: 105 | P5: =IF(OR(M5="OPEN",M5="REJECTED",M5=""),"",ROUND(M5/60*O5,1)) -> 28 | Q5: S12 | R5: CONTACT | S5: Y | T5: HANDLER | U5: N | V5: =IF(OR(S5="",U5="",NOT(ISNUMBER(M5))),"",IF(AND(S5="Y",U5="N"),M5,0)) -> 16 | W5: =IF(OR(V5="",NOT(ISNUMBER(V5))),"",ROUND(V5/60*O5,1)) -> 28 | X5: =IF(T5="NONE","NOT_COMPUTED",IF(T5="HANDLER","HIGH",IF(T5="STAND_TYPE","MEDIUM","LOW"))) -> HIGH | Y5: Second cycle same phase. One row per phase would have lost this
A6: TC90 | B6: APU-1004 | C6: LEG-26081405 | D6: RP-C3505 | E6: TRN-3505-01 | F6: 1 | G6: PRE_DEPARTURE | H6: 46248.486 | I6: 46248.56 | J6: N | K6: =IF(OR(H6="",I6=""),"",IF((I6-H6)<0,"INVALID",ROUND((I6-H6)*1440,0))) -> 106 | M6: =IF(J6="Y","OPEN",IF(K6="INVALID","REJECTED",IF(K6<>"",K6,L6))) -> 106 | N6: ACARS_EVENT | O6: 132 | P6: =IF(OR(M6="OPEN",M6="REJECTED",M6=""),"",ROUND(M6/60*O6,1)) -> 233.2 | Q6: R41 | R6: REMOTE | S6: N | T6: STAND_TYPE | U6: N | V6: =IF(OR(S6="",U6="",NOT(ISNUMBER(M6))),"",IF(AND(S6="Y",U6="N"),M6,0)) -> 0 | W6: =IF(OR(V6="",NOT(ISNUMBER(V6))),"",ROUND(V6/60*O6,1)) -> 0 | X6: =IF(T6="NONE","NOT_COMPUTED",IF(T6="HANDLER","HIGH",IF(T6="STAND_TYPE","MEDIUM","LOW"))) -> MEDIUM | Y6: Remote stand. GPU absence inferred from stand type, not reported
A7: TC91 | B7: APU-1005 | C7: LEG-26081403 | D7: RP-C4112 | E7: TRN-4112-01 | F7: 1 | G7: PRE_DEPARTURE | J7: N | K7: =IF(OR(H7="",I7=""),"",IF((I7-H7)<0,"INVALID",ROUND((I7-H7)*1440,0))) | L7: 120 | M7: =IF(J7="Y","OPEN",IF(K7="INVALID","REJECTED",IF(K7<>"",K7,L7))) -> 120 | N7: GROUND_TIME_EST | O7: 105 | P7: =IF(OR(M7="OPEN",M7="REJECTED",M7=""),"",ROUND(M7/60*O7,1)) -> 210 | T7: NONE | V7: =IF(OR(S7="",U7="",NOT(ISNUMBER(M7))),"",IF(AND(S7="Y",U7="N"),M7,0)) | W7: =IF(OR(V7="",NOT(ISNUMBER(V7))),"",ROUND(V7/60*O7,1)) | X7: =IF(T7="NONE","NOT_COMPUTED",IF(T7="HANDLER","HIGH",IF(T7="STAND_TYPE","MEDIUM","LOW"))) -> NOT_COMPUTED | Y7: No APU events and no GPU data. Avoidable is NULL, not zero
A8: TC92 | B8: APU-1006 | C8: LEG-26081402 | D8: RP-C4110 | E8: TRN-4110-01 | F8: 1 | G8: OVERNIGHT | H8: 46248.927 | I8: 46249.238 | J8: N | K8: =IF(OR(H8="",I8=""),"",IF((I8-H8)<0,"INVALID",ROUND((I8-H8)*1440,0))) -> 447 | M8: =IF(J8="Y","OPEN",IF(K8="INVALID","REJECTED",IF(K8<>"",K8,L8))) -> 447 | N8: ACARS_EVENT | O8: 105 | P8: =IF(OR(M8="OPEN",M8="REJECTED",M8=""),"",ROUND(M8/60*O8,1)) -> 782.3 | Q8: S08 | R8: CONTACT | S8: Y | T8: HANDLER | U8: N | V8: =IF(OR(S8="",U8="",NOT(ISNUMBER(M8))),"",IF(AND(S8="Y",U8="N"),M8,0)) -> 447 | W8: =IF(OR(V8="",NOT(ISNUMBER(V8))),"",ROUND(V8/60*O8,1)) -> 782.3 | X8: =IF(T8="NONE","NOT_COMPUTED",IF(T8="HANDLER","HIGH",IF(T8="STAND_TYPE","MEDIUM","LOW"))) -> HIGH | Y8: Crosses midnight. Bare times would have computed 87 minutes instead of 447
A9: TC98 | B9: APU-1007 | C9: LEG-26081412 | D9: RP-C4122 | E9: TRN-4122-01 | F9: 1 | G9: PRE_DEPARTURE | H9: 46250.543 | J9: Y | K9: =IF(OR(H9="",I9=""),"",IF((I9-H9)<0,"INVALID",ROUND((I9-H9)*1440,0))) | M9: =IF(J9="Y","OPEN",IF(K9="INVALID","REJECTED",IF(K9<>"",K9,L9))) -> OPEN | N9: ACARS_EVENT | O9: 105 | P9: =IF(OR(M9="OPEN",M9="REJECTED",M9=""),"",ROUND(M9/60*O9,1)) | Q9: S15 | R9: CONTACT | S9: Y | T9: HANDLER | V9: =IF(OR(S9="",U9="",NOT(ISNUMBER(M9))),"",IF(AND(S9="Y",U9="N"),M9,0)) | W9: =IF(OR(V9="",NOT(ISNUMBER(V9))),"",ROUND(V9/60*O9,1)) | X9: =IF(T9="NONE","NOT_COMPUTED",IF(T9="HANDLER","HIGH",IF(T9="STAND_TYPE","MEDIUM","LOW"))) -> HIGH | Y9: Open cycle, no stop event received. Capped and flagged, never computed
A10: TC99 | B10: APU-1008 | C10: LEG-26081417 | D10: RP-C4128 | E10: TRN-4128-01 | F10: 1 | G10: PRE_DEPARTURE | H10: 46252.222 | I10: 46252.218 | J10: N | K10: =IF(OR(H10="",I10=""),"",IF((I10-H10)<0,"INVALID",ROUND((I10-H10)*1440,0))) -> INVALID | M10: =IF(J10="Y","OPEN",IF(K10="INVALID","REJECTED",IF(K10<>"",K10,L10))) -> REJECTED | N10: ACARS_EVENT | O10: 105 | P10: =IF(OR(M10="OPEN",M10="REJECTED",M10=""),"",ROUND(M10/60*O10,1)) | Q10: S03 | R10: CONTACT | S10: Y | T10: HANDLER | U10: N | V10: =IF(OR(S10="",U10="",NOT(ISNUMBER(M10))),"",IF(AND(S10="Y",U10="N"),M10,0)) | W10: =IF(OR(V10="",NOT(ISNUMBER(V10))),"",ROUND(V10/60*O10,1)) | X10: =IF(T10="NONE","NOT_COMPUTED",IF(T10="HANDLER","HIGH",IF(T10="STAND_TYPE","MEDIUM","LOW"))) -> HIGH | Y10: Stop before start. Clock skew or event reordering. Rejected, never negative
